Workbook

Sheet Funciones
A1: ELEMENTO DE ESTUDIO | B1: ID | C1: VERBO | D1: OBJETO | E1: ESTÁNDAR | F1: UNIDAD | G1: FUNCIÓN | H1: TIPO DE FUNCIÓN | I1: ID ELEMENTO (TAG) | J1: FUENTE | K1: OBSERVACIÓN | L1: DENOMINACIÓN EN TAXONOMÍA | M1: TAGS CUBIERTOS | N1: N.º ELEMENTOS CUBIERTOS | O1: CATEGORÍA RCM | P1: TIPO P/S | Q1: VISIBILIDAD | R1: MÉTODO DE VERIFICACIÓN | S1: BASE DEL ESTÁNDAR | T1: ID ANTERIORES (EXCEL ORIGINAL) | U1: DEFINICIÓN DEL ELEMENTO (punto de partida de la función) | V1: FUENTE DE LA DEFINICIÓN | W1: FUNCIÓN ANTERIOR (tu versión)
A2: Vehículo de pasajeros | B2: F-MET-001 | C2: Transportar | D2: pasajeros | E2: hasta 300 | F2: por coche | G2: =TRIM(CONCATENATE(C2," ",D2," ",E2," ",F2)) -> Transportar pasajeros hasta 300 por coche | H2: Significativa – Operación | I2: MET-MRO-VPA001 | J2: Wikipedia | K2: Confirmar con ficha CAF/MAN. | L2: Vehículo de pasajeros | M2: |MET-MRO-VPA001| | N2: 1 | O2: Operación | P2: Primaria | Q2: Evidente | R2: Ficha | S2: CONTEXTO OPERACIONAL | T2: Nueva (dato medible del estudio)
A3: Sistema de puertas de viajeros | B3: F-MET-004 | C3: Bloquear | D3: la tracción | E3: con 0 | F3: arranques con puerta abierta | G3: =TRIM(CONCATENATE(C3," ",D3," ",E3," ",F3)) -> Bloquear la tracción con 0 arranques con puerta abierta | H3: Significativa – Seguridad/Ambiental | I3: MET-MRO-VPA001-PUE | L3: Sistema de Puertas de Viajeros | M3: |MET-MRO-VPA001-PUE| | N3: 1 | O3: Seguridad | P3: Secundaria | Q3: Oculta | R3: Comprobación de seguridad (PM-2012 pág. 20) | S3: NORMA | T3: F-MET-007
A4: Sistema de puertas de viajeros | B4: F-MET-005 | C4: Permitir | D4: el intercambio de pasajeros | E4: con 24 | F4: puertas operativas | G4: =TRIM(CONCATENATE(C4," ",D4," ",E4," ",F4)) -> Permitir el intercambio de pasajeros con 24 puertas operativas | H4: Significativa – Operación | I4: MET-MRO-VPA001-PUE | J4: Nombre del equipo en SAP (IW43_2021-28092026.xlsx) | K4: 24 puertas por unidad (PV01–PV24 en SAP). | L4: Sistema de Puertas de Viajeros | M4: |MET-MRO-VPA001-PUE| | N4: 1 | O4: Operación | P4: Primaria | Q4: Evidente | R4: Protocolo C.E8.92.203 | S4: DISEÑO | T4: Nueva (dato medible del estudio)
A5: Sistema de frenos | B5: F-MET-006 | C5: Frenar | D5: el tren | E5: en una distancia máxima de 30 | F5: m | G5: =TRIM(CONCATENATE(C5," ",D5," ",E5," ",F5)) -> Frenar el tren en una distancia máxima de 30 m | H5: Significativa – Seguridad/Ambiental | I5: MET-MRO-VPA001-FRE | J5: Funciones validadas del proyecto (HTML de funciones) | L5: Sistema de Frenos | M5: |MET-MRO-VPA001-FRE| | N5: 1 | O5: Seguridad | P5: Primaria | Q5: Evidente | R5: Protocolo C.E8.92.302 | S5: FABRICANTE | T5: F-MET-011
A6: Sistema de frenos | B6: F-MET-007 | C6: Detener | D6: el tren | E6: en una distancia máxima de 30 | F6: m | G6: =TRIM(CONCATENATE(C6," ",D6," ",E6," ",F6)) -> Detener el tren en una distancia máxima de 30 m | H6: Significativa – Seguridad/Ambiental | I6: MET-MRO-VPA001-FRE | J6: Funciones validadas del proyecto (HTML de funciones) | L6: Sistema de Frenos | M6: |MET-MRO-VPA001-FRE| | N6: 1 | O6: Seguridad | P6: Primaria | Q6: Evidente | R6: Protocolo C.E8.92.302 | S6: FABRICANTE | T6: F-MET-012
A7: Sistema de frenos | B7: F-MET-008 | C7: Inmovilizar | D7: el tren | E7: con carga de 203 | F7: t en pendiente de 3 % | G7: =TRIM(CONCATENATE(C7," ",D7," ",E7," ",F7)) -> Inmovilizar el tren con carga de 203 t en pendiente de 3 % | H7: Significativa – Seguridad/Ambiental | I7: MET-MRO-VPA001-FRE | K7: Masa estimada 203,4 t: tara 118 t + 1.220 pasajeros × 70 kg. Fuerza de retención en pendiente de 3 %: 59,9 kN (65,8 kN con margen de 10 %). Falta: confirmar la pendiente máxima de la red con el Metro. | L7: Sistema de Frenos | M7: |MET-MRO-VPA001-FRE| | N7: 1 | O7: Seguridad | P7: Secundaria | Q7: Oculta | R7: Prueba de estacionamiento | S7: FABRICANTE | T7: F-MET-013
A8: Sistema de tracción | B8: F-MET-018 | C8: Alcanzar | D8: una velocidad máxima | E8: entre 78 y 80 | F8: km/h | G8: =TRIM(CONCATENATE(C8," ",D8," ",E8," ",F8)) -> Alcanzar una velocidad máxima entre 78 y 80 km/h | H8: Significativa – Operación | I8: MET-MRO-VPA001-TRA | J8: Wikipedia | L8: Sistema de Traccion | M8: |MET-MRO-VPA001-TRA| | N8: 1 | O8: Operación | P8: Primaria | Q8: Evidente | R8: Protocolo C.E8.92.301 | S8: CONTEXTO OPERACIONAL | T8: F-MET-024
A9: Sistema de tracción | B9: F-MET-019 | C9: Entregar | D9: el par de tracción | E9: en arranque entre _____ y _____ | F9: N·m | G9: =TRIM(CONCATENATE(C9," ",D9," ",E9," ",F9)) -> Entregar el par de tracción en arranque entre _____ y _____ N·m | H9: Significativa – Operación | I9: MET-MRO-VPA001-TRA | K9: Falta: aceleración de arranque (ficha). Referencia típica de metro 0,9–1,1 m/s² (no validada). | Revisión 27/10: la función pasó de aceleración (0,9–1,1 m/s²) a par de tracción en N·m; los valores de par quedan por confirmar con el fabricante. | L9: Sistema de Traccion | M9: |MET-MRO-VPA001-TRA| | N9: 1 | O9: Operación | P9: Secundaria | Q9: Evidente | R9: Protocolo C.E8.92.301; lectura del par en el registro del convertidor | S9: FABRICANTE | T9: Nueva (dato medible del estudio)
A10: Sistema de aire | B10: F-MET-022 | C10: Mantener | D10: la presión | E10: del depósito principal entre 8,5 y 10 | F10: bar | G10: =TRIM(CONCATENATE(C10," ",D10," ",E10," ",F10)) -> Mantener la presión del depósito principal entre 8,5 y 10 bar | H10: Significativa – Seguridad/Ambiental | I10: MET-MRO-VPA001-AIR | K10: Falta: presiones de conexión/desconexión. Referencia típica de metro: entre 8,5 y 10 bar (no validada). | L10: Sistema de Aire | M10: |MET-MRO-VPA001-AIR| | N10: 1 | O10: Operación | P10: Primaria | Q10: Evidente | R10: Manómetro doble B15 | S10: FABRICANTE | T10: F-MET-028
A11: Sistema de aire | B11: F-MET-023 | C11: Contener | D11: el aire | E11: del circuito principal con caída máxima de 0,2 | F11: bar en 5 min | G11: =TRIM(CONCATENATE(C11," ",D11," ",E11," ",F11)) -> Contener el aire del circuito principal con caída máxima de 0,2 bar en 5 min | H11: Significativa – Mantenimiento | I11: MET-MRO-VPA001-AIR | K11: Falta: caída admisible (ficha). Referencia típica ≤ 0,2 bar en 5 min. | L11: Sistema de Aire | M11: |MET-MRO-VPA001-AIR| | N11: 1 | O11: Contención | P11: Secundaria | Q11: Evidente | R11: Prueba de estanqueidad con compresores parados | S11: FABRICANTE | T11: Nueva (dato medible del estudio)
A12: Secador de aire (×2) · B0700 | B12: F-MET-026 | C12: Secar | D12: el aire comprimido | E12: con punto de rocío máximo de +3 | F12: °C | G12: =TRIM(CONCATENATE(C12," ",D12," ",E12," ",F12)) -> Secar el aire comprimido con punto de rocío máximo de +3 °C | H12: Significativa – Operación | I12: MET-MAU-B0700-AIR-SAI01 | J12: ISO 8573-1 | K12: Clase 4 ISO 8573-1 como referencia; confirmar con el fabricante. | L12: Secador DE Aire | M12: |MET-MAU-B0700-AIR-SAI01|MET-MAU-B0700-AIR-SCO01| | N12: 2 | O12: Protección | P12: Primaria | Q12: Oculta | R12: Purga diaria de calderines sin agua | S12: NORMA | T12: F-MET-057, F-MET-058
A13: Bomba hidráulica (×4) · B0700 | B13: F-MET-027 | C13: Suministrar | D13: caudal de aceite | E13: [ESTÁNDAR POR CONFIRMAR] | G13: =TRIM(CONCATENATE(C13," ",D13," ",E13," ",F13)) -> Suministrar caudal de aceite [ESTÁNDAR POR CONFIRMAR] | H13: Significativa – Operación | I13: MET-MAU-B0700-AVA-BEM01 | K13: Falta: caudal nominal (placa de la bomba). | L13: Bomba Avance Embolos Axiales | M13: |MET-MAU-B0700-AVA-BEM01|MET-MAU-B0700-AVA-BOB01|MET-MAU-B0700-AVA-BOP01|MET-MAU-B0700-AVA-BOP02| | N13: 4 | O13: Operación | P13: Primaria | Q13: Evidente | R13: Caudalímetro / tiempos de ciclo | S13: FABRICANTE | T13: F-MET-059, F-MET-061, F-MET-062, F-MET-063
A14: Bomba hidráulica (×4) · B0700 | B14: F-MET-028 | C14: Generar | D14: presión hidráulica | E14: [ESTÁNDAR POR CONFIRMAR] | G14: =TRIM(CONCATENATE(C14," ",D14," ",E14," ",F14)) -> Generar presión hidráulica [ESTÁNDAR POR CONFIRMAR] | H14: Significativa – Operación | I14: MET-MAU-B0700-AVA-BEM01 | K14: Falta: presión de trabajo (placa / esquema hidráulico). | L14: Bomba Avance Embolos Axiales | M14: |MET-MAU-B0700-AVA-BEM01|MET-MAU-B0700-AVA-BOB01|MET-MAU-B0700-AVA-BOP01|MET-MAU-B0700-AVA-BOP02| | N14: 4 | O14: Operación | P14: Secundaria | Q14: Evidente | R14: Manómetro | S14: FABRICANTE | T14: Nueva (dato medible del estudio)
A15: Bomba Manual · B0700 | B15: F-MET-029 | C15: Suministrar | D15: caudal de emergencia | E15: [ESTÁNDAR POR CONFIRMAR] | G15: =TRIM(CONCATENATE(C15," ",D15," ",E15," ",F15)) -> Suministrar caudal de emergencia [ESTÁNDAR POR CONFIRMAR] | H15: Significativa – Seguridad/Ambiental | I15: MET-MAU-B0700-AVA-BMA01 | K15: Falta: el caudal y la presión de emergencia. | L15: Bomba Manual | M15: |MET-MAU-B0700-AVA-BMA01| | N15: 1 | O15: Protección | P15: Secundaria | Q15: Oculta | R15: Prueba funcional de la bomba manual | S15: FABRICANTE | T15: F-MET-060
A16: Compresor A/C Hidráulico · B0700 | B16: F-MET-031 | C16: Suministrar | D16: caudal de aire | E16: [ESTÁNDAR POR CONFIRMAR] | G16: =TRIM(CONCATENATE(C16," ",D16," ",E16," ",F16)) -> Suministrar caudal de aire [ESTÁNDAR POR CONFIRMAR] | H16: Significativa – Operación | I16: MET-MAU-B0700-AVA-COH01 | K16: Falta: el caudal y la presión nominales del compresor (ficha del compresor). | L16: Compresor A/C Hidráulico | M16: |MET-MAU-B0700-AVA-COH01| | N16: 1 | O16: Operación | P16: Primaria | Q16: Evidente | R16: Tiempo de llenado de calderines | S16: FABRICANTE | T16: F-MET-064
A17: Compresor A/C Hidráulico · B0700 | B17: F-MET-032 | C17: Comprimir | D17: el refrigerante | E17: [ESTÁNDAR POR CONFIRMAR] | G17: =TRIM(CONCATENATE(C17," ",D17," ",E17," ",F17)) -> Comprimir el refrigerante [ESTÁNDAR POR CONFIRMAR] | H17: Significativa – Operación | I17: MET-MAU-B0700-AVA-COH01 | K17: Falta: presiones de alta/baja. | L17: Compresor A/C Hidráulico | M17: |MET-MAU-B0700-AVA-COH01| | N17: 1 | O17: Operación | P17: Primaria | Q17: Evidente | R17: Manómetros de servicio | S17: FABRICANTE | T17: Nueva (dato medible del estudio)
A18: Intercambiador Aire-aceite · B0700 | B18: F-MET-033 | C18: Mantener | D18: la temperatura del aceite hidráulico | E18: por debajo de 80 | F18: °C | G18: =TRIM(CONCATENATE(C18," ",D18," ",E18," ",F18)) -> Mantener la temperatura del aceite hidráulico por debajo de 80 °C | H18: Significativa – Operación | I18: MET-MAU-B0700-AVA-INA01 | K18: Falta: temperatura máxima del aceite hidráulico. | L18: Intercambiador Aire-aceite | M18: |MET-MAU-B0700-AVA-INA01| | N18: 1 | O18: Protección | P18: Primaria | Q18: Evidente | R18: Termómetro | S18: FABRICANTE | T18: F-MET-065
A19: Bogie (×2) · B0700 | B19: F-MET-041 | C19: Soportar | D19: la carga vertical | E19: de 18 | F19: t por bogie | G19: =TRIM(CONCATENATE(C19," ",D19," ",E19," ",F19)) -> Soportar la carga vertical de 18 t por bogie | H19: Significativa – Seguridad/Ambiental | I19: MET-MAU-B0700-BOI-BMO01 | K19: Falta: carga por bogie. | L19: Bogie Motriz | M19: |MET-MAU-B0700-BOI-BMO01|MET-MAU-B0700-BOI-BPO01| | N19: 2 | O19: Soporte | P19: Primaria | Q19: Oculta | R19: Pesaje | S19: FABRICANTE | T19: F-MET-074, F-MET-076
A20: Bogie (×2) · B0700 | B20: F-MET-042 | C20: Impedir | D20: el remonte de pestaña | E20: con cota qR ≥ 6,5 | F20: mm | G20: =TRIM(CONCATENATE(C20," ",D20," ",E20," ",F20)) -> Impedir el remonte de pestaña con cota qR ≥ 6,5 mm | H20: Significativa – Seguridad/Ambiental | I20: MET-MAU-B0700-BOI-BMO01 | J20: TSI LOC&PAS / OTIF UTP LOC&PAS, tablas 1 y 2 | K20: qR: cota de la cara activa de la pestaña (galga de perfil). | L20: Bogie Motriz | M20: |MET-MAU-B0700-BOI-BMO01|MET-MAU-B0700-BOI-BPO01| | N20: 2 | O20: Seguridad | P20: Secundaria | Q20: Oculta | R20: Galga de perfil | S20: NORMA | T20: F-MET-075, F-MET-077
A21: Cabina (×3) · B0700 | B21: F-MET-044 | C21: Impedir | D21: la entrada de agua | E21: con 0 | F21: filtraciones | G21: =TRIM(CONCATENATE(C21," ",D21," ",E21," ",F21)) -> Impedir la entrada de agua con 0 filtraciones | H21: Significativa – Operación | I21: MET-MAU-B0700-CAJ-CABI01 | J21: Manual de Mantenimiento DR1227 Plasser & Theurer DIC-40 (WS6761) – p.81 | K21: Valor del manual DR1227 de la DIC-40 (máquina Plasser equivalente); validar con el manual de esta máquina. | L21: Cabina Trabajo | M21: |MET-MAU-B0700-CAJ-CABI01|MET-MAU-B0700-CAJ-CBI01|MET-MAU-B0700-CAJ-CDE01| | N21: 3 | O21: Protección | P21: Primaria | Q21: Evidente | R21: Control visual anual de juntas de goma | S21: FABRICANTE | T21: F-MET-078, F-MET-079, F-MET-080
A22: Caja Baterias · B0700 | B22: F-MET-047 | C22: Suministrar | D22: la corriente de arranque | E22: con tensión mínima de 19,2 | F22: V | G22: =TRIM(CONCATENATE(C22," ",D22," ",E22," ",F22)) -> Suministrar la corriente de arranque con tensión mínima de 19,2 V | H22: Significativa – Operación | I22: MET-MAU-B0700-ELE-CAJB01 | K22: Falta: tensión y capacidad (placa). | L22: Caja Baterias | M22: |MET-MAU-B0700-ELE-CAJB01| | N22: 1 | O22: Operación | P22: Primaria | Q22: Evidente | R22: Voltímetro | S22: FABRICANTE | T22: F-MET-082
A23: Caja Baterias · B0700 | B23: F-MET-901 | C23: Almacenar | D23: energía eléctrica | E23: con tensión mínima de 19,2 | F23: V | G23: =TRIM(CONCATENATE(C23," ",D23," ",E23," ",F23)) -> Almacenar energía eléctrica con tensión mínima de 19,2 V | H23: Significativa – Operación | I23: MET-MAU-B0700-ELE-CAJB01 | K23: Función agregada en la revisión 27/10. Mismo estándar de tensión que la función existente del activo. | L23: Caja Baterias | M23: |MET-MAU-B0700-ELE-CAJB01| | N23: 1 | O23: Operación | P23: Primaria | Q23: Evidente | R23: Voltímetro | S23: FABRICANTE | T23: Nueva (solicitada en la revisión) | W23: Función nueva: no existía en la versión anterior
A24: Sistema Frenos · B0700 | B24: F-MET-050 | C24: Presurizar | D24: los cilindros de freno | E24: entre 3,7 y 3,9 | F24: bar | G24: =TRIM(CONCATENATE(C24," ",D24," ",E24," ",F24)) -> Presurizar los cilindros de freno entre 3,7 y 3,9 bar | H24: Significativa – Seguridad/Ambiental | I24: MET-MAU-B0700-FRN | J24: UIC 540 | K24: Presión de freno a fondo del freno automático UIC 540 (3,8 ± 0,1 bar). | L24: Sistema Frenos | M24: |MET-MAU-B0700-FRN| | N24: 1 | O24: Seguridad | P24: Secundaria | Q24: Evidente | R24: Manómetro | S24: NORMA | T24: Nueva (dato medible del estudio)
A25: Bomba Lubricación · B0700 | B25: F-MET-055 | C25: Lubricar | D25: los puntos de engrase | E25: a un máximo de 15 | F25: bar | G25: =TRIM(CONCATENATE(C25," ",D25," ",E25," ",F25)) -> Lubricar los puntos de engrase a un máximo de 15 bar | H25: Significativa – Económica | I25: MET-MAU-B0700-LUB-BLU01 | J25: Manual de Mantenimiento DR1227 Plasser & Theurer DIC-40 (WS6761) – p.38 | K25: Criterio del manual Plasser (DR1227). | L25: Bomba Lubricación | M25: |MET-MAU-B0700-LUB-BLU01| | N25: 1 | O25: Protección | P25: Primaria | Q25: Oculta | R25: Manómetro de la bomba | S25: FABRICANTE | T25: F-MET-086
A26: Caja Twindisc AM365 Acoplamientos · B0700 | B26: F-MET-061 | C26: Transmitir | D26: el par motriz | E26: hasta 2.300 | F26: N.m | G26: =TRIM(CONCATENATE(C26," ",D26," ",E26," ",F26)) -> Transmitir el par motriz hasta 2.300 N.m | H26: Significativa – Operación | I26: MET-MAU-B0700-TRC-CTW01 | K26: hasta 2.300 N.m | L26: Caja Twindisc AM365 Acoplamientos | M26: |MET-MAU-B0700-TRC-CTW01| | N26: 1 | O26: Operación | P26: Primaria | Q26: Evidente | R26: Prueba de tracción | S26: FABRICANTE | T26: F-MET-094
A27: Motor Deutz TCD2015V8 Power Pack · B0700 | B27: F-MET-064 | C27: Entregar | D27: potencia mecánica | E27: en un rango de 490 a 510 | F27: kW | G27: =TRIM(CONCATENATE(C27," ",D27," ",E27," ",F27)) -> Entregar potencia mecánica en un rango de 490 a 510 kW | H27: Significativa – Operación | I27: MET-MAU-B0700-TRC-MOP01 | J27: DEUTZ | K27: potencia mecánica en un rago de 490 kW a 510 kW. | L27: Motor Deutz TCD2015V8 Power Pack | M27: |MET-MAU-B0700-TRC-MOP01| | N27: 1 | O27: Operación | P27: Primaria | Q27: Evidente | R27: Banco / opacímetro / registro ECU | S27: FABRICANTE | T27: F-MET-095
A28: Transmisión Cardan · B0700 | B28: F-MET-069 | C28: Transmitir | D28: torque al eje | E28: hasta 2.500 | F28: N.m | G28: =TRIM(CONCATENATE(C28," ",D28," ",E28," ",F28)) -> Transmitir torque al eje hasta 2.500 N.m | H28: Significativa – Operación | I28: MET-MAU-B0700-TRC-TCA01 | K28: hasta 2.500 N.m | L28: Transmisión Cardan | M28: |MET-MAU-B0700-TRC-TCA01| | N28: 1 | O28: Operación | P28: Primaria | Q28: Evidente | R28: Control de juego y vibración mensual (DR1227 pág. 104) | S28: FABRICANTE | T28: F-MET-096
A29: Compresor (×2) · B3011 | B29: F-MET-911 | C29: Comprimir | D29: el aire | E29: a una presión de _____ | F29: bar | G29: =TRIM(CONCATENATE(C29," ",D29," ",E29," ",F29)) -> Comprimir el aire a una presión de _____ bar | H29: Significativa – Operación | I29: MET-MAU-B3011-AIR-COM01 | K29: Función agregada en la revisión 27/10. Falta: presión de trabajo en bar (placa del compresor); si se prefiere psi, cambiar la unidad. | L29: Compresor 1 BT-3011 | M29: |MET-MAU-B3011-AIR-COM01|MET-MAU-B3011-AIR-COM02| | N29: 2 | O29: Operación | P29: Primaria | Q29: Evidente | R29: Lectura del manómetro y tiempo de llenado de calderines | S29: FABRICANTE | T29: Nueva (solicitada en la revisión) | W29: Función nueva: no existía en la versión anterior
A30: Compresor (×2) · B3011 | B30: F-MET-072 | C30: Suministrar | D30: aire | E30: con caudal de 980 a 1.020 | F30: L/min | G30: =TRIM(CONCATENATE(C30," ",D30," ",E30," ",F30)) -> Suministrar aire con caudal de 980 a 1.020 L/min | H30: Significativa – Operación | I30: MET-MAU-B3011-AIR-COM01 | K30: caudal de 980 a 1.020 L/min. | Revisión 27/10: la función principal pasó a ser comprimir el aire (nueva función de presión); esta queda como secundaria. | L30: Compresor 1 BT-3011 | M30: |MET-MAU-B3011-AIR-COM01|MET-MAU-B3011-AIR-COM02| | N30: 2 | O30: Operación | P30: Secundaria | Q30: Evidente | R30: Tiempo de llenado de calderines | S30: FABRICANTE | T30: F-MET-097, F-MET-098
A31: Secador de Aire BT-3011 · B3011 | B31: F-MET-076 | C31: Secar | D31: el aire comprimido | E31: con punto de rocío máximo de +3 | F31: °C | G31: =TRIM(CONCATENATE(C31," ",D31," ",E31," ",F31)) -> Secar el aire comprimido con punto de rocío máximo de +3 °C | H31: Significativa – Operación | I31: MET-MAU-B3011-AIR-SAI01 | J31: ISO 8573-1 | K31: Clase 4 ISO 8573-1 como referencia; confirmar con el fabricante. | L31: Secador DE Aire BT-3011 | M31: |MET-MAU-B3011-AIR-SAI01| | N31: 1 | O31: Protección | P31: Primaria | Q31: Oculta | R31: Purga diaria de calderines sin agua | S31: NORMA | T31: F-MET-100
A32: Unidad hidráulica (×2) · PERFI | B32: F-MET-077 | C32: Suministrar | D32: aceite | E32: con caudal de 38 a 42 | F32: L/min | G32: =TRIM(CONCATENATE(C32," ",D32," ",E32," ",F32)) -> Suministrar aceite con caudal de 38 a 42 L/min | H32: Significativa – Operación | I32: MET-TAL-PERFI-PER-HIA01 | K32: caudal de 38 a 42 L/min. | L32: Unidad Hidraulica | M32: |MET-TAL-PERFI-PER-HIA01|MET-TAL-PERFI-PER-HID01| | N32: 2 | O32: Operación | P32: Primaria | Q32: Evidente | R32: Caudalímetro / tiempos de ciclo | S32: FABRICANTE | T32: F-MET-1000, F-MET-1001
A33: Torno de foso (×2) · PERFI | B33: F-MET-084 | C33: Limitar | D33: la excentricidad | E33: a un máximo de 0,1 | F33: mm | G33: =TRIM(CONCATENATE(C33," ",D33," ",E33," ",F33)) -> Limitar la excentricidad a un máximo de 0,1 mm | H33: Significativa – Operación | I33: MET-TAL-PERFI-PER-PER01 | J33: Hegenscheidt | K33: Dato del torno U2000-150 del mismo taller; confirmar si la perfiladora PFR es el mismo equipo. | L33: Perfiladora DE Ruedas PFR | M33: |MET-TAL-PERFI-PER-PER01|MET-TAL-PERFI-PER-PER02| | N33: 2 | O33: Operación | P33: Secundaria | Q33: Evidente | R33: Medición integrada | S33: FUENTE TÉCNICA | T33: Nueva (dato medible del estudio)
A34: Torno de foso (×2) · PERFI | B34: F-MET-085 | C34: Igualar | D34: el diámetro en bogie | E34: con diferencia máxima de 0,3 | F34: mm | G34: =TRIM(CONCATENATE(C34," ",D34," ",E34," ",F34)) -> Igualar el diámetro en bogie con diferencia máxima de 0,3 mm | H34: Significativa – Operación | I34: MET-TAL-PERFI-PER-PER01 | J34: Hegenscheidt | K34: Dato del torno U2000-150 del mismo taller; confirmar si la perfiladora PFR es el mismo equipo. | L34: Perfiladora DE Ruedas PFR | M34: |MET-TAL-PERFI-PER-PER01|MET-TAL-PERFI-PER-PER02| | N34: 2 | O34: Operación | P34: Secundaria | Q34: Evidente | R34: Medición integrada | S34: FUENTE TÉCNICA | T34: Nueva (dato medible del estudio)
A35: Potencia PFR · PERFI | B35: F-MET-088 | C35: Suministrar | D35: energía eléctrica | E35: de 80 | F35: kVA | G35: =TRIM(CONCATENATE(C35," ",D35," ",E35," ",F35)) -> Suministrar energía eléctrica de 80 kVA | H35: Significativa – Operación | I35: MET-TAL-PERFI-PER-PON01 | J35: Hegenscheidt | L35: Potencia PFR | M35: |MET-TAL-PERFI-PER-PON01| | N35: 1 | O35: Operación | P35: Primaria | Q35: Evidente | R35: Medición de demanda | S35: FABRICANTE | T35: F-MET-1007
A36: Bomba de Emergencia BT-3011 · B3011 | B36: F-MET-094 | C36: Suministrar | D36: aceite | E36: con un caudal de 13 a 16 | F36: L/min | G36: =TRIM(CONCATENATE(C36," ",D36," ",E36," ",F36)) -> Suministrar aceite con un caudal de 13 a 16 L/min | H36: Significativa – Seguridad/Ambiental | I36: MET-MAU-B3011-AVA-BMB01 | K36: caudal de 13 a 16 L/min. | L36: Bomba DE Emergencia BT-3011 | M36: |MET-MAU-B3011-AVA-BMB01| | N36: 1 | O36: Protección | P36: Secundaria | Q36: Oculta | R36: Prueba funcional de la bomba de emergencia | S36: FABRICANTE | T36: F-MET-104
A37: Motor HD EJE Motriz 1 BT-3011 · B3011 | B37: F-MET-096 | C37: Generar | D37: torque | E37: hasta 3.500 | F37: N.m | G37: =TRIM(CONCATENATE(C37," ",D37," ",E37," ",F37)) -> Generar torque hasta 3.500 N.m | H37: Significativa – Operación | I37: MET-MAU-B3011-AVA-MMO01 | K37: Torque hasta 3.500 N.m | L37: Motor HD EJE Motriz 1 BT-3011 | M37: |MET-MAU-B3011-AVA-MMO01| | N37: 1 | O37: Operación | P37: Primaria | Q37: Evidente | R37: Prueba de tracción | S37: FABRICANTE | T37: F-MET-108
A38: Bogie Motriz · B3011 | B38: F-MET-104 | C38: Soportar | D38: carga vertical | E38: hasta 20 | F38: toneladas | G38: =TRIM(CONCATENATE(C38," ",D38," ",E38," ",F38)) -> Soportar carga vertical hasta 20 toneladas | H38: Significativa – Seguridad/Ambiental | I38: MET-MAU-B3011-BOI-BMO01 | K38: Falta: carga por bogie. | L38: Bogie Motriz | M38: |MET-MAU-B3011-BOI-BMO01| | N38: 1 | O38: Soporte | P38: Primaria | Q38: Oculta | R38: Pesaje | S38: FABRICANTE | T38: F-MET-117
A39: EJE Motriz 2 BT-3011 · B3011 | B39: F-MET-106 | C39: Transmitir | D39: la potencia del motor a las ruedas | E39: hasta un par de _____ | F39: N·m | G39: =TRIM(CONCATENATE(C39," ",D39," ",E39," ",F39)) -> Transmitir la potencia del motor a las ruedas hasta un par de _____ N·m | H39: Significativa – Seguridad/Ambiental | I39: MET-MAU-B3011-BOI-MOZ01 | K39: Falta: carga por eje. | Revisión 27/10: la función pasó de soportar la carga por eje (16 t) a recibir la potencia del motor y transmitirla a las ruedas; par por confirmar con el fabricante. | L39: EJE Motriz 2 BT-3011 | M39: |MET-MAU-B3011-BOI-MOZ01| | N39: 1 | O39: Soporte | P39: Primaria | Q39: Oculta | R39: Ensayos no destructivos (END) del eje | S39: FABRICANTE | T39: F-MET-119
A40: EJE Motriz 2 BT-3011 · B3011 | B40: F-MET-107 | C40: Impedir | D40: el remonte de pestaña | E40: con cota qR ≥ 6,5 | F40: mm | G40: =TRIM(CONCATENATE(C40," ",D40," ",E40," ",F40)) -> Impedir el remonte de pestaña con cota qR ≥ 6,5 mm | H40: Significativa – Seguridad/Ambiental | I40: MET-MAU-B3011-BOI-MOZ01 | J40: TSI LOC&PAS / OTIF UTP LOC&PAS, tablas 1 y 2 | K40: qR: cota de la cara activa de la pestaña (galga de perfil). | L40: EJE Motriz 2 BT-3011 | M40: |MET-MAU-B3011-BOI-MOZ01| | N40: 1 | O40: Seguridad | P40: Primaria | Q40: Oculta | R40: Galga de perfil | S40: NORMA | T40: F-MET-118
A41: EJE Motriz 2 BT-3011 · B3011 | B41: F-MET-108 | C41: Mantener | D41: la distancia entre ruedas | E41: de 1.357 a 1.363 | F41: mm | G41: =TRIM(CONCATENATE(C41," ",D41," ",E41," ",F41)) -> Mantener la distancia entre ruedas de 1.357 a 1.363 mm | H41: Significativa – Seguridad/Ambiental | I41: MET-MAU-B3011-BOI-MOZ01 | J41: TSI LOC&PAS / OTIF UTP LOC&PAS, tablas 1 y 2 | K41: Distancia entre caras internas; asegura el juego rueda-carril en vía de 1.435 mm. Límite TSI según diámetro: ≥ 1.357 (> 840 mm), 1.358–1.363 (760–840 mm), ≥ 1.359 (≤ 760 mm). | L41: EJE Motriz 2 BT-3011 | M41: |MET-MAU-B3011-BOI-MOZ01| | N41: 1 | O41: Seguridad | P41: Secundaria | Q41: Oculta | R41: Calibre | S41: NORMA | T41: Nueva (dato medible del estudio)
A42: Tanque de Aceite Hidraulico BT-3011 · B3011 | B42: F-MET-116 | C42: Almacenar | D42: el aceite hidráulico | E42: hasta 150 | F42: L | G42: =TRIM(CONCATENATE(C42," ",D42," ",E42," ",F42)) -> Almacenar el aceite hidráulico hasta 150 L | H42: Significativa – Operación | I42: MET-MAU-B3011-CAJ-TAH01 | K42: Falta: volumen del tanque. | L42: Tanque DE Aceite Hidraulico BT-3011 | M42: |MET-MAU-B3011-CAJ-TAH01| | N42: 1 | O42: Contención | P42: Primaria | Q42: Evidente | R42: Mirilla de nivel | S42: FABRICANTE | T42: F-MET-126
A43: Baterias BT-3011 · B3011 | B43: F-MET-118 | C43: Almacenar | D43: energía eléctrica | E43: hasta 800 | F43: CCA | G43: =TRIM(CONCATENATE(C43," ",D43," ",E43," ",F43)) -> Almacenar energía eléctrica hasta 800 CCA | H43: Significativa – Operación | I43: MET-MAU-B3011-ELE-BTE01 | K43: Criterio de prueba de carga: 9,6 V por batería de 12 V en sistema de 24 V. Confirmar tensión nominal en la placa. | Revisión 27/10: objeto cambiado de "carga eléctrica" a "energía eléctrica". | L43: Baterias BT-3011 | M43: |MET-MAU-B3011-ELE-BTE01| | N43: 1 | O43: Operación | P43: Primaria | Q43: Evidente | R43: Voltímetro | S43: FABRICANTE | T43: F-MET-127
A44: Generador 28V/140A BT-3011 · B3011 | B44: F-MET-120 | C44: Generar | D44: corriente de carga | E44: de 140 | F44: A | G44: =TRIM(CONCATENATE(C44," ",D44," ",E44," ",F44)) -> Generar corriente de carga de 140 A | H44: Significativa – Operación | I44: MET-MAU-B3011-ELE-GEE01 | J44: Nombre del equipo en SAP (IW43_2021-28092026.xlsx) | K44: Valores del nombre del equipo en SAP (Generador 28V/140A). | L44: Generador 28V/140A BT-3011 | M44: |MET-MAU-B3011-ELE-GEE01| | N44: 1 | O44: Operación | P44: Primaria | Q44: Evidente | R44: Voltímetro / amperímetro | S44: DISEÑO | T44: F-MET-128
A45: Cilindro DE Freno (×2) · B3011 | B45: F-MET-125 | C45: Presurizar | D45: los cilindros de freno | E45: entre 3,7 y 3,9 | F45: bar | G45: =TRIM(CONCATENATE(C45," ",D45," ",E45," ",F45)) -> Presurizar los cilindros de freno entre 3,7 y 3,9 bar | H45: Significativa – Seguridad/Ambiental | I45: MET-MAU-B3011-FRN-CID01 | J45: UIC 540 | K45: Presión de freno a fondo del freno automático UIC 540 (3,8 ± 0,1 bar). | L45: Cilindro DE Freno EJE 1 | M45: |MET-MAU-B3011-FRN-CID01|MET-MAU-B3011-FRN-CIM01| | N45: 2 | O45: Seguridad | P45: Primaria | Q45: Evidente | R45: Manómetro en toma de prueba | S45: NORMA | T45: F-MET-132, F-MET-133
A46: Timoneria DE Freno (×2) · B3011 | B46: F-MET-128 | C46: Transmitir | D46: la fuerza a zapatas | E46: con juego de 5 a 7 | F46: mm | G46: =TRIM(CONCATENATE(C46," ",D46," ",E46," ",F46)) -> Transmitir la fuerza a zapatas con juego de 5 a 7 mm | H46: Significativa – Seguridad/Ambiental | I46: MET-MAU-B3011-FRN-TFR01 | J46: Manual de Mantenimiento DR1227 Plasser & Theurer DIC-40 (WS6761) – p.51 | K46: Valor del manual Plasser DR1227; aplicar como referencia en otras máquinas Plasser. | L46: Timoneria DE Freno EJE Motriz 1 Y 2 | M46: |MET-MAU-B3011-FRN-TFR01|MET-MAU-B3011-FRN-TIF01| | N46: 2 | O46: Seguridad | P46: Primaria | Q46: Evidente | R46: Medición de juego / prueba de frenado | S46: FUENTE TÉCNICA | T46: F-MET-136, F-MET-137
A47: Carro Tensor Y DE Registro (×2) · B3011 | B47: F-MET-140 | C47: Tensar | D47: la cuerda de medición | E47: con una fuerza de 98 a 105 | F47: N | G47: =TRIM(CONCATENATE(C47," ",D47," ",E47," ",F47)) -> Tensar la cuerda de medición con una fuerza de 98 a 105 N | H47: Significativa – Operación | I47: MET-MAU-B3011-MED-CARR01 | K47: Falta: tensión de la cuerda. | L47: Carro Tensor Y DE Registro Trasero | M47: |MET-MAU-B3011-MED-CARR01|MET-MAU-B3011-MED-CTE01| | N47: 2 | O47: Medición | P47: Primaria | Q47: Oculta | R47: Calibración | S47: FABRICANTE | T47: Nueva (dato medible del estudio)
A48: Caja de Engranaje Distribuidor BT-3011 · B3011 | B48: F-MET-148 | C48: Distribuir | D48: el par entre ejes | E48: hasta 1.780 | F48: N.m | G48: =TRIM(CONCATENATE(C48," ",D48," ",E48," ",F48)) -> Distribuir el par entre ejes hasta 1.780 N.m | H48: Significativa – Operación | I48: MET-MAU-B3011-TRC-CAJA01 | K48: Falta: la relación de transmisión. | L48: Caja DE Engranaje Distribuidor BT-3011 | M48: |MET-MAU-B3011-TRC-CAJA01| | N48: 1 | O48: Operación | P48: Primaria | Q48: Evidente | R48: Prueba de tracción / termografía y ruido | S48: FABRICANTE | T48: F-MET-163
A49: Motor Diesel KHD BF6M 1015/C Deutz · B3011 | B49: F-MET-151 | C49: Entregar | D49: potencia mecánica | E49: hasta 300 | F49: kW | G49: =TRIM(CONCATENATE(C49," ",D49," ",E49," ",F49)) -> Entregar potencia mecánica hasta 300 kW | H49: Significativa – Operación | I49: MET-MAU-B3011-TRC-MDE01 | J49: DEUTZ | K49: Potencia nominal del Deutz BF6M1015C según el fabricante. | L49: Motor Diesel KHD BF6M 1015/C Deutz | M49: |MET-MAU-B3011-TRC-MDE01| | N49: 1 | O49: Operación | P49: Primaria | Q49: Evidente | R49: Banco / registro | S49: FABRICANTE | T49: F-MET-164
A50: Motor Diesel KHD BF6M 1015/C Deutz · B3011 | B50: F-MET-152 | C50: Mover | D50: Eje | E50: de 0 a 1.200 | F50: rpm | G50: =TRIM(CONCATENATE(C50," ",D50," ",E50," ",F50)) -> Mover Eje de 0 a 1.200 rpm | H50: Significativa – Operación | I50: MET-MAU-B3011-TRC-MDE01 | J50: DEUTZ | K50: Par máximo de 1.978 N·m a 1.200 rpm (Deutz). | L50: Motor Diesel KHD BF6M 1015/C Deutz | M50: |MET-MAU-B3011-TRC-MDE01| | N50: 1 | O50: Operación | P50: Secundaria | Q50: Evidente | R50: Banco | S50: FABRICANTE | T50: Nueva (dato medible del estudio)
A51: Locotractor CRAB (×2) · CRA01–CRA02 | B51: F-MET-157 | C51: Remolcar | D51: vehículos | E51: hasta 300 | F51: toneladas en sistema de rieles | G51: =TRIM(CONCATENATE(C51," ",D51," ",E51," ",F51)) -> Remolcar vehículos hasta 300 toneladas en sistema de rieles | H51: Significativa – Operación | I51: MET-MAU-CRA01 | K51: Masa remolcable del locotractor CRAB: 300 t. Validar con la placa. | L51: Locotractor CRAB-01 | M51: |MET-MAU-CRA01|MET-MAU-CRA02| | N51: 2 | O51: Operación | P51: Primaria | Q51: Evidente | R51: Prueba de arrastre | S51: FABRICANTE | T51: Nueva (dato medible del estudio)
A52: Bomba Direccion (×2) · CRA01–CRA02 | B52: F-MET-158 | C52: Suministrar | D52: caudal de aceite | E52: entre 23 y 27 | F52: L/min | G52: =TRIM(CONCATENATE(C52," ",D52," ",E52," ",F52)) -> Suministrar caudal de aceite entre 23 y 27 L/min | H52: Significativa – Operación | I52: MET-MAU-CRA01-AVA-BOD01 | K52: Caudal nominal de la bomba de dirección. Validar con la placa. | L52: Bomba Direccion | M52: |MET-MAU-CRA01-AVA-BOD01|MET-MAU-CRA02-AVA-BOD01| | N52: 2 | O52: Operación | P52: Primaria | Q52: Evidente | R52: Caudalímetro / tiempos de ciclo | S52: FABRICANTE | T52: F-MET-165, F-MET-173
A53: Bomba Direccion (×2) · CRA01–CRA02 | B53: F-MET-159 | C53: Incrementar | D53: presión hidráulica | E53: hasta 150 | F53: bar | G53: =TRIM(CONCATENATE(C53," ",D53," ",E53," ",F53)) -> Incrementar presión hidráulica hasta 150 bar | H53: Significativa – Operación | I53: MET-MAU-CRA01-AVA-BOD01 | K53: Presión máxima del circuito de dirección. Validar con el tarado de la válvula de alivio. | L53: Bomba Direccion | M53: |MET-MAU-CRA01-AVA-BOD01|MET-MAU-CRA02-AVA-BOD01| | N53: 2 | O53: Operación | P53: Secundaria | Q53: Evidente | R53: Manómetro | S53: FABRICANTE | T53: Nueva (dato medible del estudio)
A54: Cabina (×2) · CRA01–CRA02 | B54: F-MET-160 | C54: Sellar | D54: la cabina | E54: con 0 | F54: filtraciones en prueba de agua | G54: =TRIM(CONCATENATE(C54," ",D54," ",E54," ",F54)) -> Sellar la cabina con 0 filtraciones en prueba de agua | H54: Significativa – Operación | I54: MET-MAU-CRA01-CAJ-CAI01 | J54: Manual de Mantenimiento DR1227 Plasser & Theurer DIC-40 (WS6761) – p.81 | K54: Valor del manual DR1227 de la DIC-40 (máquina Plasser equivalente); validar con el manual de esta máquina. | L54: Cabina | M54: |MET-MAU-CRA01-CAJ-CAI01|MET-MAU-CRA02-CAJ-CAI01| | N54: 2 | O54: Protección | P54: Primaria | Q54: Evidente | R54: Control visual anual de juntas de goma | S54: FABRICANTE | T54: F-MET-166, F-MET-174
A55: Banco DE Baterias (×2) · CRA01–CRA02 | B55: F-MET-163 | C55: Suministrar | D55: energía | E55: de 78 a 82 | F55: V en corriente directa | G55: =TRIM(CONCATENATE(C55," ",D55," ",E55," ",F55)) -> Suministrar energía de 78 a 82 V en corriente directa | H55: Significativa – Operación | I55: MET-MAU-CRA01-ELE-BAN01 | K55: Tensión nominal del banco: 80 V CC. | L55: Banco DE Baterias | M55: |MET-MAU-CRA01-ELE-BAN01|MET-MAU-CRA02-ELE-BAN01| | N55: 2 | O55: Operación | P55: Primaria | Q55: Evidente | R55: Ensayo de capacidad | S55: FABRICANTE | T55: F-MET-168, F-MET-176
A56: Banco DE Baterias (×2) · CRA01–CRA02 | B56: F-MET-902 | C56: Almacenar | D56: energía eléctrica | E56: con tensión de 78 a 82 | F56: V en corriente directa | G56: =TRIM(CONCATENATE(C56," ",D56," ",E56," ",F56)) -> Almacenar energía eléctrica con tensión de 78 a 82 V en corriente directa | H56: Significativa – Operación | I56: MET-MAU-CRA01-ELE-BAN01 | K56: Función agregada en la revisión 27/10. Mismo estándar de tensión que la función existente del activo. | L56: Banco DE Baterias | M56: |MET-MAU-CRA01-ELE-BAN01|MET-MAU-CRA02-ELE-BAN01| | N56: 2 | O56: Operación | P56: Primaria | Q56: Evidente | R56: Ensayo de capacidad | S56: FABRICANTE | T56: Nueva (solicitada en la revisión) | W56: Función nueva: no existía en la versión anterior
A57: Banco DE Baterias (×2) · CRA01–CRA02 | B57: F-MET-843 | C57: Almacenar | D57: energía eléctrica | E57: con capacidad de 800 | F57: Ah | G57: =TRIM(CONCATENATE(C57," ",D57," ",E57," ",F57)) -> Almacenar energía eléctrica con capacidad de 800 Ah | H57: Significativa – Operación | I57: MET-MAU-CRA01-ELE-BAN01 | K57: Capacidad nominal del banco: 800 Ah. | Revisión 27/10: la función pasó de "Entregar capacidad de carga" a "Almacenar energía eléctrica". | L57: Banco DE Baterias | M57: |MET-MAU-CRA01-ELE-BAN01|MET-MAU-CRA02-ELE-BAN01| | N57: 2 | O57: Operación | P57: Primaria | Q57: Evidente | R57: Ensayo de capacidad | S57: FABRICANTE | T57: F-MET-168, F-MET-176
A58: Sistema Frenos (×2) · CRA01–CRA02 | B58: F-MET-165 | C58: Presurizar | D58: los cilindros de freno | E58: entre 3,7 y 3,9 | F58: bar | G58: =TRIM(CONCATENATE(C58," ",D58," ",E58," ",F58)) -> Presurizar los cilindros de freno entre 3,7 y 3,9 bar | H58: Significativa – Seguridad/Ambiental | I58: MET-MAU-CRA01-FRN | J58: UIC 540 | K58: Presión de freno a fondo del freno automático UIC 540 (3,8 ± 0,1 bar). | L58: Sistema Frenos | M58: |MET-MAU-CRA01-FRN|MET-MAU-CRA02-FRN| | N58: 2 | O58: Seguridad | P58: Secundaria | Q58: Evidente | R58: Manómetro | S58: NORMA | T58: Nueva (dato medible del estudio)
A59: Timonería de freno (×2) · CRA01–CRA02 | B59: F-MET-166 | C59: Transmitir | D59: la fuerza a zapatas | E59: con holgura de 5 a 8 | F59: mm | G59: =TRIM(CONCATENATE(C59," ",D59," ",E59," ",F59)) -> Transmitir la fuerza a zapatas con holgura de 5 a 8 mm | H59: Significativa – Seguridad/Ambiental | I59: MET-MAU-CRA01-FRN-TIF01 | K59: Juego zapata-rueda admisible. | L59: Timoneria DE Freno | M59: |MET-MAU-CRA01-FRN-TIF01|MET-MAU-CRA02-FRN-TIM01| | N59: 2 | O59: Seguridad | P59: Primaria | Q59: Evidente | R59: Medición de juego | S59: FABRICANTE | T59: F-MET-169, F-MET-177
A60: Motor Electrico (×2) · CRA01–CRA02 | B60: F-MET-170 | C60: Entregar | D60: potencia | E60: de 18 a 22 | F60: kW | G60: =TRIM(CONCATENATE(C60," ",D60," ",E60," ",F60)) -> Entregar potencia de 18 a 22 kW | H60: Significativa – Operación | I60: MET-MAU-CRA01-TRC-MEL01 | K60: Potencia nominal del motor eléctrico del CRAB. | L60: Motor Electrico | M60: |MET-MAU-CRA01-TRC-MEL01|MET-MAU-CRA02-TRC-MEL01| | N60: 2 | O60: Operación | P60: Primaria | Q60: Evidente | R60: Placa | S60: FABRICANTE | T60: F-MET-171, F-MET-179
A61: Caja Distribuidora (×2) · CRA01–CRA02 | B61: F-MET-172 | C61: Distribuir | D61: el par entre ejes | E61: hasta 4.300 | F61: N.m | G61: =TRIM(CONCATENATE(C61," ",D61," ",E61," ",F61)) -> Distribuir el par entre ejes hasta 4.300 N.m | H61: Significativa – Operación | I61: MET-MAU-CRA01-TRN-CAJD01 | K61: Par máximo de salida de la caja distribuidora. Falta: relación de transmisión. | L61: Caja Distribuidora | M61: |MET-MAU-CRA01-TRN-CAJD01|MET-MAU-CRA02-TRN-CAJD01| | N61: 2 | O61: Operación | P61: Primaria | Q61: Evidente | R61: Prueba de tracción / termografía y ruido | S61: FABRICANTE | T61: F-MET-172, F-MET-180
A62: Dresina Grua 851 | B62: F-MET-175 | C62: Remolcar | D62: trenes de trabajo | E62: hasta 500 | F62: toneladas | G62: =TRIM(CONCATENATE(C62," ",D62," ",E62," ",F62)) -> Remolcar trenes de trabajo hasta 500 toneladas | H62: Significativa – Operación | I62: MET-MAU-DG851 | K62: Falta: masa remolcable (placa). | L62: Dresina Grua 851 | M62: |MET-MAU-DG851| | N62: 1 | O62: Operación | P62: Primaria | Q62: Evidente | R62: Prueba de arrastre | S62: FABRICANTE | T62: Nueva (dato medible del estudio)
A63: Compresor DG-851 | B63: F-MET-912 | C63: Comprimir | D63: el aire | E63: a una presión de _____ | F63: bar | G63: =TRIM(CONCATENATE(C63," ",D63," ",E63," ",F63)) -> Comprimir el aire a una presión de _____ bar | H63: Significativa – Operación | I63: MET-MAU-DG851-AIR-COM01 | K63: Función agregada en la revisión 27/10. Falta: presión de trabajo en bar (placa del compresor); si se prefiere psi, cambiar la unidad. | L63: Compresor DG-851 | M63: |MET-MAU-DG851-AIR-COM01| | N63: 1 | O63: Operación | P63: Primaria | Q63: Evidente | R63: Lectura del manómetro y tiempo de llenado de calderines | S63: FABRICANTE | T63: Nueva (solicitada en la revisión) | W63: Función nueva: no existía en la versión anterior
A64: Compresor DG-851 | B64: F-MET-176 | C64: Suministrar | D64: caudal de aire | E64: [ESTÁNDAR POR CONFIRMAR] | G64: =TRIM(CONCATENATE(C64," ",D64," ",E64," ",F64)) -> Suministrar caudal de aire [ESTÁNDAR POR CONFIRMAR] | H64: Significativa – Operación | I64: MET-MAU-DG851-AIR-COM01 | K64: Falta: caudal (placa). | Revisión 27/10: la función principal pasó a ser comprimir el aire (nueva función de presión); esta queda como secundaria. | L64: Compresor DG-851 | M64: |MET-MAU-DG851-AIR-COM01| | N64: 1 | O64: Operación | P64: Secundaria | Q64: Evidente | R64: Tiempo de llenado de calderines | S64: FABRICANTE | T64: F-MET-181
A65: Motor Hidraulico DG-851 | B65: F-MET-178 | C65: Entregar | D65: torque | E65: hasta _____ | F65: N.m | G65: =TRIM(CONCATENATE(C65," ",D65," ",E65," ",F65)) -> Entregar torque hasta _____ N.m | H65: Significativa – Operación | I65: MET-MAU-DG851-AVA-MOH01 | K65: Falta: par y velocidad nominal (placa del motor hidráulico). | L65: Motor Hidraulico DG-851 | M65: |MET-MAU-DG851-AVA-MOH01| | N65: 1 | O65: Operación | P65: Primaria | Q65: Evidente | R65: Prueba de tracción | S65: FABRICANTE | T65: F-MET-182
A66: Cabina DG-851 | B66: F-MET-180 | C66: Sellar | D66: la cabina | E66: con 0 | F66: filtraciones en prueba de agua | G66: =TRIM(CONCATENATE(C66," ",D66," ",E66," ",F66)) -> Sellar la cabina con 0 filtraciones en prueba de agua | H66: Significativa – Operación | I66: MET-MAU-DG851-CAJ-CAI01 | J66: Manual de Mantenimiento DR1227 Plasser & Theurer DIC-40 (WS6761) – p.81 | K66: Valor del manual DR1227 de la DIC-40 (máquina Plasser equivalente); validar con el manual de esta máquina. | L66: Cabina DG-851 | M66: |MET-MAU-DG851-CAJ-CAI01| | N66: 1 | O66: Protección | P66: Primaria | Q66: Evidente | R66: Control visual anual de juntas de goma | S66: FABRICANTE | T66: F-MET-183
A67: Deposito de Combustible DG-851 | B67: F-MET-182 | C67: Retener | D67: el combustible | E67: a presión de prueba de 0,3 | F67: bar | G67: =TRIM(CONCATENATE(C67," ",D67," ",E67," ",F67)) -> Retener el combustible a presión de prueba de 0,3 bar | H67: Significativa – Seguridad/Ambiental | I67: MET-MAU-DG851-CAJ-DEC01 | K67: Referencia UNECE R34 (tanques de vehículos); no validada para esta máquina. Vigilancia diaria: inspección visual de goteos. | L67: Deposito DE Combustible DG-851 | M67: |MET-MAU-DG851-CAJ-DEC01| | N67: 1 | O67: Medio Ambiente | P67: Secundaria | Q67: Evidente | R67: Inspección visual | S67: DERIVADA TÉCNICAMENTE | T67: Nueva (dato medible del estudio)
A68: Banco de Baterias DG-851 | B68: F-MET-186 | C68: Almacenar | D68: energía eléctrica | E68: con tensión mínima de 19,2 | F68: V | G68: =TRIM(CONCATENATE(C68," ",D68," ",E68," ",F68)) -> Almacenar energía eléctrica con tensión mínima de 19,2 V | H68: Significativa – Operación | I68: MET-MAU-DG851-ELE-BAN01 | K68: Criterio de prueba de carga: 9,6 V por batería de 12 V en sistema de 24 V. Confirmar tensión nominal en la placa. | L68: Banco DE Baterias DG-851 | M68: |MET-MAU-DG851-ELE-BAN01| | N68: 1 | O68: Operación | P68: Primaria | Q68: Evidente | R68: Voltímetro | S68: FABRICANTE | T68: F-MET-187
A69: Brazo Estabilizador DG-851 | B69: F-MET-191 | C69: Evitar | D69: el vuelco de la plataforma | E69: con momento de 107 | F69: kN·m | G69: =TRIM(CONCATENATE(C69," ",D69," ",E69," ",F69)) -> Evitar el vuelco de la plataforma con momento de 107 kN·m | H69: Significativa – Seguridad/Ambiental | I69: MET-MAU-DG851-ELV-BES01 | K69: Falta: fuerza de apoyo. | L69: Brazo Estabilizador DG-851 | M69: |MET-MAU-DG851-ELV-BES01| | N69: 1 | O69: Seguridad | P69: Primaria | Q69: Evidente | R69: Prueba funcional | S69: FABRICANTE | T69: F-MET-189
A70: Sistema Frenos · DG851 | B70: F-MET-193 | C70: Presurizar | D70: los cilindros de freno | E70: entre 3,7 y 3,9 | F70: bar | G70: =TRIM(CONCATENATE(C70," ",D70," ",E70," ",F70)) -> Presurizar los cilindros de freno entre 3,7 y 3,9 bar | H70: Significativa – Seguridad/Ambiental | I70: MET-MAU-DG851-FRN | J70: UIC 540 | K70: Presión de freno a fondo del freno automático UIC 540 (3,8 ± 0,1 bar). | L70: Sistema Frenos | M70: |MET-MAU-DG851-FRN| | N70: 1 | O70: Seguridad | P70: Secundaria | Q70: Evidente | R70: Manómetro | S70: NORMA | T70: Nueva (dato medible del estudio)
A71: Timoneria de Frenos DG-851 | B71: F-MET-194 | C71: Transmitir | D71: la fuerza a zapatas | E71: hasta detener el vehiculo | G71: =TRIM(CONCATENATE(C71," ",D71," ",E71," ",F71)) -> Transmitir la fuerza a zapatas hasta detener el vehiculo | H71: Significativa – Seguridad/Ambiental | I71: MET-MAU-DG851-FRN-TIM01 | K71: Falta: juego zapata-rueda del fabricante. Referencia en máquina Plasser: entre 5 y 7 mm. | L71: Timoneria DE Frenos DG-851 | M71: |MET-MAU-DG851-FRN-TIM01| | N71: 1 | O71: Seguridad | P71: Primaria | Q71: Evidente | R71: Medición de juego | S71: FABRICANTE | T71: F-MET-190
A72: Bomba de Inyeccion DG-851 | B72: F-MET-198 | C72: Elevar | D72: la presión del combustible | E72: [ESTÁNDAR POR CONFIRMAR] | G72: =TRIM(CONCATENATE(C72," ",D72," ",E72," ",F72)) -> Elevar la presión del combustible [ESTÁNDAR POR CONFIRMAR] | H72: Significativa – Operación | I72: MET-MAU-DG851-TRC-BIN01 | K72: Falta: presión de inyección (manual del motor). | L72: Bomba DE Inyeccion DG-851 | M72: |MET-MAU-DG851-TRC-BIN01| | N72: 1 | O72: Operación | P72: Primaria | Q72: Oculta | R72: Banco de inyección | S72: FABRICANTE | T72: F-MET-193
A73: Bloque Motor DG-851 | B73: F-MET-199 | C73: Entregar | D73: potencia mecánica | E73: [ESTÁNDAR POR CONFIRMAR] | G73: =TRIM(CONCATENATE(C73," ",D73," ",E73," ",F73)) -> Entregar potencia mecánica [ESTÁNDAR POR CONFIRMAR] | H73: Significativa – Operación | I73: MET-MAU-DG851-TRC-BLO01 | K73: Falta: potencia nominal y velocidad (placa del motor). | L73: Bloque Motor DG-851 | M73: |MET-MAU-DG851-TRC-BLO01| | N73: 1 | O73: Operación | P73: Primaria | Q73: Evidente | R73: Placa del motor | S73: FABRICANTE | T73: F-MET-194
A74: Engranaje (×2) · DG851 | B74: F-MET-204 | C74: Transmitir | D74: el par motriz | E74: [ESTÁNDAR POR CONFIRMAR] | G74: =TRIM(CONCATENATE(C74," ",D74," ",E74," ",F74)) -> Transmitir el par motriz [ESTÁNDAR POR CONFIRMAR] | H74: Significativa – Operación | I74: MET-MAU-DG851-TRN-ENM01 | K74: Falta: par y relación de transmisión. | L74: Engranaje EJE Motriz 1 DG-851 | M74: |MET-MAU-DG851-TRN-ENM01|MET-MAU-DG851-TRN-ENM02| | N74: 2 | O74: Operación | P74: Primaria | Q74: Evidente | R74: Prueba de tracción | S74: FABRICANTE | T74: F-MET-196, F-MET-197
A75: Dresina Inspeccion de Catenaria Tipo 1 | B75: F-MET-207 | C75: Recorrer | D75: curvas | E75: de radio mínimo de 90 | F75: m | G75: =TRIM(CONCATENATE(C75," ",D75," ",E75," ",F75)) -> Recorrer curvas de radio mínimo de 90 m | H75: Significativa – Seguridad/Ambiental | I75: MET-MAU-DIC41 | J75: Manual de Mantenimiento DR1227 Plasser & Theurer DIC-40 (WS6761) – p.47 | L75: Dresina Inspeccion de Catenaria Tipo 1 | M75: |MET-MAU-DIC41| | N75: 1 | O75: Seguridad | P75: Secundaria | Q75: Evidente | R75: Prueba en curva | S75: FABRICANTE | T75: Nueva (dato medible del estudio)
A76: Compresor Aire (×2) · DIC41–DIC42 | B76: F-MET-913 | C76: Comprimir | D76: el aire | E76: a una presión de _____ | F76: bar | G76: =TRIM(CONCATENATE(C76," ",D76," ",E76," ",F76)) -> Comprimir el aire a una presión de _____ bar | H76: Significativa – Operación | I76: MET-MAU-DIC41-AIR-COP01 | K76: Función agregada en la revisión 27/10. Falta: presión de trabajo en bar (placa del compresor); si se prefiere psi, cambiar la unidad. | L76: Compresor Aire | M76: |MET-MAU-DIC41-AIR-COP01|MET-MAU-DIC42-AIR-COP01| | N76: 2 | O76: Operación | P76: Primaria | Q76: Evidente | R76: Lectura del manómetro y tiempo de llenado de calderines | S76: FABRICANTE | T76: Nueva (solicitada en la revisión) | W76: Función nueva: no existía en la versión anterior
A77: Compresor Aire (×2) · DIC41–DIC42 | B77: F-MET-210 | C77: Suministrar | D77: caudal de aire | E77: [ESTÁNDAR POR CONFIRMAR] | G77: =TRIM(CONCATENATE(C77," ",D77," ",E77," ",F77)) -> Suministrar caudal de aire [ESTÁNDAR POR CONFIRMAR] | H77: Significativa – Operación | I77: MET-MAU-DIC41-AIR-COP01 | K77: Falta: caudal (placa). | Revisión 27/10: la función principal pasó a ser comprimir el aire (nueva función de presión); esta queda como secundaria. | L77: Compresor Aire | M77: |MET-MAU-DIC41-AIR-COP01|MET-MAU-DIC42-AIR-COP01| | N77: 2 | O77: Operación | P77: Secundaria | Q77: Evidente | R77: Tiempo de llenado de calderines | S77: FABRICANTE | T77: F-MET-199, F-MET-219
A78: Bomba DE Traccion (×2) · DIC41–DIC42 | B78: F-MET-212 | C78: Suministrar | D78: caudal de aceite | E78: [ESTÁNDAR POR CONFIRMAR] | G78: =TRIM(CONCATENATE(C78," ",D78," ",E78," ",F78)) -> Suministrar caudal de aceite [ESTÁNDAR POR CONFIRMAR] | H78: Significativa – Operación | I78: MET-MAU-DIC41-AVA-BOT01 | K78: Falta: caudal nominal (placa de la bomba). | L78: Bomba DE Traccion | M78: |MET-MAU-DIC41-AVA-BOT01|MET-MAU-DIC42-AVA-BOT01| | N78: 2 | O78: Operación | P78: Primaria | Q78: Evidente | R78: Caudalímetro / tiempos de ciclo | S78: FABRICANTE | T78: F-MET-200, F-MET-220
A79: Bomba DE Traccion (×2) · DIC41–DIC42 | B79: F-MET-213 | C79: Generar | D79: presión hidráulica | E79: [ESTÁNDAR POR CONFIRMAR] | G79: =TRIM(CONCATENATE(C79," ",D79," ",E79," ",F79)) -> Generar presión hidráulica [ESTÁNDAR POR CONFIRMAR] | H79: Significativa – Operación | I79: MET-MAU-DIC41-AVA-BOT01 | K79: Falta: presión de trabajo (placa / esquema hidráulico). | L79: Bomba DE Traccion | M79: |MET-MAU-DIC41-AVA-BOT01|MET-MAU-DIC42-AVA-BOT01| | N79: 2 | O79: Operación | P79: Secundaria | Q79: Evidente | R79: Manómetro | S79: FABRICANTE | T79: Nueva (dato medible del estudio)
A80: Motor HD (×2) · DIC41–DIC42 | B80: F-MET-214 | C80: Entregar | D80: par de giro | E80: [ESTÁNDAR POR CONFIRMAR] | G80: =TRIM(CONCATENATE(C80," ",D80," ",E80," ",F80)) -> Entregar par de giro [ESTÁNDAR POR CONFIRMAR] | H80: Significativa – Operación | I80: MET-MAU-DIC41-AVA-MMO01 | K80: Falta: par y velocidad nominal (placa del motor hidráulico). | L80: Motor HD EJE Motriz 1 | M80: |MET-MAU-DIC41-AVA-MMO01|MET-MAU-DIC42-AVA-MMO01| | N80: 2 | O80: Operación | P80: Primaria | Q80: Evidente | R80: Prueba de tracción | S80: FABRICANTE | T80: F-MET-201, F-MET-221
A81: Cabina (×2) · DIC41–DIC42 | B81: F-MET-216 | C81: Sellar | D81: la cabina | E81: con 0 | F81: filtraciones en prueba de agua | G81: =TRIM(CONCATENATE(C81," ",D81," ",E81," ",F81)) -> Sellar la cabina con 0 filtraciones en prueba de agua | H81: Significativa – Operación | I81: MET-MAU-DIC41-CAJ-CAI01 | J81: Manual de Mantenimiento DR1227 Plasser & Theurer DIC-40 (WS6761) – p.81 | L81: Cabina | M81: |MET-MAU-DIC41-CAJ-CAI01|MET-MAU-DIC42-CAJ-CAI01| | N81: 2 | O81: Protección | P81: Primaria | Q81: Evidente | R81: Control visual anual de juntas de goma | S81: FABRICANTE | T81: F-MET-202, F-MET-222
A82: Banco DE Baterias (×2) · DIC41–DIC42 | B82: F-MET-220 | C82: Suministrar | D82: la corriente de arranque | E82: con tensión mínima de 19,2 | F82: V | G82: =TRIM(CONCATENATE(C82," ",D82," ",E82," ",F82)) -> Suministrar la corriente de arranque con tensión mínima de 19,2 V | H82: Significativa – Operación | I82: MET-MAU-DIC41-ELE-BAN01 | J82: Manual de Mantenimiento DR1227 Plasser & Theurer DIC-40 (WS6761) – p.32 | K82: Criterio de prueba de carga: 9,6 V por batería de 12 V en sistema de 24 V. Confirmar tensión nominal en la placa. | L82: Banco DE Baterias | M82: |MET-MAU-DIC41-ELE-BAN01|MET-MAU-DIC42-ELE-BAN01| | N82: 2 | O82: Operación | P82: Primaria | Q82: Evidente | R82: Voltímetro | S82: FABRICANTE | T82: F-MET-204, F-MET-224
A83: Banco DE Baterias (×2) · DIC41–DIC42 | B83: F-MET-903 | C83: Almacenar | D83: energía eléctrica | E83: con tensión mínima de 19,2 | F83: V | G83: =TRIM(CONCATENATE(C83," ",D83," ",E83," ",F83)) -> Almacenar energía eléctrica con tensión mínima de 19,2 V | H83: Significativa – Operación | I83: MET-MAU-DIC41-ELE-BAN01 | K83: Función agregada en la revisión 27/10. Mismo estándar de tensión que la función existente del activo. | L83: Banco DE Baterias | M83: |MET-MAU-DIC41-ELE-BAN01|MET-MAU-DIC42-ELE-BAN01| | N83: 2 | O83: Operación | P83: Primaria | Q83: Evidente | R83: Voltímetro | S83: FABRICANTE | T83: Nueva (solicitada en la revisión) | W83: Función nueva: no existía en la versión anterior
A84: Grúa (×2) · DIC41–DIC42 | B84: F-MET-225 | C84: Elevar | D84: las cargas | E84: con momento de 107 | F84: kN·m | G84: =TRIM(CONCATENATE(C84," ",D84," ",E84," ",F84)) -> Elevar las cargas con momento de 107 kN·m | H84: Significativa – Seguridad/Ambiental | I84: MET-MAU-DIC41-ELV-GRP01 | J84: Palfinger | L84: Grua PK11502 Palfinger | M84: |MET-MAU-DIC41-ELV-GRP01|MET-MAU-DIC42-ELV-GRU01| | N84: 2 | O84: Operación | P84: Primaria | Q84: Evidente | R84: Diagrama de cargas | S84: FABRICANTE | T84: F-MET-205, F-MET-226
A85: Plataforma PIC6500 · DIC41–DIC42 | B85: F-MET-228 | C85: Transportar | D85: material | E85: hasta 1.000 | F85: kg | G85: =TRIM(CONCATENATE(C85," ",D85," ",E85," ",F85)) -> Transportar material hasta 1.000 kg | H85: Significativa – Operación | I85: MET-MAU-DIC41-ELV-PLA01 | J85: Manual de Mantenimiento DR1227 Plasser & Theurer DIC-40 (WS6761) – p.47 | K85: Lectura del rótulo en la fotografía del manual: validar. | L85: Plataforma PIC6500 | M85: |MET-MAU-DIC41-ELV-PLA01| | N85: 1 | O85: Operación | P85: Primaria | Q85: Evidente | R85: Rótulo / control de carga | S85: FABRICANTE | T85: F-MET-206
A86: Timoneria DE Frenos (×2) · DIC41–DIC42 | B86: F-MET-231 | C86: Transmitir | D86: la fuerza a zapatas | E86: con juego de 5 a 7 | F86: mm | G86: =TRIM(CONCATENATE(C86," ",D86," ",E86," ",F86)) -> Transmitir la fuerza a zapatas con juego de 5 a 7 mm | H86: Significativa – Seguridad/Ambiental | I86: MET-MAU-DIC41-FRN-TIM01 | J86: Manual de Mantenimiento DR1227 Plasser & Theurer DIC-40 (WS6761) – p.51 | K86: Valor del manual Plasser DR1227; aplicar como referencia en otras máquinas Plasser. | L86: Timoneria DE Frenos | M86: |MET-MAU-DIC41-FRN-TIM01|MET-MAU-DIC42-FRN-TIM01| | N86: 2 | O86: Seguridad | P86: Primaria | Q86: Evidente | R86: Medición de juego / prueba de frenado | S86: FABRICANTE | T86: F-MET-207, F-MET-229
A87: Equipo de Medicion sin Contacto · DIC41–DIC42 | B87: F-MET-236 | C87: Medir | D87: la altura del hilo | E87: [ESTÁNDAR POR CONFIRMAR] | G87: =TRIM(CONCATENATE(C87," ",D87," ",E87," ",F87)) -> Medir la altura del hilo [ESTÁNDAR POR CONFIRMAR] | H87: Significativa – Operación | I87: MET-MAU-DIC41-MED-MEI01 | K87: Falta: exactitud del sistema de medición. | L87: Equipo DE Medicion SIN Contacto | M87: |MET-MAU-DIC41-MED-MEI01| | N87: 1 | O87: Medición | P87: Primaria | Q87: Oculta | R87: Calibración | S87: FABRICANTE | T87: F-MET-210
A88: Equipo de Medicion sin Contacto · DIC41–DIC42 | B88: F-MET-237 | C88: Medir | D88: el descentramiento del hilo | E88: con exactitud de ±_____ | F88: mm | G88: =TRIM(CONCATENATE(C88," ",D88," ",E88," ",F88)) -> Medir el descentramiento del hilo con exactitud de ±_____ mm | H88: Significativa – Operación | I88: MET-MAU-DIC41-MED-MEI01 | K88: Falta: exactitud del sistema de medición. | L88: Equipo DE Medicion SIN Contacto | M88: |MET-MAU-DIC41-MED-MEI01| | N88: 1 | O88: Medición | P88: Secundaria | Q88: Oculta | R88: Calibración | S88: FABRICANTE | T88: Nueva (dato medible del estudio) | U88: Equipo que mide, sin contacto, la altura y el descentramiento del hilo de contacto respecto al eje de la vía. | V88: Definición técnica de trabajo (ingeniería ferroviaria) | W88: Medir el descentramiento del hilo [ESTÁNDAR POR CONFIRMAR]
A89: Pantografo (×2) · DIC41–DIC42 | B89: F-MET-238 | C89: Mantener | D89: la fuerza de contacto | E89: de 60 a 140 | F89: N | G89: =TRIM(CONCATENATE(C89," ",D89," ",E89," ",F89)) -> Mantener la fuerza de contacto de 60 a 140 N | H89: Significativa – Operación | I89: MET-MAU-DIC41-MED-PAT01 | J89: Faiveley (Wabtec) | K89: Rango de pantógrafos de metro equivalentes; validar con la ficha del pantógrafo de medición. | L89: Pantografo | M89: |MET-MAU-DIC41-MED-PAT01|MET-MAU-DIC42-MED-PAT01| | N89: 2 | O89: Medición | P89: Primaria | Q89: Evidente | R89: Dinamómetro | S89: FUENTE TÉCNICA | T89: F-MET-211, F-MET-232 | U89: Equipo montado en un vehículo ferroviario para captar corriente de un hilo de contacto o de un riel conductor. | V89: ISO/DIS 22575:2024 (borrador), consultada en el glosario de la ERA | W89: Mantener la fuerza de contacto de 60 a 140 N
A90: Sistema Traccion (×2) · DIC41–DIC42 | B90: F-MET-240 | C90: Circular | D90: por la vía | E90: hasta 40 | F90: km/h | G90: =TRIM(CONCATENATE(C90," ",D90," ",E90," ",F90)) -> Circular por la vía hasta 40 km/h | H90: Significativa – Operación | I90: MET-MAU-DIC41-TRC | J90: Manual de Mantenimiento DR1227 Plasser & Theurer DIC-40 (WS6761) – p.47 | L90: Sistema Traccion | M90: |MET-MAU-DIC41-TRC|MET-MAU-DIC42-TRC| | N90: 2 | O90: Operación | P90: Primaria | Q90: Evidente | R90: Velocímetro | S90: FABRICANTE | T90: Nueva (dato medible del estudio) | U90: Conjunto de motor, transmisión y ejes que desarrolla el esfuerzo tractor para desplazar el vehículo. | V90: Definición técnica de trabajo (ingeniería ferroviaria) | W90: Circular por la vía hasta 40 km/h
A91: Motor Diesel (×2) · DIC41–DIC42 | B91: F-MET-241 | C91: Entregar | D91: potencia mecánica | E91: de _____ | F91: kW | G91: =TRIM(CONCATENATE(C91," ",D91," ",E91," ",F91)) -> Entregar potencia mecánica de _____ kW | H91: Significativa – Operación | I91: MET-MAU-DIC41-TRC-MOR01 | K91: Falta: potencia nominal y velocidad (placa del motor). | L91: Motor Diesel | M91: |MET-MAU-DIC41-TRC-MOR01|MET-MAU-DIC42-TRC-MOR01| | N91: 2 | O91: Operación | P91: Primaria | Q91: Evidente | R91: Placa del motor | S91: FABRICANTE | T91: F-MET-214, F-MET-235 | U91: Motor de combustión interna de ciclo diésel que convierte la energía química del combustible en potencia mecánica en el eje. Su desempeño se expresa en potencia (kW) y velocidad (rpm). | V91: Definición técnica de trabajo; parámetros y unidades según ISO 14224, clase Motores de combustión (kW, rpm) | W91: Entregar potencia mecánica [ESTÁNDAR POR CONFIRMAR]
A92: Caja DE Engranaje Distribuidor (×2) · DIC41–DIC42 | B92: F-MET-246 | C92: Distribuir | D92: el par entre ejes | E92: hasta _____ | F92: N·m | G92: =TRIM(CONCATENATE(C92," ",D92," ",E92," ",F92)) -> Distribuir el par entre ejes hasta _____ N·m | H92: Significativa – Operación | I92: MET-MAU-DIC41-TRN-CAJA01 | K92: Falta: la relación de transmisión. | L92: Caja DE Engranaje Distribuidor | M92: |MET-MAU-DIC41-TRN-CAJA01|MET-MAU-DIC42-TRN-CAJA01| | N92: 2 | O92: Operación | P92: Primaria | Q92: Evidente | R92: Prueba de tracción / termografía y ruido | S92: FABRICANTE | T92: F-MET-215, F-MET-236 | U92: Caja de engranajes que reparte el par del motor entre los ejes del vehículo. | V92: Definición técnica de trabajo (ingeniería ferroviaria) | W92: Distribuir el par entre ejes [ESTÁNDAR POR CONFIRMAR]
A93: Eje Tractor (×3) · DIC41–DIC42 | B93: F-MET-249 | C93: Soportar | D93: la carga por eje | E93: hasta _____ | F93: t | G93: =TRIM(CONCATENATE(C93," ",D93," ",E93," ",F93)) -> Soportar la carga por eje hasta _____ t | H93: Significativa – Seguridad/Ambiental | I93: MET-MAU-DIC41-TRN-EJT01 | K93: Falta: carga por eje. | L93: Eje Tractor 1 | M93: |MET-MAU-DIC41-TRN-EJT01|MET-MAU-DIC41-TRN-EJT02|MET-MAU-DIC42-TRN-EJT01| | N93: 3 | O93: Soporte | P93: Secundaria | Q93: Oculta | R93: Pesaje | S93: FABRICANTE | T93: F-MET-216, F-MET-217, F-MET-237 | U93: Conjunto formado por un par de ruedas y el eje que las une. Los discos de freno y los rodamientos montados sobre el eje o las ruedas se consideran parte del eje montado. En este caso es un eje propulsado: recibe el par del sistema de tracción. | V93: ISO/DIS 22575:2024 (borrador), consultada en el glosario de la ERA | W93: Soportar la carga por eje [ESTÁNDAR POR CONFIRMAR]
A94: Eje Tractor (×3) · DIC41–DIC42 | B94: F-MET-250 | C94: Impedir | D94: el remonte de pestaña | E94: con cota qR ≥ 6,5 | F94: mm | G94: =TRIM(CONCATENATE(C94," ",D94," ",E94," ",F94)) -> Impedir el remonte de pestaña con cota qR ≥ 6,5 mm | H94: Significativa – Seguridad/Ambiental | I94: MET-MAU-DIC41-TRN-EJT01 | J94: TSI LOC&PAS / OTIF UTP LOC&PAS, tablas 1 y 2 | K94: qR: cota de la cara activa de la pestaña (galga de perfil). | L94: Eje Tractor 1 | M94: |MET-MAU-DIC41-TRN-EJT01|MET-MAU-DIC41-TRN-EJT02|MET-MAU-DIC42-TRN-EJT01| | N94: 3 | O94: Seguridad | P94: Primaria | Q94: Oculta | R94: Galga de perfil | S94: NORMA | T94: Nueva (dato medible del estudio) | U94: Conjunto formado por un par de ruedas y el eje que las une. Los discos de freno y los rodamientos montados sobre el eje o las ruedas se consideran parte del eje montado. En este caso es un eje propulsado: recibe el par del sistema de tracción. | V94: ISO/DIS 22575:2024 (borrador), consultada en el glosario de la ERA | W94: Impedir el remonte de pestaña con cota qR ≥ 6,5 mm
A95: Eje Tractor (×3) · DIC41–DIC42 | B95: F-MET-251 | C95: Mantener | D95: la distancia entre ruedas | E95: de 1.357 a 1.363 | F95: mm | G95: =TRIM(CONCATENATE(C95," ",D95," ",E95," ",F95)) -> Mantener la distancia entre ruedas de 1.357 a 1.363 mm | H95: Significativa – Seguridad/Ambiental | I95: MET-MAU-DIC41-TRN-EJT01 | J95: TSI LOC&PAS / OTIF UTP LOC&PAS, tablas 1 y 2 | K95: Distancia entre caras internas; asegura el juego rueda-carril en vía de 1.435 mm. Límite TSI según diámetro: ≥ 1.357 (> 840 mm), 1.358–1.363 (760–840 mm), ≥ 1.359 (≤ 760 mm). | L95: Eje Tractor 1 | M95: |MET-MAU-DIC41-TRN-EJT01|MET-MAU-DIC41-TRN-EJT02|MET-MAU-DIC42-TRN-EJT01| | N95: 3 | O95: Seguridad | P95: Secundaria | Q95: Oculta | R95: Calibre | S95: NORMA | T95: Nueva (dato medible del estudio) | U95: Conjunto formado por un par de ruedas y el eje que las une. Los discos de freno y los rodamientos montados sobre el eje o las ruedas se consideran parte del eje montado. En este caso es un eje propulsado: recibe el par del sistema de tracción. | V95: ISO/DIS 22575:2024 (borrador), consultada en el glosario de la ERA | W95: Mantener la distancia entre ruedas de 1.357 a 1.363 mm
A96: Eje Tractor (×3) · DIC41–DIC42 | B96: F-MET-252 | C96: Guiar | D96: el eje | E96: con pestaña de _____ | F96: mm | G96: =TRIM(CONCATENATE(C96," ",D96," ",E96," ",F96)) -> Guiar el eje con pestaña de _____ mm | H96: Significativa – Seguridad/Ambiental | I96: MET-MAU-DIC41-TRN-EJT01 | K96: Falta: diámetro de rueda de la máquina para fijar el límite de espesor de pestaña Sd. Límite TSI: 25 a 33 mm (rueda de 760 a 840 mm); 22 a 33 mm (rueda > 840 mm). | L96: Eje Tractor 1 | M96: |MET-MAU-DIC41-TRN-EJT01|MET-MAU-DIC41-TRN-EJT02|MET-MAU-DIC42-TRN-EJT01| | N96: 3 | O96: Seguridad | P96: Secundaria | Q96: Oculta | R96: Galga de perfil | S96: FABRICANTE | T96: Nueva (dato medible del estudio) | U96: Conjunto formado por un par de ruedas y el eje que las une. Los discos de freno y los rodamientos montados sobre el eje o las ruedas se consideran parte del eje montado. En este caso es un eje propulsado: recibe el par del sistema de tracción. | V96: ISO/DIS 22575:2024 (borrador), consultada en el glosario de la ERA | W96: Guiar el eje [ESTÁNDAR POR CONFIRMAR]
A97: Dresina Inspeccion de Catenaria Tipo 2 | B97: F-MET-254 | C97: Recorrer | D97: curvas | E97: con radio mínimo de 90 | F97: m | G97: =TRIM(CONCATENATE(C97," ",D97," ",E97," ",F97)) -> Recorrer curvas con radio mínimo de 90 m | H97: Significativa – Seguridad/Ambiental | I97: MET-MAU-DIC42 | J97: Manual de Mantenimiento DR1227 Plasser & Theurer DIC-40 (WS6761) – p.47 | L97: Dresina Inspeccion de Catenaria Tipo 2 | M97: |MET-MAU-DIC42| | N97: 1 | O97: Seguridad | P97: Secundaria | Q97: Evidente | R97: Prueba en curva | S97: FABRICANTE | T97: Nueva (dato medible del estudio) | U97: Vehículo ferroviario de servicio equipado para inspeccionar la catenaria. | V97: Definición técnica de trabajo (ingeniería ferroviaria) | W97: Recorrer curvas de radio 90 m mínimo
A98: Brazo Estabilizador · DIC42 | B98: F-MET-257 | C98: Evitar | D98: el vuelco de la máquina en izaje | E98: con momento de _____ | F98: kN·m | G98: =TRIM(CONCATENATE(C98," ",D98," ",E98," ",F98)) -> Evitar el vuelco de la máquina en izaje con momento de _____ kN·m | H98: Significativa – Seguridad/Ambiental | I98: MET-MAU-DIC42-ELV-BES01 | K98: Falta: fuerza de apoyo. | L98: Brazo Estabilizador | M98: |MET-MAU-DIC42-ELV-BES01| | N98: 1 | O98: Seguridad | P98: Primaria | Q98: Evidente | R98: Prueba funcional | S98: FABRICANTE | T98: F-MET-225 | U98: Apoyo extensible que fija la máquina durante el izaje para evitar el vuelco. | V98: Definición técnica de trabajo (ingeniería ferroviaria) | W98: Estabilizar la máquina en izaje [ESTÁNDAR POR CONFIRMAR]
A99: Enganche Automatico Alliance · DIC41–DIC42 | B99: F-MET-258 | C99: Acoplar | D99: vehículos | E99: con tracción de _____ | F99: kN | G99: =TRIM(CONCATENATE(C99," ",D99," ",E99," ",F99)) -> Acoplar vehículos con tracción de _____ kN | H99: Significativa – Operación | I99: MET-MAU-DIC42-ENA-EAL01 | K99: Falta: resistencia del enganche Alliance. | L99: Enganche Automatico Alliance | M99: |MET-MAU-DIC42-ENA-EAL01| | N99: 1 | O99: Interfaz | P99: Primaria | Q99: Evidente | R99: Prueba de acople | S99: FABRICANTE | T99: F-MET-227 | U99: Equipo montado en el vehículo para conectar vehículos ferroviarios, transferir los esfuerzos de tracción y frenado y disipar la energía de compresión. Es un dispositivo mecánico que, opcionalmente, también transfiere potencia, datos o aire entre vehículos. El tipo automático acopla al aproximar los vehículos, sin maniobra manual. | V99: ISO/DIS 22575:2024 (borrador), consultada en el glosario de la ERA | W99: Acoplar vehículos [ESTÁNDAR POR CONFIRMAR]
A100: Enganche Automatico Alliance · DIC41–DIC42 | B100: F-MET-260 | C100: Mantener | D100: la altura del enganche | E100: entre _____ y _____ | F100: mm | G100: =TRIM(CONCATENATE(C100," ",D100," ",E100," ",F100)) -> Mantener la altura del enganche entre _____ y _____ mm | H100: Significativa – Seguridad/Ambiental | I100: MET-MAU-DIC42-ENA-EAL01 | K100: Falta: altura nominal y tolerancia. | L100: Enganche Automatico Alliance | M100: |MET-MAU-DIC42-ENA-EAL01| | N100: 1 | O100: Interfaz | P100: Secundaria | Q100: Evidente | R100: Medición cada 500 h (DR1227 pág. 77) | S100: FABRICANTE | T100: Nueva (dato medible del estudio) | U100: Equipo montado en el vehículo para conectar vehículos ferroviarios, transferir los esfuerzos de tracción y frenado y disipar la energía de compresión. Es un dispositivo mecánico que, opcionalmente, también transfiere potencia, datos o aire entre vehículos. El tipo automático acopla al aproximar los vehículos, sin maniobra manual. | V100: ISO/DIS 22575:2024 (borrador), consultada en el glosario de la ERA | W100: Mantener la altura del enganche [ESTÁNDAR POR CONFIRMAR]
...

Sheet Análisis RCM
A1: ID FUNCIÓN | B1: ELEMENTO DE ESTUDIO | C1: FUNCIÓN | D1: FALLA FUNCIONAL | E1: MODO DE FALLA | F1: EFECTOS DE FALLA | G1: FALLA POTENCIAL | H1: CONSECUENCIA | I1: CRITERIOS MÁS CRÍTICOS | J1: 1A ¿El modo de falla es evidente para la tripulación/operador bajo condiciones normales de operación? | K1: 1B ¿Se puede definir una tarea de búsqueda de falla técnicamente factible que revele la falla oculta y sea rentable realizarla a un intervalo adecuado? | L1: 1C ¿La falla oculta combinada con una segunda falla tiene graves consecuencias de seguridad o medio ambiente? | M1: 2A ¿La falla tiene consecuencias de seguridad o medio ambiente (incumple regulaciones, lesiona personal, causa daño ambiental)? | N1: 3A ¿Existe una tarea proactiva (CBM, basada en tiempo/uso) técnicamente factible que pueda mitigar la probabilidad de la falla a un nivel aceptable? | O1: 4A ¿La falla tiene consecuencias operacionales (afecta producción, eficiencia, calidad, servicio al cliente)? | P1: 5A ¿Existe una tarea de mantenimiento basado en condición (CBM) técnicamente factible y rentable? | Q1: 5B ¿Existe una tarea de restauración o reemplazo programado (basada en tiempo/uso) técnicamente factible y rentable? | R1: 5C ¿El costo de la falla (pérdida de producción + reparación) es aceptable si la falla ocurre? | S1: 6A ¿El costo total del mantenimiento proactivo (inspecciones, paradas) es menor que el costo total de esperar a que falle y repararlo? | T1: 6B ¿Existe una tarea CBM o basada en tiempo/uso técnicamente factible? | U1: RESULTADO DEL ÁRBOL | V1: TIPO DE MANTENIMIENTO | W1: actividad | X1: frecuencia (meses) | Y1: RESPONSABLE
A2: F-MET-001 | B2: Vehículo de pasajeros | C2: {=INDEX(Funciones!$G$2:$G$372,MATCH($A2,Funciones!$B$2:$B$372,0))} -> Transportar pasajeros hasta 300 por coche | D2: No transporta pasajeros. La función se pierde por completo: no se cumple ningún punto del estándar. Estándar: hasta 300 por coche (contexto operacional: Wikipedia). Se verifica con: ficha. | E2: A. Tren inmovilizado por disparo del breaker principal | F2: 1. Local: El breaker principal se dispara y abre el circuito de potencia de alta tensión del tren. 2. En el equipo: Los convertidores y motores de tracción quedan sin alimentación y el tren pierde tracción. El tren se detiene en línea o no sale de patio y el centro de control recibe la novedad de tren inmovilizado. 3. General: El tren sale de circulación y los pasajeros no se transportan hasta que se restablece la alimentación. | G2: No hay una condición detectable que avise con anticipación: el breaker principal dispara de forma súbita. Se detecta con: prueba funcional programada; registro de eventos y alarmas del equipo. | H2: {=_xlfn.XLOOKUP(E:E,'Calificación consecuencia'!B:B,'Calificación consecuencia'!K:K,"No encontrada",2)} -> Alta | I2: Impacto a la operación; Continuidad operacional | J2: Sí | M2: Sí | N2: No | U2: sustitición cíclica | V2: sustitición cíclica | W2: Cambio de breaker | X2: 12 | Y2: técnico electricista
A3: F-MET-001 | B3: Vehículo de pasajeros | C3: {=INDEX(Funciones!$G$2:$G$372,MATCH($A3,Funciones!$B$2:$B$372,0))} -> Transportar pasajeros hasta 300 por coche | D3: No transporta pasajeros. La función se pierde por completo: no se cumple ningún punto del estándar. Estándar: hasta 300 por coche (contexto operacional: Wikipedia). Se verifica con: ficha. | E3: A. Tren inmovilizado por pérdida de presión en el circuito principal de aire | F3: 1. Local: Se pierde presión en el circuito principal de aire: el compresor no alcanza a reponer el aire y la presión cae por debajo del mínimo de operación. 2. En el equipo: Los equipos neumáticos (freno, puertas, suspensión) no reciben la presión de trabajo; el freno se aplica por baja presión. El tren se inmoviliza con el freno aplicado y no puede arrancar. 3. General: El tren sale de circulación hasta recuperar la presión del circuito. | G3: Mayor tiempo de recarga o presión que no se sostiene en el circuito principal de aire. Se detecta con: lectura de manómetros; prueba de caída de presión del circuito. | H3: {=_xlfn.XLOOKUP(E:E,'Calificación consecuencia'!B:B,'Calificación consecuencia'!K:K,"No encontrada",2)} -> Media | I3: Impacto a la operación; Continuidad operacional | J3: Sí | M3: Sí | N3: Sí | U3: Tarea proactiva obligatoria: basada en condición (CBM) | V3: Predictivo (basado en condición)
A4: F-MET-001 | B4: Vehículo de pasajeros | C4: {=INDEX(Funciones!$G$2:$G$372,MATCH($A4,Funciones!$B$2:$B$372,0))} -> Transportar pasajeros hasta 300 por coche | D4: No transporta pasajeros. La función se pierde por completo: no se cumple ningún punto del estándar. Estándar: hasta 300 por coche (contexto operacional: Wikipedia). Se verifica con: ficha. | E4: A. Coche dañado por impacto con un obstáculo en la vía | F4: 1. Local: El coche golpea un obstáculo en la vía y su caja recibe el impacto; se deforman o rompen los elementos de la estructura y de los equipos de la zona golpeada. 2. En el equipo: El coche queda con daño estructural y con equipos de la zona afectada fuera de funcionamiento. El tren no puede continuar su recorrido y se detiene en el sitio. 3. General: El tren sale de circulación y el servicio se interrumpe hasta retirarlo de la vía. | G4: No hay una condición detectable que avise con anticipación: el impacto con el obstáculo es un evento súbito y externo. Se detecta con: inspección visual de la vía y registro de eventos del tren. | H4: {=_xlfn.XLOOKUP(E:E,'Calificación consecuencia'!B:B,'Calificación consecuencia'!K:K,"No encontrada",2)} -> Media | I4: Impacto a la operación; Continuidad operacional | J4: Sí | M4: Sí | N4: No | U4: Rediseño | V4: Rediseño
A5: F-MET-001 | B5: Vehículo de pasajeros | C5: {=INDEX(Funciones!$G$2:$G$372,MATCH($A5,Funciones!$B$2:$B$372,0))} -> Transportar pasajeros hasta 300 por coche | D5: No transporta pasajeros. La función se pierde por completo: no se cumple ningún punto del estándar. Estándar: hasta 300 por coche (contexto operacional: Wikipedia). Se verifica con: ficha. | E5: A. Módulo de potencia del convertidor disparado por ducto de aire obstruido | F5: 1. Local: Los ductos de aire del convertidor se obstruyen y el módulo de potencia se sobrecalienta hasta que su protección térmica lo dispara. 2. En el equipo: El convertidor deja de entregar potencia a los motores y el tren pierde tracción. El conductor reporta paradas y arranques no programados sin una causa fija, porque el módulo se rearma al enfriarse y se vuelve a disparar. 3. General: Se afecta el cumplimiento de los tiempos de recorrido y se afecta el servicio del tren. | G5: Pérdida de potencia y caída de presión o de caudal en el módulo de potencia del convertidor por ducto de aire obstruido. Se detecta con: lectura de presión y de presión diferencial; inspección del filtro y del circuito. | H5: {=_xlfn.XLOOKUP(E:E,'Calificación consecuencia'!B:B,'Calificación consecuencia'!K:K,"No encontrada",2)} -> Media | I5: Impacto a la operación; Continuidad operacional | J5: Sí | M5: Sí | N5: Sí | U5: Tarea proactiva obligatoria: basada en condición (CBM) | V5: Predictivo (basado en condición)
A6: F-MET-001 | B6: Vehículo de pasajeros | C6: {=INDEX(Funciones!$G$2:$G$372,MATCH($A6,Funciones!$B$2:$B$372,0))} -> Transportar pasajeros hasta 300 por coche | D6: No transporta pasajeros. La función se pierde por completo: no se cumple ningún punto del estándar. Estándar: hasta 300 por coche (contexto operacional: Wikipedia). Se verifica con: ficha. | E6: A. Contactos del breaker principal picados por arco eléctrico repetido | F6: 1. Local: Los contactos del breaker principal se pican por los arcos repetidos: la superficie de contacto se reduce y la resistencia de paso aumenta. 2. En el equipo: El breaker se calienta y su apertura o cierre se vuelve inestable; la alimentación de alta tensión se interrumpe de forma intermitente. El conductor reporta paradas y arranques no programados sin una causa fija. 3. General: El servicio se interrumpe de forma repetida y el tren termina fuera de circulación. | G6: No hay una condición detectable que avise con anticipación: los contactos del breaker principal dejan de funcionar de forma súbita. Se detecta con: prueba funcional programada; registro de eventos y alarmas del equipo. | H6: {=_xlfn.XLOOKUP(E:E,'Calificación consecuencia'!B:B,'Calificación consecuencia'!K:K,"No encontrada",2)} -> Media | I6: Impacto a la operación; Continuidad operacional | J6: Sí | M6: Sí | N6: No | U6: Rediseño | V6: Rediseño
A7: F-MET-001 | B7: Vehículo de pasajeros | C7: {=INDEX(Funciones!$G$2:$G$372,MATCH($A7,Funciones!$B$2:$B$372,0))} -> Transportar pasajeros hasta 300 por coche | D7: Transporta menos de 300 pasajeros por coche. Estándar: hasta 300 por coche (contexto operacional: Wikipedia). Se verifica con: ficha. | E7: B. Coche aislado por puertas bloqueadas | F7: 1. Local: Una o más puertas del coche quedan bloqueadas, no abren y se aíslan del sistema. 2. En el equipo: Las puertas aisladas no se utilizan para el ingreso ni la salida y el coche queda con menos accesos. El coche sale con capacidad reducida y la ocupación se limita por debajo de los 300 pasajeros. 3. General: El tren transporta menos pasajeros por viaje y los tiempos de parada en estación se alargan. | G7: Puertas con apertura o cierre cada vez más lentos y errores de cierre repetidos en el pupitre del conductor. Se detecta con: revisión del registro de fallas de puertas; medición de tiempos de ciclo. | H7: {=_xlfn.XLOOKUP(E:E,'Calificación consecuencia'!B:B,'Calificación consecuencia'!K:K,"No encontrada",2)} -> Baja | I7: Continuidad operacional; Impacto a la operación | J7: Sí | M7: No | O7: Sí | P7: Sí | U7: Tarea CBM programada | V7: Predictivo (basado en condición)
A8: F-MET-001 | B8: Vehículo de pasajeros | C8: {=INDEX(Funciones!$G$2:$G$372,MATCH($A8,Funciones!$B$2:$B$372,0))} -> Transportar pasajeros hasta 300 por coche | D8: Transporta menos de 300 pasajeros por coche. Estándar: hasta 300 por coche (contexto operacional: Wikipedia). Se verifica con: ficha. | E8: B. Freno del coche aplicado por distribuidor KE atascado en posición de apretado | F8: 1. Local: El distribuidor KE queda atascado en la posición de apretado y mantiene aire en los cilindros del freno del coche. 2. En el equipo: Las zapatas permanecen aplicadas contra la rueda aunque el conductor suelte el freno. El coche se aísla del tren o debe operar con el freno arrastrando y con menor ocupación. 3. General: La capacidad de transporte del tren se limita y los tiempos de recorrido aumentan. | G8: Respuesta más lenta o movimiento duro del freno del coche antes de quedar trabado. Se detecta con: prueba funcional; medición de tiempos de ciclo. | H8: {=_xlfn.XLOOKUP(E:E,'Calificación consecuencia'!B:B,'Calificación consecuencia'!K:K,"No encontrada",2)} -> Baja | I8: Continuidad operacional; Impacto a la operación | J8: Sí | M8: No | O8: Sí | P8: Sí | U8: Tarea CBM programada | V8: Predictivo (basado en condición)
A9: F-MET-004 | B9: Sistema de puertas de viajeros | C9: {=INDEX(Funciones!$G$2:$G$372,MATCH($A9,Funciones!$B$2:$B$372,0))} -> Bloquear la tracción con 0 arranques con puerta abierta | D9: No bloquea la tracción. La función se pierde por completo: no se cumple ningún punto del estándar. Estándar: con 0 arranques con puerta abierta (norma). Se verifica con: comprobación de seguridad (PM-2012 pág. 20). | E9: A. Lazo de puertas cerradas en cortocircuito por aislamiento del cable dañado | F9: 1. Local: El aislamiento del cable del lazo de puertas cerradas se daña y el lazo se pone en cortocircuito: el circuito siempre indica puertas cerradas, sin importar su estado real. 2. En el equipo: El sistema de mando no recibe la señal de puerta abierta. En servicio no se nota; se descubre en la comprobación de seguridad del lazo de puertas (PM-2012 pág. 20), cuando el tren no se bloquea con una puerta abierta. 3. General: La tracción no se bloquea con puertas abiertas y la función queda sin respaldo de bloqueo hasta la comprobación. | G9: Aumento de temperatura, de consumo de corriente o caída de la resistencia de aislamiento del lazo de puertas cerradas. Se detecta con: termografía; medición de corriente; prueba de aislamiento (megóhmetro). Al ser una función oculta no se nota en operación: depende de la inspección o prueba programada. | H9: {=_xlfn.XLOOKUP(E:E,'Calificación consecuencia'!B:B,'Calificación consecuencia'!K:K,"No encontrada",2)} -> Media | I9: Seguridad; Continuidad operacional | J9: No | K9: Sí | U9: Tarea de búsqueda de falla programada | V9: Detectivo (búsqueda de falla)
A10: F-MET-004 | B10: Sistema de puertas de viajeros | C10: {=INDEX(Funciones!$G$2:$G$372,MATCH($A10,Funciones!$B$2:$B$372,0))} -> Bloquear la tracción con 0 arranques con puerta abierta | D10: No bloquea la tracción. La función se pierde por completo: no se cumple ningún punto del estándar. Estándar: con 0 arranques con puerta abierta (norma). Se verifica con: comprobación de seguridad (PM-2012 pág. 20). | E10: A. Relé de puertas cerradas pegado por contactos soldados | F10: 1. Local: Los contactos del relé de puertas cerradas se sueldan entre sí y el relé queda pegado en posición cerrada. 2. En el equipo: El circuito del lazo de puertas continúa señalando puertas cerradas aunque alguna esté abierta. En servicio no se nota; se descubre en la comprobación de seguridad del lazo de puertas. 3. General: La tracción no se bloquea con puertas abiertas y la función queda sin respaldo de bloqueo. | G10: Respuesta más lenta o movimiento duro del relé de puertas cerradas antes de quedar trabado. Se detecta con: prueba funcional; medición de tiempos de ciclo. Al ser una función oculta no se nota en operación: depende de la inspección o prueba programada. | H10: {=_xlfn.XLOOKUP(E:E,'Calificación consecuencia'!B:B,'Calificación consecuencia'!K:K,"No encontrada",2)} -> Baja | I10: Seguridad; Continuidad operacional | J10: No | K10: Sí | U10: Tarea de búsqueda de falla programada | V10: Detectivo (búsqueda de falla)
A11: F-MET-004 | B11: Sistema de puertas de viajeros | C11: {=INDEX(Funciones!$G$2:$G$372,MATCH($A11,Funciones!$B$2:$B$372,0))} -> Bloquear la tracción con 0 arranques con puerta abierta | D11: No bloquea la tracción. La función se pierde por completo: no se cumple ningún punto del estándar. Estándar: con 0 arranques con puerta abierta (norma). Se verifica con: comprobación de seguridad (PM-2012 pág. 20). | E11: A. Final de carrera de puerta desajustado por vibración | F11: 1. Local: El final de carrera de la puerta se desajusta por vibración y deja de accionarse cuando la hoja se abre. 2. En el equipo: El lazo de puertas mantiene la señal de puerta cerrada. En servicio no se nota; se descubre en la comprobación de seguridad del lazo de puertas. 3. General: La tracción no se bloquea con esa puerta abierta. | G11: Deriva del final de carrera de puerta frente al valor patrón, con lecturas o ajustes que se van corriendo. Se detecta con: verificación contra patrón calibrado; lectura de parámetros; medición de alineación o vibración. Al ser una función oculta no se nota en operación: depende de la inspección o prueba programada. | H11: {=_xlfn.XLOOKUP(E:E,'Calificación consecuencia'!B:B,'Calificación consecuencia'!K:K,"No encontrada",2)} -> Media | I11: Seguridad; Continuidad operacional | J11: No | K11: Sí | U11: Tarea de búsqueda de falla programada | V11: Detectivo (búsqueda de falla)
A12: F-MET-004 | B12: Sistema de puertas de viajeros | C12: {=INDEX(Funciones!$G$2:$G$372,MATCH($A12,Funciones!$B$2:$B$372,0))} -> Bloquear la tracción con 0 arranques con puerta abierta | D12: No bloquea la tracción. La función se pierde por completo: no se cumple ningún punto del estándar. Estándar: con 0 arranques con puerta abierta (norma). Se verifica con: comprobación de seguridad (PM-2012 pág. 20). | E12: A. Contacto del relé de puertas sulfatado por humedad en el conector | F12: 1. Local: El contacto del relé de puertas se sulfata por la humedad que entra al conector y la señal pasa de forma irregular. 2. En el equipo: El lazo de puertas cambia de estado sin patrón. El bloqueo funciona y deja de funcionar sin patrón; solo se detecta por reportes aislados o en prueba. 3. General: La función de bloqueo es poco confiable y no puede asegurarse su actuación en cada arranque. | G12: Óxido, picaduras o sulfatación visibles del contacto del relé de puertas. Se detecta con: inspección visual; medición de resistencia de contacto o de tensión en bornes. Al ser una función oculta no se nota en operación: depende de la inspección o prueba programada. | H12: {=_xlfn.XLOOKUP(E:E,'Calificación consecuencia'!B:B,'Calificación consecuencia'!K:K,"No encontrada",2)} -> Media | I12: Seguridad; Continuidad operacional | J12: No | K12: Sí | U12: Tarea de búsqueda de falla programada | V12: Detectivo (búsqueda de falla)
A13: F-MET-004 | B13: Sistema de puertas de viajeros | C13: {=INDEX(Funciones!$G$2:$G$372,MATCH($A13,Funciones!$B$2:$B$372,0))} -> Bloquear la tracción con 0 arranques con puerta abierta | D13: No bloquea la tracción. La función se pierde por completo: no se cumple ningún punto del estándar. Estándar: con 0 arranques con puerta abierta (norma). Se verifica con: comprobación de seguridad (PM-2012 pág. 20). | E13: A. Conector de puerta flojo por vibración | F13: 1. Local: El conector de la puerta se afloja por vibración y el contacto eléctrico se vuelve intermitente. 2. En el equipo: La señal del lazo de puertas se interrumpe y se restablece sin patrón. El bloqueo funciona y deja de funcionar sin patrón; solo se detecta por reportes aislados o en prueba. 3. General: La función de bloqueo es poco confiable y no puede asegurarse su actuación en cada arranque. | G13: Pérdida de apriete, holgura o marcas de testigo desalineadas del conector de puerta. Se detecta con: control de torque con llave; inspección visual de marcas de testigo. Al ser una función oculta no se nota en operación: depende de la inspección o prueba programada. | H13: {=_xlfn.XLOOKUP(E:E,'Calificación consecuencia'!B:B,'Calificación consecuencia'!K:K,"No encontrada",2)} -> Media | I13: Seguridad; Continuidad operacional | J13: No | K13: Sí | U13: Tarea de búsqueda de falla programada | V13: Detectivo (búsqueda de falla)
A14: F-MET-004 | B14: Sistema de puertas de viajeros | C14: {=INDEX(Funciones!$G$2:$G$372,MATCH($A14,Funciones!$B$2:$B$372,0))} -> Bloquear la tracción con 0 arranques con puerta abierta | D14: Bloquea la tracción solo con parte de las puertas supervisadas. Estándar: con 0 arranques con puerta abierta (norma). Se verifica con: comprobación de seguridad (PM-2012 pág. 20). | E14: B. Final de carrera de puerta desajustado por vibración | F14: 1. Local: El final de carrera de una puerta se desajusta por vibración y no detecta la apertura de esa hoja. 2. En el equipo: El lazo ignora esa puerta; las demás siguen supervisadas. Una puerta abierta no genera bloqueo y la prueba lo revela solo en ese punto. 3. General: El bloqueo de tracción actúa con parte de las puertas y queda sin supervisión la puerta afectada. | G14: Deriva del final de carrera de puerta frente al valor patrón, con lecturas o ajustes que se van corriendo. Se detecta con: verificación contra patrón calibrado; lectura de parámetros; medición de alineación o vibración. Al ser una función oculta no se nota en operación: depende de la inspección o prueba programada. | H14: {=_xlfn.XLOOKUP(E:E,'Calificación consecuencia'!B:B,'Calificación consecuencia'!K:K,"No encontrada",2)} -> Media | I14: Seguridad; Continuidad operacional | J14: No | K14: Sí | U14: Tarea de búsqueda de falla programada | V14: Detectivo (búsqueda de falla)
A15: F-MET-004 | B15: Sistema de puertas de viajeros | C15: {=INDEX(Funciones!$G$2:$G$372,MATCH($A15,Funciones!$B$2:$B$372,0))} -> Bloquear la tracción con 0 arranques con puerta abierta | D15: Bloquea la tracción solo con parte de las puertas supervisadas. Estándar: con 0 arranques con puerta abierta (norma). Se verifica con: comprobación de seguridad (PM-2012 pág. 20). | E15: B. Cableado de supervisión cortado por rozamiento con la estructura de la puerta | F15: 1. Local: El cableado de supervisión se corta por el rozamiento con la estructura de la puerta y se pierde la señal de esa puerta. 2. En el equipo: El lazo de puertas deja de recibir la información de esa hoja. Una puerta abierta no genera bloqueo y la prueba lo revela solo en ese punto. 3. General: El bloqueo de tracción actúa con parte de las puertas y queda sin supervisión la puerta afectada. | G15: Grietas, resequedad, abultamientos o rozaduras visibles del cableado de supervisión. Se detecta con: inspección visual. Al ser una función oculta no se nota en operación: depende de la inspección o prueba programada. | H15: {=_xlfn.XLOOKUP(E:E,'Calificación consecuencia'!B:B,'Calificación consecuencia'!K:K,"No encontrada",2)} -> Media | I15: Seguridad; Continuidad operacional | J15: No | K15: Sí | U15: Tarea de búsqueda de falla programada | V15: Detectivo (búsqueda de falla)
A16: F-MET-005 | B16: Sistema de puertas de viajeros | C16: {=INDEX(Funciones!$G$2:$G$372,MATCH($A16,Funciones!$B$2:$B$372,0))} -> Permitir el intercambio de pasajeros con 24 puertas operativas | D16: No permite el intercambio de pasajeros. La función se pierde por completo: no se cumple ningún punto del estándar. Estándar: con 24 puertas operativas (diseño: Nombre del equipo en SAP (IW43_2021-28092026.xlsx)). Se verifica con: protocolo C.E8.92.203. | E16: A. Línea de aire de puertas despresurizada por fuga en el racor principal | F16: 1. Local: La línea de aire de las puertas se despresuriza por una fuga en el racor principal y el aire llega sin presión a los cilindros de las puertas. 2. En el equipo: Los actuadores neumáticos de las puertas no tienen fuerza para abrir ni cerrar. Ninguna puerta abre o cierra desde cabina y el conductor lo ve en el panel de puertas. 3. General: Los pasajeros no pueden subir ni bajar y el tren detiene su servicio en la estación. | G16: Humedad, goteo o pérdida de nivel o de presión alrededor de la línea de aire de puertas. Se detecta con: inspección visual; prueba de estanqueidad; lectura de nivel y presión. | H16: {=_xlfn.XLOOKUP(E:E,'Calificación consecuencia'!B:B,'Calificación consecuencia'!K:K,"No encontrada",2)} -> Media | I16: Impacto a la operación; Continuidad operacional | J16: Sí | M16: Sí | N16: Sí | U16: Tarea proactiva obligatoria: basada en condición (CBM) | V16: Predictivo (basado en condición)
A17: F-MET-005 | B17: Sistema de puertas de viajeros | C17: {=INDEX(Funciones!$G$2:$G$372,MATCH($A17,Funciones!$B$2:$B$372,0))} -> Permitir el intercambio de pasajeros con 24 puertas operativas | D17: No permite el intercambio de pasajeros. La función se pierde por completo: no se cumple ningún punto del estándar. Estándar: con 24 puertas operativas (diseño: Nombre del equipo en SAP (IW43_2021-28092026.xlsx)). Se verifica con: protocolo C.E8.92.203. | E17: A. Unidad de control de puertas (DCU) bloqueada por bloqueo del programa de control | F17: 1. Local: La unidad de control de puertas (DCU) se bloquea por un bloqueo del programa de control y deja de enviar órdenes a los motores de las puertas. 2. En el equipo: Las puertas no responden a las órdenes de apertura o cierre. Ninguna puerta abre o cierra desde cabina y el conductor lo ve en el panel de puertas. 3. General: Los pasajeros no pueden subir ni bajar y el tren detiene su servicio en la estación. | G17: No hay una condición detectable que avise con anticipación: la unidad de control de puertas (DCU) deja de funcionar de forma súbita. Se detecta con: prueba funcional programada; registro de eventos y alarmas del equipo. | H17: {=_xlfn.XLOOKUP(E:E,'Calificación consecuencia'!B:B,'Calificación consecuencia'!K:K,"No encontrada",2)} -> Baja | I17: Impacto a la operación; Continuidad operacional | J17: Sí | M17: Sí | N17: No | U17: Rediseño | V17: Rediseño
A18: F-MET-005 | B18: Sistema de puertas de viajeros | C18: {=INDEX(Funciones!$G$2:$G$372,MATCH($A18,Funciones!$B$2:$B$372,0))} -> Permitir el intercambio de pasajeros con 24 puertas operativas | D18: Permite el intercambio de pasajeros con menos de 24 puertas operativas. Estándar: con 24 puertas operativas (diseño: Nombre del equipo en SAP (IW43_2021-28092026.xlsx)). Se verifica con: protocolo C.E8.92.203. | E18: B. Motor de puerta quemado por roce del carro de la puerta | F18: 1. Local: El motor de la puerta se quema por el roce del carro de la puerta, que fuerza el motor por encima de su corriente nominal. 2. En el equipo: La puerta afectada no se mueve y el sistema la aísla. El panel de puertas muestra puertas aisladas y los pasajeros lo notan en el andén. 3. General: El coche queda con menos de 24 puertas operativas y el intercambio de pasajeros se hace por menos accesos. | G18: Aumento del consumo de corriente y del esfuerzo para mover el mecanismo, con calentamiento del motor de puerta. Se detecta con: medición de corriente; termografía; revisión del movimiento libre del mecanismo. | H18: {=_xlfn.XLOOKUP(E:E,'Calificación consecuencia'!B:B,'Calificación consecuencia'!K:K,"No encontrada",2)} -> Baja | I18: Continuidad operacional; Impacto a la operación | J18: Sí | M18: No | O18: Sí | P18: Sí | U18: Tarea CBM programada | V18: Predictivo (basado en condición)
A19: F-MET-005 | B19: Sistema de puertas de viajeros | C19: {=INDEX(Funciones!$G$2:$G$372,MATCH($A19,Funciones!$B$2:$B$372,0))} -> Permitir el intercambio de pasajeros con 24 puertas operativas | D19: Permite el intercambio de pasajeros con menos de 24 puertas operativas. Estándar: con 24 puertas operativas (diseño: Nombre del equipo en SAP (IW43_2021-28092026.xlsx)). Se verifica con: protocolo C.E8.92.203. | E19: B. Hoja de puerta trabada por guía deformada | F19: 1. Local: La guía de la hoja de puerta se deforma y la hoja se traba en su recorrido. 2. En el equipo: La puerta afectada no abre ni cierra completamente y se aísla. El panel de puertas muestra puertas aisladas y los pasajeros lo notan en el andén. 3. General: El coche queda con menos de 24 puertas operativas y el intercambio de pasajeros se hace por menos accesos. | G19: Respuesta más lenta o movimiento duro de la hoja de puerta antes de quedar trabado. Se detecta con: prueba funcional; medición de tiempos de ciclo. | H19: {=_xlfn.XLOOKUP(E:E,'Calificación consecuencia'!B:B,'Calificación consecuencia'!K:K,"No encontrada",2)} -> Baja | I19: Continuidad operacional; Impacto a la operación | J19: Sí | M19: No | O19: Sí | P19: Sí | U19: Tarea CBM programada | V19: Predictivo (basado en condición)
A20: F-MET-005 | B20: Sistema de puertas de viajeros | C20: {=INDEX(Funciones!$G$2:$G$372,MATCH($A20,Funciones!$B$2:$B$372,0))} -> Permitir el intercambio de pasajeros con 24 puertas operativas | D20: Permite el intercambio de pasajeros con menos de 24 puertas operativas. Estándar: con 24 puertas operativas (diseño: Nombre del equipo en SAP (IW43_2021-28092026.xlsx)). Se verifica con: protocolo C.E8.92.203. | E20: B. Detector de obstáculo descalibrado por suciedad en el sensor | F20: 1. Local: El sensor del detector de obstáculo se ensucia y se descalibra: detecta obstáculos que no existen. 2. En el equipo: La puerta interpreta un obstáculo en cada cierre y reabre. Las puertas abren y cierran con reaperturas que el conductor reporta repetidamente. 3. General: Los cierres se repiten y los tiempos de parada en estación se alargan. | G20: Deriva del detector de obstáculo frente al valor patrón, con lecturas o ajustes que se van corriendo. Se detecta con: verificación contra patrón calibrado; lectura de parámetros; medición de alineación o vibración. | H20: {=_xlfn.XLOOKUP(E:E,'Calificación consecuencia'!B:B,'Calificación consecuencia'!K:K,"No encontrada",2)} -> Media | I20: Continuidad operacional; Impacto a la operación | J20: Sí | M20: No | O20: Sí | P20: No | Q20: Sí | U20: Tarea basada en tiempo/uso programada | V20: Preventivo (basado en tiempo/uso)
A21: F-MET-005 | B21: Sistema de puertas de viajeros | C21: {=INDEX(Funciones!$G$2:$G$372,MATCH($A21,Funciones!$B$2:$B$372,0))} -> Permitir el intercambio de pasajeros con 24 puertas operativas | D21: Permite el intercambio de pasajeros con menos de 24 puertas operativas. Estándar: con 24 puertas operativas (diseño: Nombre del equipo en SAP (IW43_2021-28092026.xlsx)). Se verifica con: protocolo C.E8.92.203. | E21: B. Tarjeta de control de puerta inestable por soldaduras fatigadas | F21: 1. Local: Las soldaduras de la tarjeta de control de la puerta se fatigan y las pistas pierden contacto de forma intermitente. 2. En el equipo: La tarjeta ordena movimientos incompletos o reaperturas sin causa. Las puertas abren y cierran con reaperturas que el conductor reporta repetidamente. 3. General: Los cierres se repiten y los tiempos de parada en estación se alargan. | G21: Lecturas o comportamiento inestables de la tarjeta de control de puerta al vibrar o calentarse. Se detecta con: inspección visual de las soldaduras; prueba funcional bajo vibración; termografía. | H21: {=_xlfn.XLOOKUP(E:E,'Calificación consecuencia'!B:B,'Calificación consecuencia'!K:K,"No encontrada",2)} -> Baja | I21: Continuidad operacional; Impacto a la operación | J21: Sí | M21: No | O21: Sí | P21: Sí | U21: Tarea CBM programada | V21: Predictivo (basado en condición)
A22: F-MET-006 | B22: Sistema de frenos | C22: {=INDEX(Funciones!$G$2:$G$372,MATCH($A22,Funciones!$B$2:$B$372,0))} -> Frenar el tren en una distancia máxima de 30 m | D22: No frena el tren. La función se pierde por completo: no se cumple ningún punto del estándar. Estándar: en una distancia máxima de 247 m desde 80 km/h (fabricante). Se verifica con: protocolo C.E8.92.302. | E22: A. Válvula distribuidora de freno atascada por contaminación del émbolo con partículas | F22: 1. Local: La válvula distribuidora de freno queda atascada por partículas en el émbolo y no deja pasar aire hacia los cilindros. 2. En el equipo: Los cilindros de freno no se presurizan y el manómetro de cilindros no sube. Al aplicar el freno de servicio el tren no se detiene en la distancia prevista. 3. General: El tren pierde su capacidad de frenado de servicio y debe detenerse con otros medios o salir de circulación. | G22: Respuesta más lenta o movimiento duro de la válvula distribuidora de freno antes de quedar trabado. Se detecta con: prueba funcional; medición de tiempos de ciclo. | H22: {=_xlfn.XLOOKUP(E:E,'Calificación consecuencia'!B:B,'Calificación consecuencia'!K:K,"No encontrada",2)} -> Media | I22: Seguridad; Impacto a la operación | J22: Sí | M22: Sí | N22: Sí | U22: Tarea proactiva obligatoria: basada en condición (CBM) | V22: Predictivo (basado en condición)
A23: F-MET-006 | B23: Sistema de frenos | C23: {=INDEX(Funciones!$G$2:$G$372,MATCH($A23,Funciones!$B$2:$B$372,0))} -> Frenar el tren en una distancia máxima de 30 m | D23: No frena el tren. La función se pierde por completo: no se cumple ningún punto del estándar. Estándar: en una distancia máxima de 247 m desde 80 km/h (fabricante). Se verifica con: protocolo C.E8.92.302. | E23: A. Manguera del conducto general rota por envejecimiento del caucho | F23: 1. Local: La manguera del conducto general se rompe por el envejecimiento del caucho y el aire de mando se escapa por la rotura. 2. En el equipo: La presión del conducto general cae y las válvulas distribuidoras no reciben la orden de aplicar. Al aplicar el freno de servicio el tren no se detiene en la distancia prevista y el manómetro de cilindros no sube. 3. General: El tren pierde su capacidad de frenado de servicio y sale de circulación. | G23: Grietas, resequedad, abultamientos o rozaduras visibles de la manguera del conducto general. Se detecta con: inspección visual. | H23: {=_xlfn.XLOOKUP(E:E,'Calificación consecuencia'!B:B,'Calificación consecuencia'!K:K,"No encontrada",2)} -> Media | I23: Seguridad; Impacto a la operación | J23: Sí | M23: Sí | N23: Sí | U23: Tarea proactiva obligatoria: basada en condición (CBM) | V23: Predictivo (basado en condición)
A24: F-MET-006 | B24: Sistema de frenos | C24: {=INDEX(Funciones!$G$2:$G$372,MATCH($A24,Funciones!$B$2:$B$372,0))} -> Frenar el tren en una distancia máxima de 30 m | D24: No frena el tren. La función se pierde por completo: no se cumple ningún punto del estándar. Estándar: en una distancia máxima de 247 m desde 80 km/h (fabricante). Se verifica con: protocolo C.E8.92.302. | E24: A. Control de freno de servicio bloqueado por defecto del módulo electrónico | F24: 1. Local: El módulo electrónico del control de freno de servicio se bloquea y deja de emitir la orden de frenado. 2. En el equipo: Las electroválvulas de freno no se activan. Al aplicar el freno de servicio el tren no se detiene en la distancia prevista y el manómetro de cilindros no sube. 3. General: El tren pierde su capacidad de frenado de servicio y sale de circulación. | G24: No hay una condición detectable que avise con anticipación: el control de freno de servicio deja de funcionar de forma súbita. Se detecta con: prueba funcional programada; registro de eventos y alarmas del equipo. | H24: {=_xlfn.XLOOKUP(E:E,'Calificación consecuencia'!B:B,'Calificación consecuencia'!K:K,"No encontrada",2)} -> Media | I24: Seguridad; Impacto a la operación | J24: Sí | M24: Sí | N24: No | U24: Rediseño | V24: Rediseño
A25: F-MET-006 | B25: Sistema de frenos | C25: {=INDEX(Funciones!$G$2:$G$372,MATCH($A25,Funciones!$B$2:$B$372,0))} -> Frenar el tren en una distancia máxima de 30 m | D25: Frena el tren con distancia de frenado mayor a 247 m desde 80 km/h. Estándar: en una distancia máxima de 247 m desde 80 km/h (fabricante). Se verifica con: protocolo C.E8.92.302. | E25: B. Zapatas de freno desgastadas por fin de vida útil | F25: 1. Local: Las zapatas llegan al final de su vida útil y el material de fricción se agota; baja el coeficiente de fricción contra la rueda. 2. En el equipo: La fuerza de frenado transmitida a la rueda es menor aunque la presión del cilindro sea la correcta. El conductor nota mayor distancia de frenado y la prueba de frenado da una distancia mayor a 247 m desde 80 km/h. 3. General: El tren frena con menos fuerza y requiere más distancia para detenerse. | G25: Pérdida progresiva de material de las zapatas de freno hasta acercarse al límite de desgaste. Se detecta con: medición con calibre, galga o micrómetro; inspección visual. | H25: {=_xlfn.XLOOKUP(E:E,'Calificación consecuencia'!B:B,'Calificación consecuencia'!K:K,"No encontrada",2)} -> Media | I25: Seguridad; Continuidad operacional | J25: Sí | M25: Sí | N25: Sí | U25: Tarea proactiva obligatoria: basada en condición (CBM) | V25: Predictivo (basado en condición)
A26: F-MET-006 | B26: Sistema de frenos | C26: {=INDEX(Funciones!$G$2:$G$372,MATCH($A26,Funciones!$B$2:$B$372,0))} -> Frenar el tren en una distancia máxima de 30 m | D26: Frena el tren con distancia de frenado mayor a 247 m desde 80 km/h. Estándar: en una distancia máxima de 247 m desde 80 km/h (fabricante). Se verifica con: protocolo C.E8.92.302. | E26: B. Membrana del cilindro de freno agrietada por envejecimiento | F26: 1. Local: La membrana del cilindro de freno se agrieta por el envejecimiento y deja pasar parte del aire. 2. En el equipo: El cilindro no alcanza toda su presión ni su recorrido, y empuja con menos fuerza. El conductor nota mayor distancia de frenado y la prueba de frenado da una distancia de frenado mayor a la máxima. 3. General: El tren frena con menos fuerza y requiere más distancia para detenerse. | G26: Grietas, resequedad, abultamientos o rozaduras visibles de la membrana del cilindro de freno. Se detecta con: inspección visual. | H26: {=_xlfn.XLOOKUP(E:E,'Calificación consecuencia'!B:B,'Calificación consecuencia'!K:K,"No encontrada",2)} -> Media | I26: Seguridad; Continuidad operacional | J26: Sí | M26: Sí | N26: Sí | U26: Tarea proactiva obligatoria: basada en condición (CBM) | V26: Predictivo (basado en condición)
A27: F-MET-006 | B27: Sistema de frenos | C27: {=INDEX(Funciones!$G$2:$G$372,MATCH($A27,Funciones!$B$2:$B$372,0))} -> Frenar el tren en una distancia máxima de 30 m | D27: Frena el tren con distancia de frenado mayor a 247 m desde 80 km/h. Estándar: en una distancia máxima de 247 m desde 80 km/h (fabricante). Se verifica con: protocolo C.E8.92.302. | E27: B. Timonería de freno desajustada por desgaste de articulaciones | F27: 1. Local: Las articulaciones de la timonería de freno se desgastan y se genera juego en el mecanismo. 2. En el equipo: Parte del recorrido del cilindro se consume en el juego y la zapata se aplica con menos fuerza. El conductor nota mayor distancia de frenado y la prueba de frenado da una distancia de frenado mayor a la máxima. 3. General: El tren frena con menos fuerza y requiere más distancia para detenerse. | G27: Deriva de la timonería de freno frente al valor patrón, con lecturas o ajustes que se van corriendo. Se detecta con: verificación contra patrón calibrado; lectura de parámetros; medición de alineación o vibración. | H27: {=_xlfn.XLOOKUP(E:E,'Calificación consecuencia'!B:B,'Calificación consecuencia'!K:K,"No encontrada",2)} -> Media | I27: Seguridad; Continuidad operacional | J27: Sí | M27: Sí | N27: Sí | U27: Tarea proactiva obligatoria: basada en condición (CBM) | V27: Predictivo (basado en condición)
A28: F-MET-006 | B28: Sistema de frenos | C28: {=INDEX(Funciones!$G$2:$G$372,MATCH($A28,Funciones!$B$2:$B$372,0))} -> Frenar el tren en una distancia máxima de 30 m | D28: Frena el tren con distancia de frenado mayor a 247 m desde 80 km/h. Estándar: en una distancia máxima de 247 m desde 80 km/h (fabricante). Se verifica con: protocolo C.E8.92.302. | E28: B. Equipo antibloqueo activado por sensor de velocidad sucio | F28: 1. Local: El sensor de velocidad se ensucia y entrega señales erróneas al equipo antibloqueo, que activa el alivio de freno sin que las ruedas estén deslizando. 2. En el equipo: El freno se libera y se reaplica de forma intermitente. El freno responde con retardos o saltos que el conductor reporta como frenado errático. 3. General: El tren recorre más distancia hasta detenerse y con una respuesta irregular. | G28: Lecturas erráticas del sensor asociado del equipo antibloqueo. Se detecta con: lectura de la señal del sensor con equipo de diagnóstico; inspección visual. | H28: {=_xlfn.XLOOKUP(E:E,'Calificación consecuencia'!B:B,'Calificación consecuencia'!K:K,"No encontrada",2)} -> Media | I28: Seguridad; Continuidad operacional | J28: Sí | M28: Sí | N28: Sí | U28: Tarea proactiva obligatoria: basada en condición (CBM) | V28: Predictivo (basado en condición)
A29: F-MET-006 | B29: Sistema de frenos | C29: {=INDEX(Funciones!$G$2:$G$372,MATCH($A29,Funciones!$B$2:$B$372,0))} -> Frenar el tren en una distancia máxima de 30 m | D29: Frena el tren con distancia de frenado mayor a 247 m desde 80 km/h. Estándar: en una distancia máxima de 247 m desde 80 km/h (fabricante). Se verifica con: protocolo C.E8.92.302. | E29: B. Distribuidor de freno pegajoso por grasa endurecida en el émbolo | F29: 1. Local: La grasa del émbolo del distribuidor se endurece y el émbolo se mueve con dificultad. 2. En el equipo: El distribuidor responde con retardo al aplicar y al aliviar el freno. El freno responde con retardos o saltos que el conductor reporta como frenado errático. 3. General: El tren frena con una respuesta irregular y mayor distancia de parada. | G29: Respuesta más lenta o movimiento duro del distribuidor de freno antes de quedar trabado. Se detecta con: prueba funcional; medición de tiempos de ciclo. | H29: {=_xlfn.XLOOKUP(E:E,'Calificación consecuencia'!B:B,'Calificación consecuencia'!K:K,"No encontrada",2)} -> Media | I29: Seguridad; Continuidad operacional | J29: Sí | M29: Sí | N29: Sí | U29: Tarea proactiva obligatoria: basada en condición (CBM) | V29: Predictivo (basado en condición)
A30: F-MET-007 | B30: Sistema de frenos | C30: {=INDEX(Funciones!$G$2:$G$372,MATCH($A30,Funciones!$B$2:$B$372,0))} -> Detener el tren en una distancia máxima de 30 m | D30: No detiene el tren en emergencia. La función se pierde por completo: no se cumple ningún punto del estándar. Estándar: en una distancia máxima de 190 m desde 80 km/h (fabricante). Se verifica con: protocolo C.E8.92.302. | E30: A. Válvula de emergencia atascada por suciedad en el émbolo | F30: 1. Local: El émbolo de la válvula de emergencia se atasca por suciedad y la válvula no abre el escape del conducto de freno. 2. En el equipo: El conducto no se despresuriza con la rapidez de emergencia y los cilindros no reciben presión de emergencia. Al abrir el bucle de emergencia el tren no frena y el manómetro de cilindros no responde. 3. General: El tren no cuenta con el freno de emergencia y debe salir de circulación. | G30: Respuesta más lenta o movimiento duro de la válvula de emergencia antes de quedar trabado. Se detecta con: prueba funcional; medición de tiempos de ciclo. | H30: {=_xlfn.XLOOKUP(E:E,'Calificación consecuencia'!B:B,'Calificación consecuencia'!K:K,"No encontrada",2)} -> Media | I30: Seguridad; Impacto a la operación | J30: Sí | M30: Sí | N30: Sí | U30: Tarea proactiva obligatoria: basada en condición (CBM) | V30: Predictivo (basado en condición)
A31: F-MET-007 | B31: Sistema de frenos | C31: {=INDEX(Funciones!$G$2:$G$372,MATCH($A31,Funciones!$B$2:$B$372,0))} -> Detener el tren en una distancia máxima de 30 m | D31: No detiene el tren en emergencia. La función se pierde por completo: no se cumple ningún punto del estándar. Estándar: en una distancia máxima de 190 m desde 80 km/h (fabricante). Se verifica con: protocolo C.E8.92.302. | E31: A. Bucle de emergencia interrumpido por roce del cable con la estructura | F31: 1. Local: El cable del bucle de emergencia se interrumpe por el roce con la estructura y se abre el circuito. 2. En el equipo: La orden de emergencia no llega a la electroválvula. Al abrir el bucle de emergencia el tren no frena y el manómetro de cilindros no responde. 3. General: El tren no cuenta con el freno de emergencia y debe salir de circulación. | G31: Resistencia anormal o pérdida de continuidad del bucle de emergencia. Se detecta con: medición de continuidad; inspección de conexiones. | H31: {=_xlfn.XLOOKUP(E:E,'Calificación consecuencia'!B:B,'Calificación consecuencia'!K:K,"No encontrada",2)} -> Media | I31: Seguridad; Impacto a la operación | J31: Sí | M31: Sí | N31: Sí | U31: Tarea proactiva obligatoria: basada en condición (CBM) | V31: Predictivo (basado en condición)
A32: F-MET-007 | B32: Sistema de frenos | C32: {=INDEX(Funciones!$G$2:$G$372,MATCH($A32,Funciones!$B$2:$B$372,0))} -> Detener el tren en una distancia máxima de 30 m | D32: No detiene el tren en emergencia. La función se pierde por completo: no se cumple ningún punto del estándar. Estándar: en una distancia máxima de 190 m desde 80 km/h (fabricante). Se verifica con: protocolo C.E8.92.302. | E32: A. Electroválvula de emergencia desenergizada por bobina quemada | F32: 1. Local: La bobina de la electroválvula de emergencia se quema y deja de generar el campo magnético que mueve la válvula. 2. En el equipo: La válvula no cambia de posición y no descarga el conducto de freno. Al abrir el bucle de emergencia el tren no frena y el manómetro de cilindros no responde. 3. General: El tren no cuenta con el freno de emergencia y debe salir de circulación. | G32: Aumento de temperatura y de consumo de corriente de la bobina. Se detecta con: termografía; medición de corriente; prueba de aislamiento (megóhmetro). | H32: {=_xlfn.XLOOKUP(E:E,'Calificación consecuencia'!B:B,'Calificación consecuencia'!K:K,"No encontrada",2)} -> Media | I32: Seguridad; Impacto a la operación | J32: Sí | M32: Sí | N32: Sí | U32: Tarea proactiva obligatoria: basada en condición (CBM) | V32: Predictivo (basado en condición) | W32: Cambiar la bobina quemada
A33: F-MET-007 | B33: Sistema de frenos | C33: {=INDEX(Funciones!$G$2:$G$372,MATCH($A33,Funciones!$B$2:$B$372,0))} -> Detener el tren en una distancia máxima de 30 m | D33: No detiene el tren en emergencia. La función se pierde por completo: no se cumple ningún punto del estándar. Estándar: en una distancia máxima de 190 m desde 80 km/h (fabricante). Se verifica con: protocolo C.E8.92.302. | E33: A. Contacto del bucle de emergencia sulfatado por humedad | F33: 1. Local: El contacto del bucle de emergencia se sulfata por humedad y la señal pasa solo en algunos intentos. 2. En el equipo: La orden de emergencia llega de forma intermitente a la electroválvula. El freno de emergencia actúa solo en algunos intentos y se descubre en la prueba. 3. General: El freno de emergencia no es confiable en cada demanda. | G33: Óxido, picaduras o sulfatación visibles del contacto del bucle de emergencia. Se detecta con: inspección visual; medición de resistencia de contacto o de tensión en bornes. | H33: {=_xlfn.XLOOKUP(E:E,'Calificación consecuencia'!B:B,'Calificación consecuencia'!K:K,"No encontrada",2)} -> Media | I33: Seguridad; Impacto a la operación | J33: Sí | M33: Sí | N33: Sí | U33: Tarea proactiva obligatoria: basada en condición (CBM) | V33: Predictivo (basado en condición)
A34: F-MET-007 | B34: Sistema de frenos | C34: {=INDEX(Funciones!$G$2:$G$372,MATCH($A34,Funciones!$B$2:$B$372,0))} -> Detener el tren en una distancia máxima de 30 m | D34: No detiene el tren en emergencia. La función se pierde por completo: no se cumple ningún punto del estándar. Estándar: en una distancia máxima de 190 m desde 80 km/h (fabricante). Se verifica con: protocolo C.E8.92.302. | E34: A. Relé de emergencia inestable por desgaste de contactos | F34: 1. Local: Los contactos del relé de emergencia se desgastan y cierran o abren de forma inestable. 2. En el equipo: La orden de emergencia llega de forma intermitente. El freno de emergencia actúa solo en algunos intentos y se descubre en la prueba. 3. General: El freno de emergencia no es confiable en cada demanda. | G34: Lecturas que varían o se pierden al mover o vibrar el conector, con aumento de la resistencia de contacto del relé de emergencia. Se detecta con: inspección de conectores; medición de resistencia de contacto; lectura de la señal con equipo de diagnóstico. | H34: {=_xlfn.XLOOKUP(E:E,'Calificación consecuencia'!B:B,'Calificación consecuencia'!K:K,"No encontrada",2)} -> Media | I34: Seguridad; Impacto a la operación | J34: Sí | M34: Sí | N34: Sí | U34: Tarea proactiva obligatoria: basada en condición (CBM) | V34: Predictivo (basado en condición)
A35: F-MET-007 | B35: Sistema de frenos | C35: {=INDEX(Funciones!$G$2:$G$372,MATCH($A35,Funciones!$B$2:$B$372,0))} -> Detener el tren en una distancia máxima de 30 m | D35: Detiene el tren en emergencia con distancia de parada mayor a 190 m desde 80 km/h. Estándar: en una distancia máxima de 190 m desde 80 km/h (fabricante). Se verifica con: protocolo C.E8.92.302. | E35: B. Zapatas de freno desgastadas por fin de vida útil | F35: 1. Local: Las zapatas se desgastan hasta el final de su vida útil y pierden fricción contra la rueda. 2. En el equipo: La fuerza de frenado de emergencia es menor a la de diseño. La prueba de emergencia da una distancia de frenado mayor a la esperada. 3. General: El tren recorre más de 190 m desde 80 km/h hasta quedar parado en emergencia. | G35: Pérdida progresiva de material de las zapatas de freno hasta acercarse al límite de desgaste. Se detecta con: medición con calibre, galga o micrómetro; inspección visual. | H35: {=_xlfn.XLOOKUP(E:E,'Calificación consecuencia'!B:B,'Calificación consecuencia'!K:K,"No encontrada",2)} -> Media | I35: Seguridad; Continuidad operacional | J35: Sí | M35: Sí | N35: Sí | U35: Tarea proactiva obligatoria: basada en condición (CBM) | V35: Predictivo (basado en condición)
A36: F-MET-007 | B36: Sistema de frenos | C36: {=INDEX(Funciones!$G$2:$G$372,MATCH($A36,Funciones!$B$2:$B$372,0))} -> Detener el tren en una distancia máxima de 30 m | D36: Detiene el tren en emergencia con distancia de parada mayor a 190 m desde 80 km/h. Estándar: en una distancia máxima de 190 m desde 80 km/h (fabricante). Se verifica con: protocolo C.E8.92.302. | E36: B. Válvula de emergencia obstruida por filtro con suciedad | F36: 1. Local: El filtro de la válvula de emergencia se llena de suciedad y restringe el paso del aire. 2. En el equipo: El conducto se descarga más lento de lo previsto y los cilindros alcanzan su presión con retardo. La prueba de emergencia da una distancia de frenado mayor a la esperada. 3. General: El tren recorre más de 190 m desde 80 km/h hasta quedar parado en emergencia. | G36: Aumento de la presión diferencial o caída del caudal por acumulación de suciedad de la válvula de emergencia. Se detecta con: lectura de manómetros y diferencial de presión; medición de caudal; inspección visual. | H36: {=_xlfn.XLOOKUP(E:E,'Calificación consecuencia'!B:B,'Calificación consecuencia'!K:K,"No encontrada",2)} -> Media | I36: Seguridad; Continuidad operacional | J36: Sí | M36: Sí | N36: Sí | U36: Tarea proactiva obligatoria: basada en condición (CBM) | V36: Predictivo (basado en condición)
A37: F-MET-008 | B37: Sistema de frenos | C37: {=INDEX(Funciones!$G$2:$G$372,MATCH($A37,Funciones!$B$2:$B$372,0))} -> Inmovilizar el tren con carga de 203 t en pendiente de 3 % | D37: No inmoviliza el tren. La función se pierde por completo: no se cumple ningún punto del estándar. Estándar: con carga de 203 t en pendiente de 3 % (fabricante). Se verifica con: prueba de estacionamiento. | E37: A. Resorte del freno de estacionamiento roto por fatiga del material | F37: 1. Local: El resorte del freno de estacionamiento se rompe por fatiga y no entrega fuerza de aplicación. 2. En el equipo: Las zapatas de estacionamiento no se presionan contra la rueda. No se nota en servicio; se descubre al estacionar y ver que el tren se desplaza o en la prueba de inmovilización. 3. General: El tren no queda retenido en la pendiente cuando está estacionado. | G37: Pérdida de altura libre o de carga del resorte del freno de estacionamiento. Se detecta con: medición de altura libre y de carga en banco de pruebas; inspección visual. Al ser una función oculta no se nota en operación: depende de la inspección o prueba programada. | H37: {=_xlfn.XLOOKUP(E:E,'Calificación consecuencia'!B:B,'Calificación consecuencia'!K:K,"No encontrada",2)} -> Baja | I37: Seguridad; Continuidad operacional | J37: No | K37: Sí | U37: Tarea de búsqueda de falla programada | V37: Detectivo (búsqueda de falla)
A38: F-MET-008 | B38: Sistema de frenos | C38: {=INDEX(Funciones!$G$2:$G$372,MATCH($A38,Funciones!$B$2:$B$372,0))} -> Inmovilizar el tren con carga de 203 t en pendiente de 3 % | D38: No inmoviliza el tren. La función se pierde por completo: no se cumple ningún punto del estándar. Estándar: con carga de 203 t en pendiente de 3 % (fabricante). Se verifica con: prueba de estacionamiento. | E38: A. Cilindro de estacionamiento trabado por corrosión del vástago | F38: 1. Local: El vástago del cilindro de estacionamiento se corroe y el cilindro se traba, sin completar su recorrido. 2. En el equipo: El freno de estacionamiento no se aplica por completo. No se nota en servicio; se descubre al estacionar y ver que el tren se desplaza o en la prueba de inmovilización. 3. General: El tren no queda retenido en la pendiente cuando está estacionado. | G38: Movimiento duro, ruido o calentamiento anormal del cilindro de estacionamiento antes de trabarse. Se detecta con: análisis de vibraciones; termografía; análisis de partículas en el aceite. Al ser una función oculta no se nota en operación: depende de la inspección o prueba programada. | H38: {=_xlfn.XLOOKUP(E:E,'Calificación consecuencia'!B:B,'Calificación consecuencia'!K:K,"No encontrada",2)} -> Media | I38: Seguridad; Continuidad operacional | J38: No | K38: Sí | U38: Tarea de búsqueda de falla programada | V38: Detectivo (búsqueda de falla)
A39: F-MET-008 | B39: Sistema de frenos | C39: {=INDEX(Funciones!$G$2:$G$372,MATCH($A39,Funciones!$B$2:$B$372,0))} -> Inmovilizar el tren con carga de 203 t en pendiente de 3 % | D39: No inmoviliza el tren. La función se pierde por completo: no se cumple ningún punto del estándar. Estándar: con carga de 203 t en pendiente de 3 % (fabricante). Se verifica con: prueba de estacionamiento. | E39: A. Válvula de estacionamiento atascada por contaminación | F39: 1. Local: La válvula de estacionamiento se atasca por contaminación y no cambia de posición para aplicar el freno. 2. En el equipo: El cilindro de estacionamiento no se descarga ni se aplica cuando se requiere. No se nota en servicio; se descubre al estacionar y ver que el tren se desplaza o en la prueba de inmovilización. 3. General: El tren no queda retenido en la pendiente cuando está estacionado. | G39: Respuesta más lenta o movimiento duro de la válvula de estacionamiento antes de quedar trabado. Se detecta con: prueba funcional; medición de tiempos de ciclo. Al ser una función oculta no se nota en operación: depende de la inspección o prueba programada. | H39: {=_xlfn.XLOOKUP(E:E,'Calificación consecuencia'!B:B,'Calificación consecuencia'!K:K,"No encontrada",2)} -> Media | I39: Seguridad; Continuidad operacional | J39: No | K39: Sí | U39: Tarea de búsqueda de falla programada | V39: Detectivo (búsqueda de falla)
A40: F-MET-008 | B40: Sistema de frenos | C40: {=INDEX(Funciones!$G$2:$G$372,MATCH($A40,Funciones!$B$2:$B$372,0))} -> Inmovilizar el tren con carga de 203 t en pendiente de 3 % | D40: Inmoviliza el tren con fuerza de retención inferior a la requerida. Estándar: con carga de 203 t en pendiente de 3 % (fabricante). Se verifica con: prueba de estacionamiento. | E40: B. Zapatas de estacionamiento desgastadas por fin de vida útil | F40: 1. Local: Las zapatas de estacionamiento llegan al final de su vida útil y pierden espesor y fricción. 2. En el equipo: La fuerza de retención sobre la rueda es menor a la necesaria. La prueba de inmovilización en pendiente no sostiene la carga de 203 t. 3. General: El tren queda retenido con una fuerza inferior a la requerida y no sostiene la carga en la pendiente. | G40: Pérdida progresiva de material de las zapatas de estacionamiento hasta acercarse al límite de desgaste. Se detecta con: medición con calibre, galga o micrómetro; inspección visual. Al ser una función oculta no se nota en operación: depende de la inspección o prueba programada. | H40: {=_xlfn.XLOOKUP(E:E,'Calificación consecuencia'!B:B,'Calificación consecuencia'!K:K,"No encontrada",2)} -> Baja | I40: Continuidad operacional; Seguridad | J40: No | K40: Sí | U40: Tarea de búsqueda de falla programada | V40: Detectivo (búsqueda de falla)
A41: F-MET-008 | B41: Sistema de frenos | C41: {=INDEX(Funciones!$G$2:$G$372,MATCH($A41,Funciones!$B$2:$B$372,0))} -> Inmovilizar el tren con carga de 203 t en pendiente de 3 % | D41: Inmoviliza el tren con fuerza de retención inferior a la requerida. Estándar: con carga de 203 t en pendiente de 3 % (fabricante). Se verifica con: prueba de estacionamiento. | E41: B. Resorte del freno de estacionamiento debilitado por fatiga del material | F41: 1. Local: El resorte del freno de estacionamiento se debilita por fatiga y entrega menos fuerza de aplicación. 2. En el equipo: Las zapatas se aprietan contra la rueda con menos fuerza. La prueba de inmovilización en pendiente no sostiene la carga de 203 t. 3. General: El tren queda retenido con una fuerza inferior a la requerida y no sostiene la carga en la pendiente. | G41: Pérdida de altura libre o de carga del resorte del freno de estacionamiento. Se detecta con: medición de altura libre y de carga en banco de pruebas; inspección visual. Al ser una función oculta no se nota en operación: depende de la inspección o prueba programada. | H41: {=_xlfn.XLOOKUP(E:E,'Calificación consecuencia'!B:B,'Calificación consecuencia'!K:K,"No encontrada",2)} -> Baja | I41: Continuidad operacional; Seguridad | J41: No | K41: Sí | U41: Tarea de búsqueda de falla programada | V41: Detectivo (búsqueda de falla)
A42: F-MET-018 | B42: Sistema de tracción | C42: {=INDEX(Funciones!$G$2:$G$372,MATCH($A42,Funciones!$B$2:$B$372,0))} -> Alcanzar una velocidad máxima entre 78 y 80 km/h | D42: No alcanza una velocidad máxima. La función se pierde por completo: no se cumple ningún punto del estándar. Estándar: entre 78 y 80 km/h (contexto operacional: Wikipedia). Se verifica con: protocolo C.E8.92.301. | E42: A. Convertidor de tracción bloqueado por defecto del módulo de control | F42: 1. Local: El convertidor de tracción se bloquea por un defecto del módulo de control y deja de modular la potencia hacia los motores. 2. En el equipo: Los motores de tracción no reciben tensión ni frecuencia de trabajo. El tren no pasa de baja velocidad y el conductor lo percibe de inmediato. 3. General: El tren no alcanza la velocidad máxima y los tiempos de recorrido no se cumplen. | G42: No hay una condición detectable que avise con anticipación: el convertidor de tracción deja de funcionar de forma súbita. Se detecta con: prueba funcional programada; registro de eventos y alarmas del equipo. | H42: {=_xlfn.XLOOKUP(E:E,'Calificación consecuencia'!B:B,'Calificación consecuencia'!K:K,"No encontrada",2)} -> Media | I42: Impacto a la operación; Continuidad operacional | J42: Sí | M42: No | O42: Sí | P42: No | Q42: No | R42: Si | U42: Correctivo | V42: Correctivo (operar hasta la falla) | W42: Al presentarse el bloqueo, diagnosticar con el registro de eventos del convertidor y sustituir la tarjeta del módulo de control por una de repuesto; mantener tarjetas de repuesto en almacén | X42: No aplica | Y42: Técnico electromecánico de material rodante (taller de trenes)
A43: F-MET-018 | B43: Sistema de tracción | C43: {=INDEX(Funciones!$G$2:$G$372,MATCH($A43,Funciones!$B$2:$B$372,0))} -> Alcanzar una velocidad máxima entre 78 y 80 km/h | D43: No alcanza una velocidad máxima. La función se pierde por completo: no se cumple ningún punto del estándar. Estándar: entre 78 y 80 km/h (contexto operacional: Wikipedia). Se verifica con: protocolo C.E8.92.301. | E43: A.Aislamiento del devanado del motor de tracción degradado por envejecimiento térmico | F43: 1. Local: El aislamiento del devanado del motor de tracción se daña y el motor se quema. 2. En el equipo: El motor entra en cortocircuito y la protección del convertidor desconecta la tracción de ese grupo. El conductor recibe la alarma en cabina y el tren sigue con menos tracción. 3. General: El tren acelera más lento y no alcanza la velocidad máxima en pendientes; los tiempos de recorrido no se cumplen y el tren se retira al final de la vuelta. | G43: Caída de la resistencia de aislamiento y del índice de polarización del devanado del motor de tracción. Se detecta con: prueba de aislamiento con megóhmetro a la tensión que indique el fabricante, registrando la tendencia. | H43: {=_xlfn.XLOOKUP(E:E,'Calificación consecuencia'!B:B,'Calificación consecuencia'!K:K,"No encontrada",2)} -> No encontrada | I43: Impacto a la operación; Costo de reparación | J43: Sí | M43: No | O43: Sí | P43: Sí | U43: Tarea CBM programada | V43: Predictivo (basado en condición)
A44: F-MET-018 | B44: Sistema de tracción | C44: {=INDEX(Funciones!$G$2:$G$372,MATCH($A44,Funciones!$B$2:$B$372,0))} -> Alcanzar una velocidad máxima entre 78 y 80 km/h | D44: Alcanza una velocidad máxima por debajo de 78 km/h. Estándar: entre 78 y 80 km/h (contexto operacional: Wikipedia). Se verifica con: protocolo C.E8.92.301. | E44: B. Motor de tracción aislado por protección térmica disparada | F44: 1. Local: La protección térmica del motor de tracción se dispara y desconecta el motor. 2. En el equipo: El tren pierde la tracción de ese motor y queda con menos potencia disponible. El tren llega a una velocidad máxima menor a la esperada en tramos rectos. 3. General: El tren circula por debajo de 78 km/h y cumple los tiempos con retraso. | G44: Aumento de temperatura, de consumo de corriente o caída de la resistencia de aislamiento del motor de tracción. Se detecta con: termografía; medición de corriente; prueba de aislamiento (megóhmetro). | H44: {=_xlfn.XLOOKUP(E:E,'Calificación consecuencia'!B:B,'Calificación consecuencia'!K:K,"No encontrada",2)} -> Baja | I44: Costo de reparación; Continuidad operacional | J44: Sí | M44: No | O44: Sí | P44: Sí | U44: Tarea CBM programada | V44: Predictivo (basado en condición)
A45: F-MET-018 | B45: Sistema de tracción | C45: {=INDEX(Funciones!$G$2:$G$372,MATCH($A45,Funciones!$B$2:$B$372,0))} -> Alcanzar una velocidad máxima entre 78 y 80 km/h | D45: Alcanza una velocidad máxima por debajo de 78 km/h. Estándar: entre 78 y 80 km/h (contexto operacional: Wikipedia). Se verifica con: protocolo C.E8.92.301. | E45: B. Banda del pantógrafo desgastada por fin de vida útil | F45: 1. Local: La banda del pantógrafo se desgasta hasta el final de su vida útil y el área de contacto con el hilo disminuye. 2. En el equipo: La captación de corriente es menor y la tensión disponible en el tren baja. El tren llega a una velocidad máxima menor a la esperada en tramos rectos. 3. General: El tren circula por debajo de 78 km/h y cumple los tiempos con retraso. | G45: Pérdida progresiva de material de la banda del pantógrafo hasta acercarse al límite de desgaste. Se detecta con: medición con calibre, galga o micrómetro; inspección visual. | H45: {=_xlfn.XLOOKUP(E:E,'Calificación consecuencia'!B:B,'Calificación consecuencia'!K:K,"No encontrada",2)} -> Baja | I45: Costo de reparación; Continuidad operacional | J45: Sí | M45: No | O45: Sí | P45: Sí | U45: Tarea CBM programada | V45: Predictivo (basado en condición)
A46: F-MET-018 | B46: Sistema de tracción | C46: {=INDEX(Funciones!$G$2:$G$372,MATCH($A46,Funciones!$B$2:$B$372,0))} -> Alcanzar una velocidad máxima entre 78 y 80 km/h | D46: Alcanza una velocidad máxima que oscila fuera del rango de 78 a 80 km/h. Estándar: entre 78 y 80 km/h (contexto operacional: Wikipedia). Se verifica con: protocolo C.E8.92.301. | E46: D. Banda del pantógrafo desgastada por contacto irregular con el hilo | F46: 1. Local: La banda del pantógrafo se desgasta de forma irregular y el contacto con el hilo se interrumpe por instantes. 2. En el equipo: La corriente captada varía en el tiempo. La velocidad oscila sin causa aparente durante el recorrido. 3. General: El tren no sostiene una velocidad estable entre 78 y 80 km/h y el tiempo de recorrido varía. | G46: Pérdida progresiva de material de la banda del pantógrafo hasta acercarse al límite de desgaste. Se detecta con: medición con calibre, galga o micrómetro; inspección visual. | H46: {=_xlfn.XLOOKUP(E:E,'Calificación consecuencia'!B:B,'Calificación consecuencia'!K:K,"No encontrada",2)} -> Baja | I46: Costo de reparación; Continuidad operacional | J46: Sí | M46: No | O46: Sí | P46: Sí | U46: Tarea CBM programada | V46: Predictivo (basado en condición)
A47: F-MET-018 | B47: Sistema de tracción | C47: {=INDEX(Funciones!$G$2:$G$372,MATCH($A47,Funciones!$B$2:$B$372,0))} -> Alcanzar una velocidad máxima entre 78 y 80 km/h | D47: Alcanza una velocidad máxima que oscila fuera del rango de 78 a 80 km/h. Estándar: entre 78 y 80 km/h (contexto operacional: Wikipedia). Se verifica con: protocolo C.E8.92.301. | E47: D. Sensor de velocidad inestable por conector flojo | F47: 1. Local: El conector del sensor de velocidad se afloja por vibración y la señal se corta de forma intermitente. 2. En el equipo: El control de tracción recibe una lectura de velocidad inestable. La velocidad oscila sin causa aparente durante el recorrido. 3. General: El tren no sostiene una velocidad estable entre 78 y 80 km/h y el tiempo de recorrido varía. | G47: Lecturas que varían o se pierden al mover o vibrar el conector, con aumento de la resistencia de contacto del sensor de velocidad. Se detecta con: inspección de conectores; medición de resistencia de contacto; lectura de la señal con equipo de diagnóstico. | H47: {=_xlfn.XLOOKUP(E:E,'Calificación consecuencia'!B:B,'Calificación consecuencia'!K:K,"No encontrada",2)} -> Media | I47: Continuidad operacional; Impacto a la operación | J47: Sí | M47: No | O47: Sí | P47: No | Q47: Sí | U47: Tarea basada en tiempo/uso programada | V47: Preventivo (basado en tiempo/uso)
A48: F-MET-019 | B48: Sistema de tracción | C48: {=INDEX(Funciones!$G$2:$G$372,MATCH($A48,Funciones!$B$2:$B$372,0))} -> Entregar el par de tracción en arranque entre _____ y _____ N·m | D48: No entrega par de tracción. La función se pierde por completo: no se cumple ningún punto del estándar. Estándar: en arranque entre _____ y _____ N·m (valor por confirmar; fabricante). Se verifica con: protocolo C.E8.92.301; lectura del par en el registro del convertidor. | E48: A. Convertidor de tracción disparado por sobretemperatura | F48: 1. Local: El convertidor de tracción supera su temperatura máxima y se dispara por sobretemperatura. 2. En el equipo: El convertidor deja de entregar potencia a los motores. El tren no arranca al dar potencia y el conductor ve el mensaje de alarma de tracción. 3. General: El tren no recibe par de tracción y queda detenido o sale de circulación. | G48: Aumento de temperatura, de consumo de corriente o caída de la resistencia de aislamiento del convertidor de tracción. Se detecta con: termografía; medición de corriente; prueba de aislamiento (megóhmetro). | H48: {=_xlfn.XLOOKUP(E:E,'Calificación consecuencia'!B:B,'Calificación consecuencia'!K:K,"No encontrada",2)} -> Media | I48: Impacto a la operación; Continuidad operacional | J48: Sí | M48: No | O48: Sí | P48: Sí | U48: Tarea CBM programada | V48: Predictivo (basado en condición)
A49: F-MET-019 | B49: Sistema de tracción | C49: {=INDEX(Funciones!$G$2:$G$372,MATCH($A49,Funciones!$B$2:$B$372,0))} -> Entregar el par de tracción en arranque entre _____ y _____ N·m | D49: No entrega par de tracción. La función se pierde por completo: no se cumple ningún punto del estándar. Estándar: en arranque entre _____ y _____ N·m (valor por confirmar; fabricante). Se verifica con: protocolo C.E8.92.301; lectura del par en el registro del convertidor. | E49: A. Controlador de tracción bloqueado por bloqueo del programa de control | F49: 1. Local: El controlador de tracción se bloquea por un bloqueo del programa de control y no emite la orden de torque. 2. En el equipo: El convertidor no recibe consigna y los motores no producen torque. El tren no arranca al dar potencia y el conductor ve el mensaje de alarma de tracción. 3. General: El tren no recibe par de tracción y queda detenido o sale de circulación. | G49: No hay una condición detectable que avise con anticipación: el controlador de tracción deja de funcionar de forma súbita. Se detecta con: prueba funcional programada; registro de eventos y alarmas del equipo. | H49: {=_xlfn.XLOOKUP(E:E,'Calificación consecuencia'!B:B,'Calificación consecuencia'!K:K,"No encontrada",2)} -> Baja | I49: Impacto a la operación; Continuidad operacional | J49: Sí | M49: No | O49: Sí | P49: No | Q49: No | R49: No | U49: Rediseño | V49: Rediseño
A50: F-MET-019 | B50: Sistema de tracción | C50: {=INDEX(Funciones!$G$2:$G$372,MATCH($A50,Funciones!$B$2:$B$372,0))} -> Entregar el par de tracción en arranque entre _____ y _____ N·m | D50: Entrega par de tracción por debajo de _____ N·m. Estándar: en arranque entre _____ y _____ N·m (valor por confirmar; fabricante). Se verifica con: protocolo C.E8.92.301; lectura del par en el registro del convertidor. | E50: B. Motor de tracción aislado por protección térmica disparada | F50: 1. Local: La protección térmica del motor de tracción se dispara y desconecta el motor. 2. En el equipo: El tren pierde el torque de ese motor y la fuerza de tracción total baja. El tren tarda más en llegar a velocidad y los registros de tracción lo confirman. 3. General: El tren recibe un par menor al mínimo y se pierden segundos por estación. | G50: Aumento de temperatura, de consumo de corriente o caída de la resistencia de aislamiento del motor de tracción. Se detecta con: termografía; medición de corriente; prueba de aislamiento (megóhmetro). | H50: {=_xlfn.XLOOKUP(E:E,'Calificación consecuencia'!B:B,'Calificación consecuencia'!K:K,"No encontrada",2)} -> Baja | I50: Costo de reparación; Continuidad operacional | J50: Sí | M50: No | O50: Sí | P50: Sí | U50: Tarea CBM programada | V50: Predictivo (basado en condición)
A51: F-MET-019 | B51: Sistema de tracción | C51: {=INDEX(Funciones!$G$2:$G$372,MATCH($A51,Funciones!$B$2:$B$372,0))} -> Entregar el par de tracción en arranque entre _____ y _____ N·m | D51: Entrega par de tracción por debajo de _____ N·m. Estándar: en arranque entre _____ y _____ N·m (valor por confirmar; fabricante). Se verifica con: protocolo C.E8.92.301; lectura del par en el registro del convertidor. | E51: B. Ventilador del convertidor lento por rodamiento desgastado | F51: 1. Local: El rodamiento del ventilador del convertidor se desgasta y el ventilador gira lento. 2. En el equipo: La refrigeración del convertidor disminuye y el convertidor reduce su potencia para proteger sus componentes. El tren tarda más en llegar a velocidad y los registros de tracción lo confirman. 3. General: El tren recibe un par menor al mínimo y se pierden segundos por estación. | G51: Movimiento duro, ruido o calentamiento anormal del ventilador del convertidor antes de trabarse. Se detecta con: análisis de vibraciones; termografía; análisis de partículas en el aceite. | H51: {=_xlfn.XLOOKUP(E:E,'Calificación consecuencia'!B:B,'Calificación consecuencia'!K:K,"No encontrada",2)} -> Media | I51: Continuidad operacional; Impacto a la operación | J51: Sí | M51: No | O51: Sí | P51: Sí | U51: Tarea CBM programada | V51: Predictivo (basado en condición)
A52: F-MET-019 | B52: Sistema de tracción | C52: {=INDEX(Funciones!$G$2:$G$372,MATCH($A52,Funciones!$B$2:$B$372,0))} -> Entregar el par de tracción en arranque entre _____ y _____ N·m | D52: Entrega par de tracción por encima de _____ N·m. Estándar: en arranque entre _____ y _____ N·m (valor por confirmar; fabricante). Se verifica con: protocolo C.E8.92.301; lectura del par en el registro del convertidor. | E52: C. Sensor de carga descalibrado por deriva electrónica | F52: 1. Local: El sensor de carga se descalibra por deriva electrónica y reporta menos carga de la real. 2. En el equipo: El control calcula una consigna de torque mayor a la necesaria. Los pasajeros de pie sienten tirones al arrancar. 3. General: El tren recibe un par mayor al máximo y aumenta el esfuerzo sobre acoples y confort. | G52: Deriva del sensor de carga frente al valor patrón, con lecturas o ajustes que se van corriendo. Se detecta con: verificación contra patrón calibrado; lectura de parámetros; medición de alineación o vibración. | H52: {=_xlfn.XLOOKUP(E:E,'Calificación consecuencia'!B:B,'Calificación consecuencia'!K:K,"No encontrada",2)} -> Baja | I52: Continuidad operacional; Impacto a la operación | J52: Sí | M52: No | O52: Sí | P52: No | Q52: Sí | U52: Tarea basada en tiempo/uso programada | V52: Preventivo (basado en tiempo/uso)
A53: F-MET-019 | B53: Sistema de tracción | C53: {=INDEX(Funciones!$G$2:$G$372,MATCH($A53,Funciones!$B$2:$B$372,0))} -> Entregar el par de tracción en arranque entre _____ y _____ N·m | D53: Entrega par de tracción por encima de _____ N·m. Estándar: en arranque entre _____ y _____ N·m (valor por confirmar; fabricante). Se verifica con: protocolo C.E8.92.301; lectura del par en el registro del convertidor. | E53: C. Control de tracción desajustado por pérdida de los parámetros configurados | F53: 1. Local: El control de tracción pierde los parámetros configurados y asume valores de torque mayores a los de diseño. 2. En el equipo: El convertidor entrega torque por encima del nominal. Los pasajeros de pie sienten tirones al arrancar. 3. General: El tren recibe un par mayor al máximo y aumenta el esfuerzo sobre acoples y confort. | G53: No hay una condición detectable que avise con anticipación: el control de tracción deja de funcionar de forma súbita. Se detecta con: prueba funcional programada; registro de eventos y alarmas del equipo. | H53: {=_xlfn.XLOOKUP(E:E,'Calificación consecuencia'!B:B,'Calificación consecuencia'!K:K,"No encontrada",2)} -> Baja | I53: Continuidad operacional; Impacto a la operación | J53: Sí | M53: No | O53: Sí | P53: No | Q53: No | R53: Sí | U53: Sin mantenimiento proactivo programado (operar hasta la falla) | V53: Correctivo (operar hasta la falla)
A54: F-MET-019 | B54: Sistema de tracción | C54: {=INDEX(Funciones!$G$2:$G$372,MATCH($A54,Funciones!$B$2:$B$372,0))} -> Entregar el par de tracción en arranque entre _____ y _____ N·m | D54: Entrega un par de tracción que oscila fuera del rango de _____ a _____ N·m. Estándar: en arranque entre _____ y _____ N·m (valor por confirmar; fabricante). Se verifica con: protocolo C.E8.92.301; lectura del par en el registro del convertidor. | E54: D. Contactor de línea picado por desgaste de contactos | F54: 1. Local: Los contactos del contactor de línea se pican por desgaste y la conexión de potencia se interrumpe de forma intermitente. 2. En el equipo: La tensión que llega al convertidor varía durante el arranque. El tren arranca con tirones intermitentes que el conductor reporta. 3. General: El par de tracción oscila fuera del rango previsto y el arranque es irregular. | G54: Pérdida progresiva de material del contactor de línea hasta acercarse al límite de desgaste. Se detecta con: medición con calibre, galga o micrómetro; inspección visual. | H54: {=_xlfn.XLOOKUP(E:E,'Calificación consecuencia'!B:B,'Calificación consecuencia'!K:K,"No encontrada",2)} -> Media | I54: Continuidad operacional; Impacto a la operación | J54: Sí | M54: No | O54: Sí | P54: Sí | U54: Tarea CBM programada | V54: Predictivo (basado en condición)
A55: F-MET-019 | B55: Sistema de tracción | C55: {=INDEX(Funciones!$G$2:$G$372,MATCH($A55,Funciones!$B$2:$B$372,0))} -> Entregar el par de tracción en arranque entre _____ y _____ N·m | D55: Entrega un par de tracción que oscila fuera del rango de _____ a _____ N·m. Estándar: en arranque entre _____ y _____ N·m (valor por confirmar; fabricante). Se verifica con: protocolo C.E8.92.301; lectura del par en el registro del convertidor. | E55: D. Tarjeta de control inestable por soldaduras fatigadas | F55: 1. Local: Las soldaduras de la tarjeta de control se fatigan y pierden contacto de forma intermitente. 2. En el equipo: La consigna de torque cambia durante el arranque. El tren arranca con tirones intermitentes que el conductor reporta. 3. General: El par de tracción oscila fuera del rango previsto y el arranque es irregular. | G55: Lecturas o comportamiento inestables de la tarjeta de control al vibrar o calentarse. Se detecta con: inspección visual de las soldaduras; prueba funcional bajo vibración; termografía. | H55: {=_xlfn.XLOOKUP(E:E,'Calificación consecuencia'!B:B,'Calificación consecuencia'!K:K,"No encontrada",2)} -> Baja | I55: Continuidad operacional; Impacto a la operación | J55: Sí | M55: No | O55: Sí | P55: Sí | U55: Tarea CBM programada | V55: Predictivo (basado en condición)
A56: F-MET-022 | B56: Sistema de aire | C56: {=INDEX(Funciones!$G$2:$G$372,MATCH($A56,Funciones!$B$2:$B$372,0))} -> Mantener la presión del depósito principal entre 8,5 y 10 bar | D56: No mantiene la presión del depósito principal. La función se pierde por completo: no se cumple ningún punto del estándar. Estándar: del depósito principal entre 8,5 y 10 bar (fabricante). Se verifica con: manómetro doble B15. | E56: A. Tubería de alimentación del depósito principal rota por vibración y corrosión | F56: 1. Local: La tubería de alimentación del depósito principal se rompe por la vibración y la corrosión y el aire se escapa. 2. En el equipo: El depósito pierde presión de forma continua. El manómetro de depósito principal marca cero o cae continuamente y el conductor recibe la alarma de baja presión. 3. General: Los equipos neumáticos se quedan sin reserva y el tren sale de circulación. | G56: Fisura, deformación o marca de rotura incipiente de la tubería de alimentación del depósito principal. Se detecta con: inspección visual y ensayos no destructivos (líquidos penetrantes o partículas magnéticas). | H56: {=_xlfn.XLOOKUP(E:E,'Calificación consecuencia'!B:B,'Calificación consecuencia'!K:K,"No encontrada",2)} -> Media | I56: Impacto a la operación; Continuidad operacional | J56: Sí | M56: Sí | N56: Sí | U56: Tarea proactiva obligatoria: basada en condición (CBM) | V56: Predictivo (basado en condición)
A57: F-MET-022 | B57: Sistema de aire | C57: {=INDEX(Funciones!$G$2:$G$372,MATCH($A57,Funciones!$B$2:$B$372,0))} -> Mantener la presión del depósito principal entre 8,5 y 10 bar | D57: No mantiene la presión del depósito principal. La función se pierde por completo: no se cumple ningún punto del estándar. Estándar: del depósito principal entre 8,5 y 10 bar (fabricante). Se verifica con: manómetro doble B15. | E57: A. Compresor detenido por motor eléctrico quemado | F57: 1. Local: El motor eléctrico del compresor se quema y el compresor se detiene. 2. En el equipo: No se produce aire comprimido para reponer el consumo del tren. El manómetro de depósito principal cae de forma continua y el conductor recibe la alarma de baja presión. 3. General: Al agotarse la reserva de aire el tren no puede operar sus equipos neumáticos y sale de circulación. | G57: Aumento de temperatura y de consumo de corriente del motor. Se detecta con: termografía; medición de corriente; prueba de aislamiento (megóhmetro). | H57: {=_xlfn.XLOOKUP(E:E,'Calificación consecuencia'!B:B,'Calificación consecuencia'!K:K,"No encontrada",2)} -> Media | I57: Impacto a la operación; Continuidad operacional | J57: Sí | M57: Sí | N57: Sí | U57: Tarea proactiva obligatoria: basada en condición (CBM) | V57: Predictivo (basado en condición)
A58: F-MET-022 | B58: Sistema de aire | C58: {=INDEX(Funciones!$G$2:$G$372,MATCH($A58,Funciones!$B$2:$B$372,0))} -> Mantener la presión del depósito principal entre 8,5 y 10 bar | D58: Mantiene la presión del depósito principal por debajo de 8,5 bar. Estándar: del depósito principal entre 8,5 y 10 bar (fabricante). Se verifica con: manómetro doble B15. | E58: B. Válvulas del compresor desgastadas por fin de vida útil | F58: 1. Local: Las válvulas del compresor se desgastan hasta el final de su vida útil y pierden estanqueidad: parte del aire comprimido se devuelve en cada ciclo. 2. En el equipo: El compresor entrega menos caudal y tarda más en subir la presión. El manómetro marca menos de 8,5 bar y el compresor trabaja sin descanso. 3. General: El tren opera con presión de depósito por debajo del mínimo y con el compresor trabajando continuamente. | G58: Pérdida progresiva de material de las válvulas del compresor hasta acercarse al límite de desgaste. Se detecta con: medición con calibre, galga o micrómetro; inspección visual. | H58: {=_xlfn.XLOOKUP(E:E,'Calificación consecuencia'!B:B,'Calificación consecuencia'!K:K,"No encontrada",2)} -> Baja | I58: Continuidad operacional; Costo de reparación | J58: Sí | M58: No | O58: Sí | P58: Sí | U58: Tarea CBM programada | V58: Predictivo (basado en condición)
A59: F-MET-022 | B59: Sistema de aire | C59: {=INDEX(Funciones!$G$2:$G$372,MATCH($A59,Funciones!$B$2:$B$372,0))} -> Mantener la presión del depósito principal entre 8,5 y 10 bar | D59: Mantiene la presión del depósito principal por debajo de 8,5 bar. Estándar: del depósito principal entre 8,5 y 10 bar (fabricante). Se verifica con: manómetro doble B15. | E59: B. Racor de la tubería principal flojo por vibración | F59: 1. Local: El racor de la tubería principal se afloja por vibración y deja escapar aire. 2. En el equipo: La presión del depósito baja más rápido de lo que el compresor la repone. El manómetro marca menos de 8,5 bar y el compresor trabaja sin descanso. 3. General: El tren opera con presión de depósito por debajo del mínimo y con el compresor trabajando continuamente. | G59: Pérdida de apriete, holgura o marcas de testigo desalineadas del racor de la tubería principal. Se detecta con: control de torque con llave; inspección visual de marcas de testigo. | H59: {=_xlfn.XLOOKUP(E:E,'Calificación consecuencia'!B:B,'Calificación consecuencia'!K:K,"No encontrada",2)} -> Media | I59: Continuidad operacional; Impacto a la operación | J59: Sí | M59: No | O59: Sí | P59: No | Q59: Sí | U59: Tarea basada en tiempo/uso programada | V59: Preventivo (basado en tiempo/uso)
A60: F-MET-022 | B60: Sistema de aire | C60: {=INDEX(Funciones!$G$2:$G$372,MATCH($A60,Funciones!$B$2:$B$372,0))} -> Mantener la presión del depósito principal entre 8,5 y 10 bar | D60: Mantiene la presión del depósito principal por debajo de 8,5 bar. Estándar: del depósito principal entre 8,5 y 10 bar (fabricante). Se verifica con: manómetro doble B15. | E60: B. Válvula de seguridad abierta por resorte debilitado | F60: 1. Local: El resorte de la válvula de seguridad se debilita y la válvula abre a una presión menor a la de tarado. 2. En el equipo: El depósito descarga aire a la atmósfera antes de alcanzar la presión de trabajo. El manómetro marca menos de 8,5 bar y el compresor trabaja sin descanso. 3. General: El tren opera con presión de depósito por debajo del mínimo y con el compresor trabajando continuamente. | G60: Presión de apertura por debajo (o por encima) del tarado, descargas frecuentes o fuga en el asiento de la válvula de seguridad. Se detecta con: prueba de tarado en banco; inspección del asiento; lectura de presión. | H60: {=_xlfn.XLOOKUP(E:E,'Calificación consecuencia'!B:B,'Calificación consecuencia'!K:K,"No encontrada",2)} -> Baja | I60: Continuidad operacional; Impacto a la operación | J60: Sí | M60: No | O60: Sí | P60: No | Q60: Sí | U60: Tarea basada en tiempo/uso programada | V60: Preventivo (basado en tiempo/uso)
A61: F-MET-022 | B61: Sistema de aire | C61: {=INDEX(Funciones!$G$2:$G$372,MATCH($A61,Funciones!$B$2:$B$372,0))} -> Mantener la presión del depósito principal entre 8,5 y 10 bar | D61: Mantiene la presión del depósito principal por encima de 10 bar. Estándar: del depósito principal entre 8,5 y 10 bar (fabricante). Se verifica con: manómetro doble B15. | E61: C. Presostato del compresor descalibrado por deriva con el tiempo | F61: 1. Local: El presostato del compresor se descalibra por deriva con el tiempo y no corta el compresor a la presión prevista. 2. En el equipo: El compresor sigue comprimiendo y la presión del depósito sube por encima de 10 bar. El manómetro supera 10 bar y la válvula de seguridad descarga. 3. General: El tren opera con presión por encima del rango y la válvula de seguridad descarga aire. | G61: Deriva del presostato del compresor frente al valor patrón, con lecturas o ajustes que se van corriendo. Se detecta con: verificación contra patrón calibrado; lectura de parámetros; medición de alineación o vibración. | H61: {=_xlfn.XLOOKUP(E:E,'Calificación consecuencia'!B:B,'Calificación consecuencia'!K:K,"No encontrada",2)} -> Baja | I61: Costo de reparación; Continuidad operacional | J61: Sí | M61: No | O61: Sí | P61: Sí | U61: Tarea CBM programada | V61: Predictivo (basado en condición)
A62: F-MET-022 | B62: Sistema de aire | C62: {=INDEX(Funciones!$G$2:$G$372,MATCH($A62,Funciones!$B$2:$B$372,0))} -> Mantener la presión del depósito principal entre 8,5 y 10 bar | D62: Mantiene la presión del depósito principal por encima de 10 bar. Estándar: del depósito principal entre 8,5 y 10 bar (fabricante). Se verifica con: manómetro doble B15. | E62: C. Válvula de seguridad atascada por corrosión del asiento | F62: 1. Local: El asiento de la válvula de seguridad se corroe y la válvula se atasca cerrada. 2. En el equipo: El depósito no descarga el exceso de presión. El manómetro supera 10 bar y la válvula de seguridad descarga cuando logra abrir. 3. General: El tren opera con presión por encima del rango de 8,5 a 10 bar. | G62: Respuesta más lenta o movimiento duro de la válvula de seguridad antes de quedar trabado. Se detecta con: prueba funcional; medición de tiempos de ciclo. | H62: {=_xlfn.XLOOKUP(E:E,'Calificación consecuencia'!B:B,'Calificación consecuencia'!K:K,"No encontrada",2)} -> Baja | I62: Continuidad operacional; Impacto a la operación | J62: Sí | M62: No | O62: Sí | P62: No | Q62: Sí | U62: Tarea basada en tiempo/uso programada | V62: Preventivo (basado en tiempo/uso)
A63: F-MET-022 | B63: Sistema de aire | C63: {=INDEX(Funciones!$G$2:$G$372,MATCH($A63,Funciones!$B$2:$B$372,0))} -> Mantener la presión del depósito principal entre 8,5 y 10 bar | D63: Mantiene la presión del depósito principal con oscilaciones fuera del rango de 8,5 a 10 bar. Estándar: del depósito principal entre 8,5 y 10 bar (fabricante). Se verifica con: manómetro doble B15. | E63: D. Presostato inestable por contactos sulfatados | F63: 1. Local: Los contactos del presostato se sulfatan y cambian de estado de forma inestable. 2. En el equipo: El compresor arranca y para sin seguir los umbrales de presión. La presión sube y baja sin patrón y el compresor arranca y para con frecuencia. 3. General: El depósito opera con oscilaciones fuera del rango de 8,5 a 10 bar y el compresor sufre arranques frecuentes. | G63: Deriva del presostato frente al valor patrón, con lecturas o ajustes que se van corriendo. Se detecta con: verificación contra patrón calibrado; lectura de parámetros; medición de alineación o vibración. | H63: {=_xlfn.XLOOKUP(E:E,'Calificación consecuencia'!B:B,'Calificación consecuencia'!K:K,"No encontrada",2)} -> Media | I63: Continuidad operacional; Impacto a la operación | J63: Sí | M63: No | O63: Sí | P63: No | Q63: Sí | U63: Tarea basada en tiempo/uso programada | V63: Preventivo (basado en tiempo/uso)
A64: F-MET-022 | B64: Sistema de aire | C64: {=INDEX(Funciones!$G$2:$G$372,MATCH($A64,Funciones!$B$2:$B$372,0))} -> Mantener la presión del depósito principal entre 8,5 y 10 bar | D64: Mantiene la presión del depósito principal con oscilaciones fuera del rango de 8,5 a 10 bar. Estándar: del depósito principal entre 8,5 y 10 bar (fabricante). Se verifica con: manómetro doble B15. | E64: D. Electroválvula de descarga pegajosa por suciedad en el asiento | F64: 1. Local: El asiento de la electroválvula de descarga se llena de suciedad y la válvula se pega, descargando o reteniendo aire fuera de ciclo. 2. En el equipo: La presión del depósito varía sin relación con el consumo. La presión sube y baja sin patrón y el compresor arranca y para con frecuencia. 3. General: El depósito opera con oscilaciones fuera del rango de 8,5 a 10 bar y el compresor sufre arranques frecuentes. | G64: Respuesta más lenta o movimiento duro de la electroválvula de descarga antes de quedar trabado. Se detecta con: prueba funcional; medición de tiempos de ciclo. | H64: {=_xlfn.XLOOKUP(E:E,'Calificación consecuencia'!B:B,'Calificación consecuencia'!K:K,"No encontrada",2)} -> Media | I64: Continuidad operacional; Impacto a la operación | J64: Sí | M64: No | O64: Sí | P64: No | Q64: Sí | U64: Tarea basada en tiempo/uso programada | V64: Preventivo (basado en tiempo/uso)
A65: F-MET-023 | B65: Sistema de aire | C65: {=INDEX(Funciones!$G$2:$G$372,MATCH($A65,Funciones!$B$2:$B$372,0))} -> Contener el aire del circuito principal con caída máxima de 0,2 bar en 5 min | D65: No contiene el aire del circuito principal. La función se pierde por completo: no se cumple ningún punto del estándar. Estándar: del circuito principal con caída máxima de 0,2 bar en 5 min (fabricante). Se verifica con: prueba de estanqueidad con compresores parados. | E65: A. Manguera del circuito principal rota por envejecimiento del caucho | F65: 1. Local: La manguera del circuito principal se rompe por el envejecimiento del caucho y el aire sale por la rotura. 2. En el equipo: La presión del circuito cae rápidamente. Se oye una fuga fuerte y el manómetro cae en segundos. 3. General: El circuito no contiene el aire y los equipos neumáticos se quedan sin presión. | G65: Grietas, resequedad, abultamientos o rozaduras visibles de la manguera del circuito principal. Se detecta con: inspección visual. | H65: {=_xlfn.XLOOKUP(E:E,'Calificación consecuencia'!B:B,'Calificación consecuencia'!K:K,"No encontrada",2)} -> Media | I65: Impacto a la operación; Continuidad operacional | J65: Sí | M65: Sí | N65: Sí | U65: Tarea proactiva obligatoria: basada en condición (CBM) | V65: Predictivo (basado en condición)
A66: F-MET-023 | B66: Sistema de aire | C66: {=INDEX(Funciones!$G$2:$G$372,MATCH($A66,Funciones!$B$2:$B$372,0))} -> Contener el aire del circuito principal con caída máxima de 0,2 bar en 5 min | D66: No contiene el aire del circuito principal. La función se pierde por completo: no se cumple ningún punto del estándar. Estándar: del circuito principal con caída máxima de 0,2 bar en 5 min (fabricante). Se verifica con: prueba de estanqueidad con compresores parados. | E66: A. Depósito de aire fisurado por corrosión | F66: 1. Local: El depósito de aire se fisura por corrosión y el aire sale por la grieta. 2. En el equipo: El depósito pierde la presión almacenada. Se oye una fuga fuerte y el manómetro cae en segundos. 3. General: El circuito no contiene el aire y los equipos neumáticos se quedan sin presión. | G66: Fisura, deformación o marca de rotura incipiente del depósito de aire. Se detecta con: inspección visual y ensayos no destructivos (líquidos penetrantes o partículas magnéticas). | H66: {=_xlfn.XLOOKUP(E:E,'Calificación consecuencia'!B:B,'Calificación consecuencia'!K:K,"No encontrada",2)} -> Media | I66: Impacto a la operación; Continuidad operacional | J66: Sí | M66: Sí | N66: Sí | U66: Tarea proactiva obligatoria: basada en condición (CBM) | V66: Predictivo (basado en condición)
A67: F-MET-023 | B67: Sistema de aire | C67: {=INDEX(Funciones!$G$2:$G$372,MATCH($A67,Funciones!$B$2:$B$372,0))} -> Contener el aire del circuito principal con caída máxima de 0,2 bar en 5 min | D67: Contiene el aire del circuito principal con caída mayor a 0,2 bar en 5 min. Estándar: del circuito principal con caída máxima de 0,2 bar en 5 min (fabricante). Se verifica con: prueba de estanqueidad con compresores parados. | E67: C. Racor del circuito principal flojo por vibración | F67: 1. Local: El racor del circuito principal se afloja por vibración y deja una fuga pequeña. 2. En el equipo: El manómetro cae más de lo permitido durante el reposo. En la prueba de estanqueidad el manómetro cae más de 0,2 bar en 5 min. 3. General: El compresor debe reponer aire con mayor frecuencia y trabaja de más. | G67: Pérdida de apriete, holgura o marcas de testigo desalineadas del racor del circuito principal. Se detecta con: control de torque con llave; inspección visual de marcas de testigo. | H67: {=_xlfn.XLOOKUP(E:E,'Calificación consecuencia'!B:B,'Calificación consecuencia'!K:K,"No encontrada",2)} -> Media | I67: Continuidad operacional; Impacto a la operación | J67: Sí | M67: No | O67: Sí | P67: No | Q67: Sí | U67: Tarea basada en tiempo/uso programada | V67: Preventivo (basado en tiempo/uso)
A68: F-MET-023 | B68: Sistema de aire | C68: {=INDEX(Funciones!$G$2:$G$372,MATCH($A68,Funciones!$B$2:$B$372,0))} -> Contener el aire del circuito principal con caída máxima de 0,2 bar en 5 min | D68: Contiene el aire del circuito principal con caída mayor a 0,2 bar en 5 min. Estándar: del circuito principal con caída máxima de 0,2 bar en 5 min (fabricante). Se verifica con: prueba de estanqueidad con compresores parados. | E68: C. Empaque de la válvula resecado por envejecimiento | F68: 1. Local: El empaque de la válvula se reseca por el envejecimiento y pierde su elasticidad; deja de sellar contra el asiento. 2. En el equipo: Se escapa aire de forma lenta y continua por la válvula. En la prueba de estanqueidad el manómetro cae más de 0,2 bar en 5 min. 3. General: El circuito principal pierde presión en reposo y el compresor debe reponerla con mayor frecuencia. | G68: Pérdida de elasticidad, grietas finas o resequedad del empaque de la válvula. Se detecta con: inspección visual; medición de prestaciones (presión, caudal). | H68: {=_xlfn.XLOOKUP(E:E,'Calificación consecuencia'!B:B,'Calificación consecuencia'!K:K,"No encontrada",2)} -> Baja | I68: Continuidad operacional; Impacto a la operación | J68: Sí | M68: No | O68: Sí | P68: No | Q68: Sí | U68: Tarea basada en tiempo/uso programada | V68: Preventivo (basado en tiempo/uso)
A69: F-MET-023 | B69: Sistema de aire | C69: {=INDEX(Funciones!$G$2:$G$372,MATCH($A69,Funciones!$B$2:$B$372,0))} -> Contener el aire del circuito principal con caída máxima de 0,2 bar en 5 min | D69: Contiene el aire del circuito principal con caída mayor a 0,2 bar en 5 min. Estándar: del circuito principal con caída máxima de 0,2 bar en 5 min (fabricante). Se verifica con: prueba de estanqueidad con compresores parados. | E69: C. Válvula de purga abierta por asiento dañado | F69: 1. Local: El asiento de la válvula de purga se daña y la válvula queda abierta o sin cerrar del todo. 2. En el equipo: Parte del aire del circuito sale continuamente por la purga. En la prueba de estanqueidad el manómetro cae más de 0,2 bar en 5 min. 3. General: El circuito principal pierde presión en reposo y el compresor debe reponerla con mayor frecuencia. | G69: Presión de apertura por debajo (o por encima) del tarado, descargas frecuentes o fuga en el asiento de la válvula de purga. Se detecta con: prueba de tarado en banco; inspección del asiento; lectura de presión. | H69: {=_xlfn.XLOOKUP(E:E,'Calificación consecuencia'!B:B,'Calificación consecuencia'!K:K,"No encontrada",2)} -> Baja | I69: Continuidad operacional; Impacto a la operación | J69: Sí | M69: No | O69: Sí | P69: No | Q69: Sí | U69: Tarea basada en tiempo/uso programada | V69: Preventivo (basado en tiempo/uso)
A70: F-MET-023 | B70: Sistema de aire | C70: {=INDEX(Funciones!$G$2:$G$372,MATCH($A70,Funciones!$B$2:$B$372,0))} -> Contener el aire del circuito principal con caída máxima de 0,2 bar en 5 min | D70: Contiene el aire del circuito principal con caída mayor a 0,2 bar en 5 min. Estándar: del circuito principal con caída máxima de 0,2 bar en 5 min (fabricante). Se verifica con: prueba de estanqueidad con compresores parados. | E70: C. Junta de racor resecada por ciclos térmicos | F70: 1. Local: La junta del racor se reseca por los ciclos térmicos y sella solo en algunas condiciones de temperatura. 2. En el equipo: Hay una fuga de aire que aparece y desaparece con la temperatura o la vibración. La fuga aparece y desaparece con la temperatura o la vibración y el compresor arranca sin razón. 3. General: El circuito pierde presión de forma intermitente y el compresor trabaja más de lo normal. | G70: Pérdida de elasticidad, grietas finas o resequedad de la junta de racor. Se detecta con: inspección visual; medición de prestaciones (presión, caudal). | H70: {=_xlfn.XLOOKUP(E:E,'Calificación consecuencia'!B:B,'Calificación consecuencia'!K:K,"No encontrada",2)} -> Baja | I70: Continuidad operacional; Impacto a la operación | J70: Sí | M70: No | O70: Sí | P70: No | Q70: Sí | U70: Tarea basada en tiempo/uso programada | V70: Preventivo (basado en tiempo/uso)
A71: F-MET-023 | B71: Sistema de aire | C71: {=INDEX(Funciones!$G$2:$G$372,MATCH($A71,Funciones!$B$2:$B$372,0))} -> Contener el aire del circuito principal con caída máxima de 0,2 bar en 5 min | D71: Contiene el aire del circuito principal con caída mayor a 0,2 bar en 5 min. Estándar: del circuito principal con caída máxima de 0,2 bar en 5 min (fabricante). Se verifica con: prueba de estanqueidad con compresores parados. | E71: C. Válvula de retención rayada por partículas en el asiento | F71: 1. Local: Las partículas rayan el asiento de la válvula de retención y la válvula no cierra del todo. 2. En el equipo: El aire retrocede hacia el compresor o sale por el asiento de manera intermitente. La fuga aparece y desaparece con la temperatura o la vibración y el compresor arranca sin razón. 3. General: El circuito pierde presión de forma intermitente y el compresor trabaja más de lo normal. | G71: Pérdida progresiva de material de la válvula de retención hasta acercarse al límite de desgaste. Se detecta con: medición con calibre, galga o micrómetro; inspección visual. | H71: {=_xlfn.XLOOKUP(E:E,'Calificación consecuencia'!B:B,'Calificación consecuencia'!K:K,"No encontrada",2)} -> Baja | I71: Continuidad operacional; Impacto a la operación | J71: Sí | M71: No | O71: Sí | P71: No | Q71: Sí | U71: Tarea basada en tiempo/uso programada | V71: Preventivo (basado en tiempo/uso)
A72: F-MET-026 | B72: Secador de aire (×2) · B0700 | C72: {=INDEX(Funciones!$G$2:$G$372,MATCH($A72,Funciones!$B$2:$B$372,0))} -> Secar el aire comprimido con punto de rocío máximo de +3 °C | D72: No seca el aire comprimido. La función se pierde por completo: no se cumple ningún punto del estándar. Estándar: con punto de rocío máximo de +3 °C (norma: ISO 8573-1). Se verifica con: purga diaria de calderines sin agua. | E72: A. Cartucho desecante saturado por agotamiento del desecante | F72: 1. Local: El desecante del cartucho se agota y deja de absorber la humedad del aire. 2. En el equipo: El aire sale del secador con el mismo contenido de agua con que entró. No se nota en servicio; se descubre por agua abundante en la purga de calderines. 3. General: El aire húmedo llega a los depósitos y a los equipos neumáticos. | G72: Aumento de la presión diferencial o caída del caudal por acumulación de suciedad del cartucho desecante. Se detecta con: lectura de manómetros y diferencial de presión; medición de caudal; inspección visual. Al ser una función oculta no se nota en operación: depende de la inspección o prueba programada. | H72: {=_xlfn.XLOOKUP(E:E,'Calificación consecuencia'!B:B,'Calificación consecuencia'!K:K,"No encontrada",2)} -> Media | I72: Seguridad; Continuidad operacional | J72: No | K72: Sí | U72: Tarea de búsqueda de falla programada | V72: Detectivo (búsqueda de falla)
A73: F-MET-026 | B73: Secador de aire (×2) · B0700 | C73: {=INDEX(Funciones!$G$2:$G$372,MATCH($A73,Funciones!$B$2:$B$372,0))} -> Secar el aire comprimido con punto de rocío máximo de +3 °C | D73: No seca el aire comprimido. La función se pierde por completo: no se cumple ningún punto del estándar. Estándar: con punto de rocío máximo de +3 °C (norma: ISO 8573-1). Se verifica con: purga diaria de calderines sin agua. | E73: A. Válvula de regeneración del secador atascada por contaminación | F73: 1. Local: La válvula de regeneración del secador se atasca por contaminación y no cambia de ciclo. 2. En el equipo: El cartucho no se regenera y se satura con la humedad que retiene. No se nota en servicio; se descubre por agua abundante en la purga de calderines. 3. General: El aire húmedo llega a los depósitos y a los equipos neumáticos. | G73: Respuesta más lenta o movimiento duro de la válvula de regeneración del secador antes de quedar trabado. Se detecta con: prueba funcional; medición de tiempos de ciclo. Al ser una función oculta no se nota en operación: depende de la inspección o prueba programada. | H73: {=_xlfn.XLOOKUP(E:E,'Calificación consecuencia'!B:B,'Calificación consecuencia'!K:K,"No encontrada",2)} -> Media | I73: Seguridad; Continuidad operacional | J73: No | K73: Sí | U73: Tarea de búsqueda de falla programada | V73: Detectivo (búsqueda de falla)
A74: F-MET-026 | B74: Secador de aire (×2) · B0700 | C74: {=INDEX(Funciones!$G$2:$G$372,MATCH($A74,Funciones!$B$2:$B$372,0))} -> Secar el aire comprimido con punto de rocío máximo de +3 °C | D74: No seca el aire comprimido. La función se pierde por completo: no se cumple ningún punto del estándar. Estándar: con punto de rocío máximo de +3 °C (norma: ISO 8573-1). Se verifica con: purga diaria de calderines sin agua. | E74: A. Secador apagado por resistencia de calefacción quemada | F74: 1. Local: La resistencia de calefacción del secador se quema y el secador queda sin calentamiento. 2. En el equipo: El desecante no se regenera y la humedad del aire no se retira. No se nota en servicio; se descubre por agua abundante en la purga de calderines. 3. General: El aire húmedo llega a los depósitos y a los equipos neumáticos. | G74: Aumento de temperatura y de consumo de corriente de la resistencia de calefacción. Se detecta con: termografía; medición de corriente; prueba de aislamiento (megóhmetro). Al ser una función oculta no se nota en operación: depende de la inspección o prueba programada. | H74: {=_xlfn.XLOOKUP(E:E,'Calificación consecuencia'!B:B,'Calificación consecuencia'!K:K,"No encontrada",2)} -> Media | I74: Seguridad; Continuidad operacional | J74: No | K74: Sí | U74: Tarea de búsqueda de falla programada | V74: Detectivo (búsqueda de falla)
A75: F-MET-026 | B75: Secador de aire (×2) · B0700 | C75: {=INDEX(Funciones!$G$2:$G$372,MATCH($A75,Funciones!$B$2:$B$372,0))} -> Secar el aire comprimido con punto de rocío máximo de +3 °C | D75: Seca el aire comprimido con punto de rocío mayor a +3 °C. Estándar: con punto de rocío máximo de +3 °C (norma: ISO 8573-1). Se verifica con: purga diaria de calderines sin agua. | E75: C. Cartucho desecante degradado por fin de vida útil | F75: 1. Local: El desecante llega al final de su vida útil y retiene menos humedad de la necesaria. 2. En el equipo: El aire sale del secador con humedad residual. La purga diaria muestra agua y la medición de rocío supera +3 °C. 3. General: El aire llega a los depósitos y a los equipos con un punto de rocío mayor al permitido. | G75: Caída gradual del rendimiento del cartucho desecante, con ruido, calentamiento o vibración mayor a la normal. Se detecta con: medición de prestaciones; análisis de vibraciones o termografía. Al ser una función oculta no se nota en operación: depende de la inspección o prueba programada. | H75: {=_xlfn.XLOOKUP(E:E,'Calificación consecuencia'!B:B,'Calificación consecuencia'!K:K,"No encontrada",2)} -> Baja | I75: Continuidad operacional | J75: No | K75: Sí | U75: Tarea de búsqueda de falla programada | V75: Detectivo (búsqueda de falla)
A76: F-MET-026 | B76: Secador de aire (×2) · B0700 | C76: {=INDEX(Funciones!$G$2:$G$372,MATCH($A76,Funciones!$B$2:$B$372,0))} -> Secar el aire comprimido con punto de rocío máximo de +3 °C | D76: Seca el aire comprimido con punto de rocío mayor a +3 °C. Estándar: con punto de rocío máximo de +3 °C (norma: ISO 8573-1). Se verifica con: purga diaria de calderines sin agua. | E76: C. Filtro coalescente saturado por aceite del compresor | F76: 1. Local: El filtro coalescente se satura con el aceite que arrastra el compresor y pierde capacidad de separación. 2. En el equipo: El aceite y el agua pasan hacia el desecante y lo contaminan. La purga diaria muestra agua y la medición de rocío supera +3 °C. 3. General: El aire llega a los depósitos y a los equipos con un punto de rocío mayor al permitido. | G76: Aumento de la presión diferencial o caída del caudal por acumulación de suciedad del filtro coalescente. Se detecta con: lectura de manómetros y diferencial de presión; medición de caudal; inspección visual. Al ser una función oculta no se nota en operación: depende de la inspección o prueba programada. | H76: {=_xlfn.XLOOKUP(E:E,'Calificación consecuencia'!B:B,'Calificación consecuencia'!K:K,"No encontrada",2)} -> Baja | I76: Continuidad operacional | J76: No | K76: Sí | U76: Tarea de búsqueda de falla programada | V76: Detectivo (búsqueda de falla)
A77: F-MET-026 | B77: Secador de aire (×2) · B0700 | C77: {=INDEX(Funciones!$G$2:$G$372,MATCH($A77,Funciones!$B$2:$B$372,0))} -> Secar el aire comprimido con punto de rocío máximo de +3 °C | D77: Seca el aire comprimido con punto de rocío mayor a +3 °C. Estándar: con punto de rocío máximo de +3 °C (norma: ISO 8573-1). Se verifica con: purga diaria de calderines sin agua. | E77: C. Válvula de purga automática obstruida por suciedad | F77: 1. Local: La válvula de purga automática se obstruye con suciedad y no expulsa el condensado. 2. En el equipo: El agua se acumula en el secador y en los depósitos. La purga diaria muestra agua y la medición de rocío supera +3 °C. 3. General: El aire llega a los equipos con un punto de rocío mayor al permitido. | G77: Aumento de la presión diferencial o caída del caudal por acumulación de suciedad de la válvula de purga automática. Se detecta con: lectura de manómetros y diferencial de presión; medición de caudal; inspección visual. Al ser una función oculta no se nota en operación: depende de la inspección o prueba programada. | H77: {=_xlfn.XLOOKUP(E:E,'Calificación consecuencia'!B:B,'Calificación consecuencia'!K:K,"No encontrada",2)} -> Baja | I77: Continuidad operacional | J77: No | K77: Sí | U77: Tarea de búsqueda de falla programada | V77: Detectivo (búsqueda de falla)
A78: F-MET-027 | B78: Bomba hidráulica (×4) · B0700 | C78: {=INDEX(Funciones!$G$2:$G$372,MATCH($A78,Funciones!$B$2:$B$372,0))} -> Suministrar caudal de aceite [ESTÁNDAR POR CONFIRMAR] | D78: No suministra caudal de aceite. La función se pierde por completo: no se cumple ningún punto del estándar. Estándar: por confirmar. Se verifica con: caudalímetro / tiempos de ciclo. | E78: A. Bomba hidráulica gripada por pérdida de aceite o contaminación del lubricante | F78: 1. Local: La bomba hidráulica se traba (se gripa) por falta de aceite o por contaminación del lubricante; sus piezas internas quedan rozando sin película de aceite. 2. En el equipo: La bomba deja de mover aceite y el manómetro de la línea queda en cero. El actuador no responde. Además, el aceite contaminado y las partículas desprendidas circulan por el circuito y dañan otros componentes. 3. General: La máquina no ejecuta los movimientos hidráulicos y queda fuera de servicio. | G78: Movimiento duro, ruido o calentamiento anormal de la bomba hidráulica antes de trabarse. Se detecta con: análisis de vibraciones; termografía; análisis de partículas en el aceite. | H78: {=_xlfn.XLOOKUP(E:E,'Calificación consecuencia'!B:B,'Calificación consecuencia'!K:K,"No encontrada",2)} -> Media | I78: Continuidad operacional; Costo de reparación | J78: Sí | M78: No | O78: Sí | P78: Sí | U78: Tarea CBM programada | V78: Predictivo (basado en condición)
A79: F-MET-027 | B79: Bomba hidráulica (×4) · B0700 | C79: {=INDEX(Funciones!$G$2:$G$372,MATCH($A79,Funciones!$B$2:$B$372,0))} -> Suministrar caudal de aceite [ESTÁNDAR POR CONFIRMAR] | D79: No suministra caudal de aceite. La función se pierde por completo: no se cumple ningún punto del estándar. Estándar: por confirmar. Se verifica con: caudalímetro / tiempos de ciclo. | E79: A. Acople de la bomba roto por desalineación | F79: 1. Local: El acople de la bomba se rompe por la desalineación y el motor deja de transmitir giro a la bomba. 2. En el equipo: La bomba no gira y no mueve aceite. El actuador no responde y el manómetro de la línea queda en cero. 3. General: La máquina no ejecuta los movimientos hidráulicos y queda fuera de servicio. | G79: Fisura, deformación o marca de rotura incipiente del acople de la bomba. Se detecta con: inspección visual y ensayos no destructivos (líquidos penetrantes o partículas magnéticas). | H79: {=_xlfn.XLOOKUP(E:E,'Calificación consecuencia'!B:B,'Calificación consecuencia'!K:K,"No encontrada",2)} -> Baja | I79: Continuidad operacional; Costo de reparación | J79: Sí | M79: No | O79: Sí | P79: Sí | U79: Tarea CBM programada | V79: Predictivo (basado en condición)
A80: F-MET-027 | B80: Bomba hidráulica (×4) · B0700 | C80: {=INDEX(Funciones!$G$2:$G$372,MATCH($A80,Funciones!$B$2:$B$372,0))} -> Suministrar caudal de aceite [ESTÁNDAR POR CONFIRMAR] | D80: No suministra caudal de aceite. La función se pierde por completo: no se cumple ningún punto del estándar. Estándar: por confirmar. Se verifica con: caudalímetro / tiempos de ciclo. | E80: A. Filtro de succión obstruido por suciedad acumulada | F80: 1. Local: El filtro de succión se obstruye con suciedad y no deja pasar el aceite hacia la bomba. 2. En el equipo: La bomba se queda sin aceite en su entrada. El actuador no responde y el manómetro de la línea queda en cero. 3. General: La máquina no ejecuta los movimientos hidráulicos y queda fuera de servicio. | G80: Aumento de la presión diferencial o caída del caudal por acumulación de suciedad del filtro de succión. Se detecta con: lectura de manómetros y diferencial de presión; medición de caudal; inspección visual. | H80: {=_xlfn.XLOOKUP(E:E,'Calificación consecuencia'!B:B,'Calificación consecuencia'!K:K,"No encontrada",2)} -> Baja | I80: Continuidad operacional | J80: Sí | M80: No | O80: No | S80: No | U80: Sin mantenimiento proactivo programado (operar hasta la falla) | V80: Correctivo (operar hasta la falla)
A81: F-MET-027 | B81: Bomba hidráulica (×4) · B0700 | C81: {=INDEX(Funciones!$G$2:$G$372,MATCH($A81,Funciones!$B$2:$B$372,0))} -> Suministrar caudal de aceite [ESTÁNDAR POR CONFIRMAR] | D81: Suministra caudal de aceite por debajo del caudal nominal. Estándar: por confirmar. Se verifica con: caudalímetro / tiempos de ciclo. | E81: B. Bomba hidráulica desgastada por holguras internas | F81: 1. Local: Las holguras internas de la bomba aumentan por el desgaste y parte del aceite se devuelve por ellas. 2. En el equipo: La bomba entrega menos caudal del nominal y el aceite se calienta. La máquina trabaja lenta y el aceite se calienta más de lo normal. 3. General: Los movimientos hidráulicos se hacen con menor velocidad y los ciclos de trabajo se alargan. | G81: Pérdida progresiva de material de la bomba hidráulica hasta acercarse al límite de desgaste. Se detecta con: medición con calibre, galga o micrómetro; inspección visual. | H81: {=_xlfn.XLOOKUP(E:E,'Calificación consecuencia'!B:B,'Calificación consecuencia'!K:K,"No encontrada",2)} -> Baja | I81: Continuidad operacional; Costo de reparación | J81: Sí | M81: No | O81: Sí | P81: Sí | U81: Tarea CBM programada | V81: Predictivo (basado en condición)
A82: F-MET-027 | B82: Bomba hidráulica (×4) · B0700 | C82: {=INDEX(Funciones!$G$2:$G$372,MATCH($A82,Funciones!$B$2:$B$372,0))} -> Suministrar caudal de aceite [ESTÁNDAR POR CONFIRMAR] | D82: Suministra caudal de aceite por debajo del caudal nominal. Estándar: por confirmar. Se verifica con: caudalímetro / tiempos de ciclo. | E82: B. Racor de succión flojo por vibración | F82: 1. Local: El racor de succión se afloja por vibración y la bomba aspira aire junto con el aceite. 2. En el equipo: El caudal de aceite baja y la bomba trabaja con ruido. La máquina trabaja lenta y el aceite se calienta más de lo normal. 3. General: Los movimientos hidráulicos se hacen con menor velocidad y los ciclos de trabajo se alargan. | G82: Pérdida de apriete, holgura o marcas de testigo desalineadas del racor de succión. Se detecta con: control de torque con llave; inspección visual de marcas de testigo. | H82: {=_xlfn.XLOOKUP(E:E,'Calificación consecuencia'!B:B,'Calificación consecuencia'!K:K,"No encontrada",2)} -> Baja | I82: Continuidad operacional | J82: Sí | M82: No | O82: No | S82: No | U82: Sin mantenimiento proactivo programado (operar hasta la falla) | V82: Correctivo (operar hasta la falla) | W82: cambio del racor
A83: F-MET-027 | B83: Bomba hidráulica (×4) · B0700 | C83: {=INDEX(Funciones!$G$2:$G$372,MATCH($A83,Funciones!$B$2:$B$372,0))} -> Suministrar caudal de aceite [ESTÁNDAR POR CONFIRMAR] | D83: Suministra caudal de aceite por debajo del caudal nominal. Estándar: por confirmar. Se verifica con: caudalímetro / tiempos de ciclo. | E83: B. Filtro de succión colmatado por suciedad acumulada | F83: 1. Local: El filtro de succión se colmata con suciedad acumulada y restringe el paso de aceite. 2. En el equipo: La bomba aspira con dificultad y entrega menos caudal. La máquina trabaja lenta y el aceite se calienta más de lo normal. 3. General: Los movimientos hidráulicos se hacen con menor velocidad y los ciclos de trabajo se alargan. | G83: Aumento de la presión diferencial o caída del caudal por acumulación de suciedad del filtro de succión. Se detecta con: lectura de manómetros y diferencial de presión; medición de caudal; inspección visual. | H83: {=_xlfn.XLOOKUP(E:E,'Calificación consecuencia'!B:B,'Calificación consecuencia'!K:K,"No encontrada",2)} -> Baja | I83: Continuidad operacional | J83: Sí | M83: No | O83: No | S83: No | U83: Sin mantenimiento proactivo programado (operar hasta la falla) | V83: Correctivo (operar hasta la falla)
A84: F-MET-027 | B84: Bomba hidráulica (×4) · B0700 | C84: {=INDEX(Funciones!$G$2:$G$372,MATCH($A84,Funciones!$B$2:$B$372,0))} -> Suministrar caudal de aceite [ESTÁNDAR POR CONFIRMAR] | D84: Suministra caudal de aceite por debajo del caudal nominal. Estándar: por confirmar. Se verifica con: caudalímetro / tiempos de ciclo. | E84: B. Bomba hidráulica ruidosa por aire en la succión | F84: 1. Local: Entra aire a la succión de la bomba y se forman burbujas que colapsan dentro de la bomba (cavitación). 2. En el equipo: La bomba entrega caudal irregular y hace ruido. La bomba funciona a ratos y se escucha ruido de cavitación. 3. General: Los movimientos hidráulicos son lentos e irregulares. | G84: Ruido anormal, vibración o espuma en el aceite de la bomba hidráulica. Se detecta con: inspección auditiva y visual del nivel y del aceite; medición de vibración. | H84: {=_xlfn.XLOOKUP(E:E,'Calificación consecuencia'!B:B,'Calificación consecuencia'!K:K,"No encontrada",2)} -> Media | I84: Continuidad operacional; Costo de reparación | J84: Sí | M84: No | O84: Sí | P84: Sí | U84: Tarea CBM programada | V84: Predictivo (basado en condición)
A85: F-MET-027 | B85: Bomba hidráulica (×4) · B0700 | C85: {=INDEX(Funciones!$G$2:$G$372,MATCH($A85,Funciones!$B$2:$B$372,0))} -> Suministrar caudal de aceite [ESTÁNDAR POR CONFIRMAR] | D85: Suministra caudal de aceite por debajo del caudal nominal. Estándar: por confirmar. Se verifica con: caudalímetro / tiempos de ciclo. | E85: B. Aceite del tanque insuficiente por fuga en manguera | F85: 1. Local: El nivel de aceite del tanque baja por una fuga en la manguera y la bomba aspira aceite mezclado con aire. 2. En el equipo: El caudal de la bomba baja y se forman burbujas. La bomba funciona a ratos y se escucha ruido de cavitación. Además, el aceite fugado queda sobre la máquina y el suelo. 3. General: Los movimientos hidráulicos son lentos e irregulares. | G85: Humedad, goteo o pérdida de nivel o de presión alrededor del aceite del tanque. Se detecta con: inspección visual; prueba de estanqueidad; lectura de nivel y presión. | H85: {=_xlfn.XLOOKUP(E:E,'Calificación consecuencia'!B:B,'Calificación consecuencia'!K:K,"No encontrada",2)} -> Baja | I85: Continuidad operacional | J85: Sí | M85: No | O85: No | S85: No | U85: Sin mantenimiento proactivo programado (operar hasta la falla) | V85: Correctivo (operar hasta la falla)
A86: F-MET-028 | B86: Bomba hidráulica (×4) · B0700 | C86: {=INDEX(Funciones!$G$2:$G$372,MATCH($A86,Funciones!$B$2:$B$372,0))} -> Generar presión hidráulica [ESTÁNDAR POR CONFIRMAR] | D86: No genera presión hidráulica. La función se pierde por completo: no se cumple ningún punto del estándar. Estándar: por confirmar. Se verifica con: manómetro. | E86: A. Válvula de alivio abierta por resorte roto | F86: 1. Local: El resorte de la válvula de alivio se rompe y la válvula queda abierta, enviando el aceite directo al tanque. 2. En el equipo: El circuito no acumula presión aunque la bomba funcione. El manómetro hidráulico marca cero y el actuador no se mueve. 3. General: La máquina no ejecuta los movimientos hidráulicos y queda fuera de servicio. | G86: Presión de apertura por debajo (o por encima) del tarado, descargas frecuentes o fuga en el asiento de la válvula de alivio. Se detecta con: prueba de tarado en banco; inspección del asiento; lectura de presión. | H86: {=_xlfn.XLOOKUP(E:E,'Calificación consecuencia'!B:B,'Calificación consecuencia'!K:K,"No encontrada",2)} -> Baja | I86: Continuidad operacional | J86: Sí | M86: No | O86: No | S86: No | U86: Sin mantenimiento proactivo programado (operar hasta la falla) | V86: Correctivo (operar hasta la falla)
A87: F-MET-028 | B87: Bomba hidráulica (×4) · B0700 | C87: {=INDEX(Funciones!$G$2:$G$372,MATCH($A87,Funciones!$B$2:$B$372,0))} -> Generar presión hidráulica [ESTÁNDAR POR CONFIRMAR] | D87: No genera presión hidráulica. La función se pierde por completo: no se cumple ningún punto del estándar. Estándar: por confirmar. Se verifica con: manómetro. | E87: A. Bomba hidráulica gripada por pérdida de aceite o contaminación del lubricante | F87: 1. Local: La bomba se traba por falta de aceite o contaminación del lubricante y deja de generar flujo. 2. En el equipo: No se genera presión en el circuito. El manómetro hidráulico marca cero y el actuador no se mueve. 3. General: La máquina no ejecuta los movimientos hidráulicos y queda fuera de servicio. | G87: Movimiento duro, ruido o calentamiento anormal de la bomba hidráulica antes de trabarse. Se detecta con: análisis de vibraciones; termografía; análisis de partículas en el aceite. | H87: {=_xlfn.XLOOKUP(E:E,'Calificación consecuencia'!B:B,'Calificación consecuencia'!K:K,"No encontrada",2)} -> Media | I87: Continuidad operacional; Costo de reparación | J87: Sí | M87: No | O87: Sí | P87: Sí | U87: Tarea CBM programada | V87: Predictivo (basado en condición)
A88: F-MET-028 | B88: Bomba hidráulica (×4) · B0700 | C88: {=INDEX(Funciones!$G$2:$G$372,MATCH($A88,Funciones!$B$2:$B$372,0))} -> Generar presión hidráulica [ESTÁNDAR POR CONFIRMAR] | D88: No genera presión hidráulica. La función se pierde por completo: no se cumple ningún punto del estándar. Estándar: por confirmar. Se verifica con: manómetro. | E88: A. Manguera hidráulica reventada por fatiga de la malla | F88: 1. Local: La manguera hidráulica se revienta por la fatiga de su malla de refuerzo y el aceite sale a presión por la rotura. 2. En el equipo: El circuito pierde la presión y el aceite se derrama. El manómetro hidráulico marca cero y el actuador no se mueve. Además, hay derrame de aceite en la vía. 3. General: La máquina no ejecuta los movimientos hidráulicos y queda fuera de servicio. | G88: Grietas, resequedad, abultamientos o rozaduras visibles de la manguera hidráulica. Se detecta con: inspección visual. | H88: {=_xlfn.XLOOKUP(E:E,'Calificación consecuencia'!B:B,'Calificación consecuencia'!K:K,"No encontrada",2)} -> Baja | I88: Continuidad operacional | J88: Sí | M88: No | O88: No | S88: No | U88: Sin mantenimiento proactivo programado (operar hasta la falla) | V88: Correctivo (operar hasta la falla)
A89: F-MET-028 | B89: Bomba hidráulica (×4) · B0700 | C89: {=INDEX(Funciones!$G$2:$G$372,MATCH($A89,Funciones!$B$2:$B$372,0))} -> Generar presión hidráulica [ESTÁNDAR POR CONFIRMAR] | D89: Genera presión hidráulica por debajo de la presión de trabajo. Estándar: por confirmar. Se verifica con: manómetro. | E89: B. Bomba hidráulica desgastada por holguras internas | F89: 1. Local: Las holguras internas de la bomba aumentan por el desgaste y el caudal efectivo baja. 2. En el equipo: El circuito no alcanza la presión de trabajo. El manómetro no alcanza la presión de trabajo y el actuador pierde fuerza. 3. General: Los movimientos hidráulicos se hacen con menor fuerza y los ciclos se alargan. | G89: Pérdida progresiva de material de la bomba hidráulica hasta acercarse al límite de desgaste. Se detecta con: medición con calibre, galga o micrómetro; inspección visual. | H89: {=_xlfn.XLOOKUP(E:E,'Calificación consecuencia'!B:B,'Calificación consecuencia'!K:K,"No encontrada",2)} -> Baja | I89: Continuidad operacional; Costo de reparación | J89: Sí | M89: No | O89: Sí | P89: Sí | U89: Tarea CBM programada | V89: Predictivo (basado en condición)
A90: F-MET-028 | B90: Bomba hidráulica (×4) · B0700 | C90: {=INDEX(Funciones!$G$2:$G$372,MATCH($A90,Funciones!$B$2:$B$372,0))} -> Generar presión hidráulica [ESTÁNDAR POR CONFIRMAR] | D90: Genera presión hidráulica por debajo de la presión de trabajo. Estándar: por confirmar. Se verifica con: manómetro. | E90: B. Válvula de alivio descalibrada por resorte asentado | F90: 1. Local: El resorte de la válvula de alivio se asienta y la válvula abre a una presión menor a la de trabajo. 2. En el equipo: Parte del aceite se desvía al tanque antes de alcanzar la presión de trabajo. El manómetro no alcanza la presión de trabajo y el actuador pierde fuerza. 3. General: Los movimientos hidráulicos se hacen con menor fuerza y los ciclos se alargan. | G90: Deriva de la válvula de alivio frente al valor patrón, con lecturas o ajustes que se van corriendo. Se detecta con: verificación contra patrón calibrado; lectura de parámetros; medición de alineación o vibración. | H90: {=_xlfn.XLOOKUP(E:E,'Calificación consecuencia'!B:B,'Calificación consecuencia'!K:K,"No encontrada",2)} -> Baja | I90: Continuidad operacional | J90: Sí | M90: No | O90: No | S90: No | U90: Sin mantenimiento proactivo programado (operar hasta la falla) | V90: Correctivo (operar hasta la falla)
A91: F-MET-028 | B91: Bomba hidráulica (×4) · B0700 | C91: {=INDEX(Funciones!$G$2:$G$372,MATCH($A91,Funciones!$B$2:$B$372,0))} -> Generar presión hidráulica [ESTÁNDAR POR CONFIRMAR] | D91: Genera presión hidráulica por debajo de la presión de trabajo. Estándar: por confirmar. Se verifica con: manómetro. | E91: B. Válvula reguladora inestable por resorte fatigado | F91: 1. Local: El resorte de la válvula reguladora se fatiga y la válvula no mantiene su posición. 2. En el equipo: La presión del circuito sube y baja. La presión oscila y los movimientos son bruscos. 3. General: Los movimientos hidráulicos se hacen con tirones y el trabajo pierde precisión. | G91: Deriva de la válvula reguladora frente al valor patrón, con lecturas o ajustes que se van corriendo. Se detecta con: verificación contra patrón calibrado; lectura de parámetros; medición de alineación o vibración. | H91: {=_xlfn.XLOOKUP(E:E,'Calificación consecuencia'!B:B,'Calificación consecuencia'!K:K,"No encontrada",2)} -> Baja | I91: Continuidad operacional | J91: Sí | M91: No | O91: No | S91: No | U91: Sin mantenimiento proactivo programado (operar hasta la falla) | V91: Correctivo (operar hasta la falla)
A92: F-MET-028 | B92: Bomba hidráulica (×4) · B0700 | C92: {=INDEX(Funciones!$G$2:$G$372,MATCH($A92,Funciones!$B$2:$B$372,0))} -> Generar presión hidráulica [ESTÁNDAR POR CONFIRMAR] | D92: Genera presión hidráulica por encima de la presión de trabajo. Estándar: por confirmar. Se verifica con: manómetro. | E92: C. Válvula de alivio atascada por contaminación del asiento | F92: 1. Local: La válvula de alivio se atasca por contaminación del asiento y no abre cuando la presión llega al valor de tarado. 2. En el equipo: La presión del circuito sube por encima de la presión de trabajo. El manómetro supera la presión de trabajo y se escuchan golpes en la línea. Además, las mangueras y los sellos soportan una presión mayor a la de diseño. 3. General: El sistema hidráulico trabaja con sobrepresión y se acelera el desgaste de mangueras y sellos. | G92: Respuesta más lenta o movimiento duro de la válvula de alivio antes de quedar trabado. Se detecta con: prueba funcional; medición de tiempos de ciclo. | H92: {=_xlfn.XLOOKUP(E:E,'Calificación consecuencia'!B:B,'Calificación consecuencia'!K:K,"No encontrada",2)} -> Baja | I92: Continuidad operacional | J92: Sí | M92: No | O92: No | S92: No | U92: Sin mantenimiento proactivo programado (operar hasta la falla) | V92: Correctivo (operar hasta la falla)
A93: F-MET-029 | B93: Bomba Manual · B0700 | C93: {=INDEX(Funciones!$G$2:$G$372,MATCH($A93,Funciones!$B$2:$B$372,0))} -> Suministrar caudal de emergencia [ESTÁNDAR POR CONFIRMAR] | D93: No suministra caudal de emergencia. La función se pierde por completo: no se cumple ningún punto del estándar. Estándar: por confirmar. Se verifica con: prueba funcional de la bomba manual. | E93: A. Bomba manual trabada por corrosión del émbolo | F93: 1. Local: El émbolo de la bomba manual se corroe y queda trabado dentro del cilindro. 2. En el equipo: La bomba manual no desplaza aceite. No se nota en servicio; se descubre al probar la bomba de emergencia. 3. General: El circuito no recibe caudal de emergencia cuando se requiere. | G93: Movimiento duro, ruido o calentamiento anormal de la bomba manual antes de trabarse. Se detecta con: análisis de vibraciones; termografía; análisis de partículas en el aceite. Al ser una función oculta no se nota en operación: depende de la inspección o prueba programada. | H93: {=_xlfn.XLOOKUP(E:E,'Calificación consecuencia'!B:B,'Calificación consecuencia'!K:K,"No encontrada",2)} -> Baja | I93: Continuidad operacional; Seguridad | J93: No | K93: Sí | U93: Tarea de búsqueda de falla programada | V93: Detectivo (búsqueda de falla)
A94: F-MET-029 | B94: Bomba Manual · B0700 | C94: {=INDEX(Funciones!$G$2:$G$372,MATCH($A94,Funciones!$B$2:$B$372,0))} -> Suministrar caudal de emergencia [ESTÁNDAR POR CONFIRMAR] | D94: No suministra caudal de emergencia. La función se pierde por completo: no se cumple ningún punto del estándar. Estándar: por confirmar. Se verifica con: prueba funcional de la bomba manual. | E94: A. Motor de la bomba de emergencia quemado por humedad en el bobinado | F94: 1. Local: La humedad entra al bobinado del motor de la bomba de emergencia y lo quema. 2. En el equipo: El motor no gira y la bomba no mueve aceite. No se nota en servicio; se descubre al probar la bomba de emergencia. 3. General: El circuito no recibe caudal de emergencia cuando se requiere. | G94: Aumento de temperatura, de consumo de corriente o caída de la resistencia de aislamiento del motor de la bomba de emergencia. Se detecta con: termografía; medición de corriente; prueba de aislamiento (megóhmetro). Al ser una función oculta no se nota en operación: depende de la inspección o prueba programada. | H94: {=_xlfn.XLOOKUP(E:E,'Calificación consecuencia'!B:B,'Calificación consecuencia'!K:K,"No encontrada",2)} -> Baja | I94: Continuidad operacional; Seguridad | J94: No | K94: Sí | U94: Tarea de búsqueda de falla programada | V94: Detectivo (búsqueda de falla)
A95: F-MET-029 | B95: Bomba Manual · B0700 | C95: {=INDEX(Funciones!$G$2:$G$372,MATCH($A95,Funciones!$B$2:$B$372,0))} -> Suministrar caudal de emergencia [ESTÁNDAR POR CONFIRMAR] | D95: No suministra caudal de emergencia. La función se pierde por completo: no se cumple ningún punto del estándar. Estándar: por confirmar. Se verifica con: prueba funcional de la bomba manual. | E95: A. Batería de emergencia descargada por fin de vida útil | F95: 1. Local: La batería de emergencia llega al final de su vida útil y no mantiene carga. 2. En el equipo: El motor de la bomba de emergencia no recibe tensión. No se nota en servicio; se descubre al probar la bomba de emergencia. 3. General: El circuito no recibe caudal de emergencia cuando se requiere. | G95: Caída gradual de la tensión y de la capacidad de la batería de emergencia. Se detecta con: prueba de carga; medición de tensión en reposo y bajo carga. Al ser una función oculta no se nota en operación: depende de la inspección o prueba programada. | H95: {=_xlfn.XLOOKUP(E:E,'Calificación consecuencia'!B:B,'Calificación consecuencia'!K:K,"No encontrada",2)} -> Baja | I95: Seguridad; Continuidad operacional | J95: No | K95: Sí | U95: Tarea de búsqueda de falla programada | V95: Detectivo (búsqueda de falla)
A96: F-MET-029 | B96: Bomba Manual · B0700 | C96: {=INDEX(Funciones!$G$2:$G$372,MATCH($A96,Funciones!$B$2:$B$372,0))} -> Suministrar caudal de emergencia [ESTÁNDAR POR CONFIRMAR] | D96: Suministra caudal de emergencia por debajo del requerido en emergencia. Estándar: por confirmar. Se verifica con: prueba funcional de la bomba manual. | E96: B. Sellos de la bomba manual desgastados por fin de vida útil | F96: 1. Local: Los sellos de la bomba manual se desgastan y dejan pasar aceite internamente. 2. En el equipo: La bomba entrega menos caudal por cada carrera. La bomba entrega menos caudal del necesario en la prueba. 3. General: El caudal de emergencia queda por debajo del requerido y los movimientos de emergencia se hacen más lentos. | G96: Sudoración, humedad, resequedad o rozaduras visibles de los sellos de la bomba manual. Se detecta con: inspección visual; prueba de estanqueidad. Al ser una función oculta no se nota en operación: depende de la inspección o prueba programada. | H96: {=_xlfn.XLOOKUP(E:E,'Calificación consecuencia'!B:B,'Calificación consecuencia'!K:K,"No encontrada",2)} -> Baja | I96: Continuidad operacional; Costo de reparación | J96: No | K96: Sí | U96: Tarea de búsqueda de falla programada | V96: Detectivo (búsqueda de falla)
A97: F-MET-029 | B97: Bomba Manual · B0700 | C97: {=INDEX(Funciones!$G$2:$G$372,MATCH($A97,Funciones!$B$2:$B$372,0))} -> Suministrar caudal de emergencia [ESTÁNDAR POR CONFIRMAR] | D97: Suministra caudal de emergencia por debajo del requerido en emergencia. Estándar: por confirmar. Se verifica con: prueba funcional de la bomba manual. | E97: B. Filtro de la bomba de emergencia obstruido por suciedad | F97: 1. Local: El filtro de la bomba de emergencia se obstruye con suciedad y restringe la entrada de aceite. 2. En el equipo: La bomba aspira con dificultad y entrega menos caudal. La bomba entrega menos caudal del necesario en la prueba. 3. General: El caudal de emergencia queda por debajo del requerido y los movimientos de emergencia se hacen más lentos. | G97: Aumento de la presión diferencial o caída del caudal por acumulación de suciedad del filtro de la bomba de emergencia. Se detecta con: lectura de manómetros y diferencial de presión; medición de caudal; inspección visual. Al ser una función oculta no se nota en operación: depende de la inspección o prueba programada. | H97: {=_xlfn.XLOOKUP(E:E,'Calificación consecuencia'!B:B,'Calificación consecuencia'!K:K,"No encontrada",2)} -> Media | I97: Continuidad operacional; Costo de reparación | J97: No | K97: Sí | U97: Tarea de búsqueda de falla programada | V97: Detectivo (búsqueda de falla)
A98: F-MET-031 | B98: Compresor A/C Hidráulico · B0700 | C98: {=INDEX(Funciones!$G$2:$G$372,MATCH($A98,Funciones!$B$2:$B$372,0))} -> Suministrar caudal de aire [ESTÁNDAR POR CONFIRMAR] | D98: No suministra caudal de aire. La función se pierde por completo: no se cumple ningún punto del estándar. Estándar: por confirmar. Se verifica con: tiempo de llenado de calderines. | E98: A. Motor del compresor quemado por sobrecarga eléctrica | F98: 1. Local: El motor del compresor se quema por sobrecarga eléctrica y deja de girar. 2. En el equipo: El compresor no comprime aire. El manómetro no sube al arrancar y el compresor no carga. 3. General: El vehículo queda sin aire comprimido para sus sistemas neumáticos. | G98: Aumento de temperatura, de consumo de corriente o caída de la resistencia de aislamiento del motor del compresor. Se detecta con: termografía; medición de corriente; prueba de aislamiento (megóhmetro). | H98: {=_xlfn.XLOOKUP(E:E,'Calificación consecuencia'!B:B,'Calificación consecuencia'!K:K,"No encontrada",2)} -> Media | I98: Continuidad operacional; Costo de reparación | J98: Sí | M98: Sí | N98: Sí | U98: Tarea proactiva obligatoria: basada en condición (CBM) | V98: Predictivo (basado en condición)
A99: F-MET-031 | B99: Compresor A/C Hidráulico · B0700 | C99: {=INDEX(Funciones!$G$2:$G$372,MATCH($A99,Funciones!$B$2:$B$372,0))} -> Suministrar caudal de aire [ESTÁNDAR POR CONFIRMAR] | D99: No suministra caudal de aire. La función se pierde por completo: no se cumple ningún punto del estándar. Estándar: por confirmar. Se verifica con: tiempo de llenado de calderines. | E99: A. Correa del compresor rota por fatiga | F99: 1. Local: La correa del compresor se rompe por fatiga y el motor deja de arrastrar al compresor. 2. En el equipo: El compresor no gira. El manómetro no sube al arrancar y el compresor no carga. 3. General: El vehículo queda sin aire comprimido para sus sistemas neumáticos. | G99: Grietas, resequedad, abultamientos o rozaduras visibles de la correa del compresor. Se detecta con: inspección visual. | H99: {=_xlfn.XLOOKUP(E:E,'Calificación consecuencia'!B:B,'Calificación consecuencia'!K:K,"No encontrada",2)} -> Baja | I99: Costo de reparación; Seguridad | J99: Sí | M99: Sí | N99: Sí | U99: Tarea proactiva obligatoria: basada en condición (CBM) | V99: Predictivo (basado en condición)
A100: F-MET-031 | B100: Compresor A/C Hidráulico · B0700 | C100: {=INDEX(Funciones!$G$2:$G$372,MATCH($A100,Funciones!$B$2:$B$372,0))} -> Suministrar caudal de aire [ESTÁNDAR POR CONFIRMAR] | D100: No suministra caudal de aire. La función se pierde por completo: no se cumple ningún punto del estándar. Estándar: por confirmar. Se verifica con: tiempo de llenado de calderines. | E100: A. Compresor gripado por pérdida de la película lubricante | F100: 1. Local: El compresor se traba (se gripa) porque pierde la película de lubricante entre sus piezas móviles. 2. En el equipo: El compresor deja de girar y no comprime aire. El manómetro no sube al arrancar y el compresor no carga. 3. General: El vehículo queda sin aire comprimido para sus sistemas neumáticos. | G100: Movimiento duro, ruido o calentamiento anormal del compresor antes de trabarse. Se detecta con: análisis de vibraciones; termografía; análisis de partículas en el aceite. | H100: {=_xlfn.XLOOKUP(E:E,'Calificación consecuencia'!B:B,'Calificación consecuencia'!K:K,"No encontrada",2)} -> Media | I100: Continuidad operacional; Costo de reparación | J100: Sí | M100: Sí | N100: Sí | U100: Tarea proactiva obligatoria: basada en condición (CBM) | V100: Predictivo (basado en condición)
...

Sheet Calificación consecuencia
C1: 0.384 | D1: 0.18 | E1: 0.24 | F1: 0.096 | G1: 0.1
A2: ID FUNCIÓN | B2: MODO DE FALLA | C2: SEGURIDAD (1-4, peso 0,384) | D2: IMPACTO A LA OPERACIÓN (1-4, peso 0,18) | E2: CONTINUIDAD OPERACIONAL (1-4, peso 0,24) | F2: COSTO DE REPARACIÓN (1-4, peso 0,096) | G2: IMPACTO AMBIENTAL (1-4, peso 0,1) | H2: CONSECUENCIA PONDERADA | I2: PROBABILIDAD DE FALLA (1-4) | J2: ÍNDICE DE CRITICIDAD (consecuencia ponderada × probabilidad) | K2: CONSECUENCIA
A3: F-MET-001 | B3: A. Tren inmovilizado por disparo del breaker principal | C3: 2 | D3: 4 | E3: 4 | F3: 4 | G3: 1 | H3: =SUMPRODUCT(C3:G3,$C$1:$G$1) -> 2.932 | I3: 4 | J3: =H3*I3 -> 11.728 | K3: =IF(J3>14,"Muy Alta",IF(J3>10,"Alta",IF(J3>4,"Media","Baja"))) -> Alta
A4: F-MET-001 | B4: A. Tren inmovilizado por pérdida de presión en el circuito principal de aire | C4: 2 | D4: 4 | E4: 3 | F4: 1 | G4: 1 | H4: =SUMPRODUCT(C4:G4,$C$1:$G$1) -> 2.404 | I4: 2 | J4: =H4*I4 -> 4.808 | K4: =IF(J4>14,"Muy Alta",IF(J4>10,"Alta",IF(J4>4,"Media","Baja"))) -> Media
A5: F-MET-001 | B5: A. Coche dañado por impacto con un obstáculo en la vía | C5: 2 | D5: 4 | E5: 3 | F5: 3 | G5: 1 | H5: =SUMPRODUCT(C5:G5,$C$1:$G$1) -> 2.596 | I5: 2 | J5: =H5*I5 -> 5.192 | K5: =IF(J5>14,"Muy Alta",IF(J5>10,"Alta",IF(J5>4,"Media","Baja"))) -> Media
A6: F-MET-001 | B6: A. Módulo de potencia del convertidor disparado por ducto de aire obstruido | C6: 2 | D6: 4 | E6: 3 | F6: 1 | G6: 1 | H6: =SUMPRODUCT(C6:G6,$C$1:$G$1) -> 2.404 | I6: 2 | J6: =H6*I6 -> 4.808 | K6: =IF(J6>14,"Muy Alta",IF(J6>10,"Alta",IF(J6>4,"Media","Baja"))) -> Media
A7: F-MET-001 | B7: A. Contactos del breaker principal picados por arco eléctrico repetido | C7: 2 | D7: 4 | E7: 3 | F7: 3 | G7: 1 | H7: =SUMPRODUCT(C7:G7,$C$1:$G$1) -> 2.596 | I7: 2 | J7: =H7*I7 -> 5.192 | K7: =IF(J7>14,"Muy Alta",IF(J7>10,"Alta",IF(J7>4,"Media","Baja"))) -> Media
A8: F-MET-001 | B8: B. Coche aislado por puertas bloqueadas | C8: 1 | D8: 2 | E8: 3 | F8: 1 | G8: 1 | H8: =SUMPRODUCT(C8:G8,$C$1:$G$1) -> 1.66 | I8: 2 | J8: =H8*I8 -> 3.32 | K8: =IF(J8>14,"Muy Alta",IF(J8>10,"Alta",IF(J8>4,"Media","Baja"))) -> Baja
